Workbook

Sheet PG_Forward
A1: order_id | B1: order_line_id | C1: packing_date | D1: delivery_date | E1: sku_code | F1: seller_product_amount | G1: postpaid_amount | H1: prepaid_amount | I1: mrp | J1: total_discount_amount | K1: shipping_case | L1: total_tax_rate | M1: igst_amount | N1: cgst_amount | O1: sgst_amount | P1: tcs_amount | Q1: tds_amount | R1: commission_percentage | S1: platform_fees | T1: total_commission | U1: total_commission_plus_tcs_tds_deduction | V1: total_logistics_deduction | W1: shipping_fee | X1: fixed_fee | Y1: payment_gateway_fee | Z1: total_tax_on_logistics | AA1: article_level | AB1: shipment_zone_classification | AC1: customer_paid_amt | AD1: total_expected_settlement | AE1: total_actual_settlement | AF1: amount_pending_settlement | AG1: prepaid_commission_deduction | AH1: prepaid_logistics_deduction | AI1: prepaid_payment | AJ1: postpaid_commission_deduction | AK1: postpaid_logistics_deduction | AL1: postpaid_payment | AM1: settlement_date_prepaid_comm_deduction | AN1: settlement_date_prepaid_logistics_deduction | AO1: settlement_date_prepaid_payment | AP1: additional_amount | AQ1: taxable_amount | AR1: igst_rate | AS1: cgst_rate | AT1: sgst_rate | AU1: tcs_igst_rate | AV1: tcs_sgst_rate | AW1: tcs_cgst_rate | AX1: tds_rate | AY1: brand | AZ1: article_type | BA1: prepaid_commission_percentage | BB1: prepaid_minimum_commission | BC1: prepaid_platform_fees | BD1: prepaid_total_commission | BE1: prepaid_ship_commission_charge | BF1: prepaid_gift_commission_charge | BG1: prepaid_cod_commission_charge | BH1: prepaid_cart_discount | BI1: prepaid_coupon_discount | BJ1: postpaid_commission_percentage | BK1: postpaid_minimum_commission | BL1: postpaid_platform_fees | BM1: postpaid_total_commission | BN1: postpaid_ship_commission_charge | BO1: postpaid_gift_commission_charge | BP1: postpaid_cod_commission_charge | BQ1: postpaid_cart_discount | BR1: postpaid_coupon_discount | BS1: seller_order_id | BT1: tcs_amount_prepaid | BU1: tcs_amount_postpaid | BV1: tds_amount_prepaid | BW1: tds_amount_postpaid | BX1: Settlement_on_2025_10_03 | BY1: Settlement_on_2025_10_06 | BZ1: Settlement_on_2025_10_08 | CA1: Settlement_on_2025_10_09 | CB1: Settlement_on_2025_10_10 | CC1: Settlement_on_2025_10_13 | CD1: Settlement_on_2025_10_14 | CE1: Settlement_on_2025_10_15 | CF1: Settlement_on_2025_10_16 | CG1: Settlement_on_2025_10_17 | CH1: Settlement_on_2025_10_23 | CI1: Settlement_on_2025_10_24 | CJ1: Settlement_on_2025_10_27 | CK1: Settlement_on_2025_10_28 | CL1: Settlement_on_2025_10_29 | CM1: Settlement_on_2025_10_30 | CN1: SettlementOn16_ | CO1: SettlementOn17_ | CP1: SettlementOn18_ | CQ1: SettlementOn19_ | CR1: SettlementOn20_ | CS1: SettlementOn21_ | CT1: SettlementOn22_ | CU1: SettlementOn23_ | CV1: SettlementOn24_ | CW1: SettlementOn25_ | CX1: SettlementOn26_ | CY1: SettlementOn27_ | CZ1: SettlementOn28_ | DA1: SettlementOn29_ | DB1: SettlementOn30_ | DC1: Customer_Paid | DD1: Commission | DE1: Tax_On_Commission | DF1: Logistics | DG1: GST_taxes | DH1: Myntra_Settlement
A2: 8743896489 | B2: 10743901048 | C2: 45939.449 | D2: 45942.572 | E2: TIKICLST113026317 | F2: 2410 | G2: 2410 | H2: 0 | I2: 3500 | J2: 884 | K2: Inter-State | L2: 5 | M2: 114.76 | N2: 0 | O2: 0 | P2: 11.476 | Q2: 2.295 | R2: 24.78 | S2: 597.198 | T2: -597.198 | U2: -610.969 | V2: -71.98 | W2: 0 | X2: 61 | Y2: 0 | Z2: 10.98 | AA2: 1 | AB2: ZONAL | AC2: 2616 | AD2: 1727.051 | AE2: 1727.051 | AF2: 0 | AG2: 0 | AI2: 0 | AJ2: -610.969 | AK2: -71.98 | AL2: 2410 | AP2: 0 | AQ2: 2295.24 | AR2: 5 | AS2: 0 | AT2: 0 | AU2: 0.5 | AV2: 0 | AW2: 0 | AX2: 0.1 | AY2: Tiny Kingdom | AZ2: Clothing Set | BC2: 0 | BD2: 0 | BE2: 0 | BF2: 0 | BG2: 0 | BJ2: 24.78 | BK2: 0 | BL2: 597.198 | BM2: -597.198 | BN2: 0 | BO2: 0 | BP2: 0 | BQ2: 884 | BR2: 2.29524 | BS2: aa6d8459-4827-4236-b8a7-a81eef5aaf11 | BT2: 0 | BU2: 11.476 | BV2: 0 | BW2: 2.295 | BX2: 0 | BY2: 0 | BZ2: 0 | CA2: 0 | CB2: 0 | CC2: 0 | CD2: 0 | CE2: 0 | CF2: 0 | CG2: 0 | CH2: 0 | CI2: 0 | CJ2: 1727.051 | CK2: 0 | CL2: 0 | CM2: 0 | CN2: 0 | CO2: 0 | CP2: 0 | CQ2: 0 | CR2: 0 | CS2: 0 | CT2: 0 | CU2: 0 | CV2: 0 | CW2: 0 | CX2: 0 | CY2: 0 | CZ2: 0 | DA2: 0 | DB2: 0 | DC2: =IFERROR(G2,0)+IFERROR(H2,0) -> 2410 | DD2: =ABS(IFERROR(T2,0)) -> 597.198 | DE2: =ABS(IFERROR(P2,0)+IFERROR(Q2,0)) -> 13.771 | DF2: =ABS(IFERROR(AH2,0))+ABS(IFERROR(AK2,0))+IFERROR(W2,0) -> 71.98 | DG2: =IFERROR(M2,0)+IFERROR(N2,0)+IFERROR(O2,0)+IFERROR(P2,0) -> 126.236 | DH2: 1727.051
A3: 8746383853 | B3: 10746400495 | C3: 45940.808 | D3: 45946.475 | E3: TIKILHNC118421496 | F3: 2385 | G3: 0 | H3: 2385 | I3: 3000 | J3: 385 | K3: Inter-State | L3: 5 | M3: 113.57 | N3: 0 | O3: 0 | P3: 11.357 | Q3: 2.271 | R3: 17.7 | S3: 422.145 | T3: -422.145 | U3: -435.773 | V3: -71.98 | W3: 0 | X3: 61 | Y3: 0 | Z3: 10.98 | AA3: 2 | AB3: NATIONAL | AC3: 2615 | AD3: 1877.247 | AE3: 1877.247 | AF3: 0 | AG3: -435.773 | AH3: -71.98 | AI3: 2385 | AJ3: 0 | AL3: 0 | AM3: 45960 | AN3: 45960 | AO3: 45960 | AP3: 0 | AQ3: 2271.43 | AR3: 5 | AS3: 0 | AT3: 0 | AU3: 0.5 | AV3: 0 | AW3: 0 | AX3: 0.1 | AY3: Tiny Kingdom | AZ3: Sarees | BA3: 17.7 | BB3: 0 | BC3: 422.145 | BD3: -422.145 | BE3: 0 | BF3: 0 | BG3: 0 | BH3: 385 | BI3: 2.27143 | BL3: 0 | BM3: 0 | BN3: 0 | BO3: 0 | BP3: 0 | BS3: 498b0126-4b67-44e1-9f5c-40372d11a4b3 | BT3: 11.357 | BU3: 0 | BV3: 2.271 | BW3: 0 | BX3: 0 | BY3: 0 | BZ3: 0 | CA3: 0 | CB3: 0 | CC3: 0 | CD3: 0 | CE3: 0 | CF3: 0 | CG3: 0 | CH3: 0 | CI3: 0 | CJ3: 0 | CK3: 0 | CL3: 0 | CM3: 1877.247 | CN3: 0 | CO3: 0 | CP3: 0 | CQ3: 0 | CR3: 0 | CS3: 0 | CT3: 0 | CU3: 0 | CV3: 0 | CW3: 0 | CX3: 0 | CY3: 0 | CZ3: 0 | DA3: 0 | DB3: 0 | DC3: =IFERROR(G3,0)+IFERROR(H3,0) -> 2385 | DD3: =ABS(IFERROR(T3,0)) -> 422.145 | DE3: =ABS(IFERROR(P3,0)+IFERROR(Q3,0)) -> 13.628 | DF3: =ABS(IFERROR(AH3,0))+ABS(IFERROR(AK3,0))+IFERROR(W3,0) -> 71.98 | DG3: =IFERROR(M3,0)+IFERROR(N3,0)+IFERROR(O3,0)+IFERROR(P3,0) -> 124.927 | DH3: 1877.247
A4: 8725799225 | B4: 10725751253 | C4: 45931.8 | D4: 45936.447 | E4: TNBYCLST101412227 | F4: 2556 | G4: 0 | H4: 2556 | I4: 3250 | J4: 488 | K4: Intra-State | L4: 5 | M4: 0 | N4: 60.86 | O4: 60.86 | P4: 12.171 | Q4: 2.434 | R4: 25.96 | S4: 663.538 | T4: -663.538 | U4: -678.143 | V4: -71.98 | W4: 0 | X4: 61 | Y4: 0 | Z4: 10.98 | AA4: 1 | AB4: ZONAL | AC4: 2762 | AD4: 1805.877 | AE4: 1805.877 | AF4: 0 | AG4: -678.143 | AH4: -71.98 | AI4: 2556 | AJ4: 0 | AL4: 0 | AM4: 45953 | AN4: 45953 | AO4: 45953 | AP4: 0 | AQ4: 2434.28 | AR4: 0 | AS4: 2.5 | AT4: 2.5 | AU4: 0 | AV4: 0.25 | AW4: 0.25 | AX4: 0.1 | AY4: Tiny Baby | AZ4: Clothing Set | BA4: 25.96 | BB4: 0 | BC4: 663.538 | BD4: -663.538 | BE4: 0 | BF4: 0 | BG4: 0 | BH4: 488 | BI4: 2.43428 | BL4: 0 | BM4: 0 | BN4: 0 | BO4: 0 | BP4: 0 | BS4: a7ad35a9-eb5c-41c7-8007-586d66487e24 | BT4: 12.171 | BU4: 0 | BV4: 2.434 | BW4: 0 | BX4: 0 | BY4: 0 | BZ4: 0 | CA4: 0 | CB4: 0 | CC4: 0 | CD4: 0 | CE4: 0 | CF4: 0 | CG4: 0 | CH4: 1805.877 | CI4: 0 | CJ4: 0 | CK4: 0 | CL4: 0 | CM4: 0 | CN4: 0 | CO4: 0 | CP4: 0 | CQ4: 0 | CR4: 0 | CS4: 0 | CT4: 0 | CU4: 0 | CV4: 0 | CW4: 0 | CX4: 0 | CY4: 0 | CZ4: 0 | DA4: 0 | DB4: 0 | DC4: =IFERROR(G4,0)+IFERROR(H4,0) -> 2556 | DD4: =ABS(IFERROR(T4,0)) -> 663.538 | DE4: =ABS(IFERROR(P4,0)+IFERROR(Q4,0)) -> 14.605 | DF4: =ABS(IFERROR(AH4,0))+ABS(IFERROR(AK4,0))+IFERROR(W4,0) -> 71.98 | DG4: =IFERROR(M4,0)+IFERROR(N4,0)+IFERROR(O4,0)+IFERROR(P4,0) -> 133.891 | DH4: 1805.877
A5: 8718239977 | B5: 10718182238 | C5: 45930.615 | D5: 45934.859 | E5: TIKILHNC115963260 | F5: 3789 | G5: 0 | H5: 3788.99 | I5: 4250 | J5: 255 | K5: Inter-State | L5: 18 | M5: 577.98 | N5: 0 | O5: 0 | P5: 16.055 | Q5: 3.211 | R5: 24.78 | S5: 938.912 | T5: -938.912 | U5: -958.178 | V5: -71.98 | W5: 0 | X5: 61 | Y5: 0 | Z5: 10.98 | AA5: 1 | AB5: ZONAL | AC5: 3995 | AD5: 2758.832 | AE5: 2758.832 | AF5: 0 | AG5: -958.178 | AH5: -71.98 | AI5: 3788.99 | AJ5: 0 | AL5: 0 | AM5: 45953 | AN5: 45953 | AO5: 45953 | AP5: 0 | AQ5: 3211.02 | AR5: 18 | AS5: 0 | AT5: 0 | AU5: 0.5 | AV5: 0 | AW5: 0 | AX5: 0.1 | AY5: Tiny Kingdom | AZ5: Lehenga Choli | BA5: 24.78 | BB5: 0 | BC5: 938.912 | BD5: -938.912 | BE5: 0 | BF5: 0 | BG5: 0 | BH5: 255 | BI5: 3.21102 | BL5: 0 | BM5: 0 | BN5: 0 | BO5: 0 | BP5: 0 | BS5: 3136d9a9-9225-499d-8a5e-3fb44a352e77 | BT5: 16.055 | BU5: 0 | BV5: 3.211 | BW5: 0 | BX5: 0 | BY5: 0 | BZ5: 0 | CA5: 0 | CB5: 0 | CC5: 0 | CD5: 0 | CE5: 0 | CF5: 0 | CG5: 0 | CH5: 2758.832 | CI5: 0 | CJ5: 0 | CK5: 0 | CL5: 0 | CM5: 0 | CN5: 0 | CO5: 0 | CP5: 0 | CQ5: 0 | CR5: 0 | CS5: 0 | CT5: 0 | CU5: 0 | CV5: 0 | CW5: 0 | CX5: 0 | CY5: 0 | CZ5: 0 | DA5: 0 | DB5: 0 | DC5: =IFERROR(G5,0)+IFERROR(H5,0) -> 3788.99 | DD5: =ABS(IFERROR(T5,0)) -> 938.912 | DE5: =ABS(IFERROR(P5,0)+IFERROR(Q5,0)) -> 19.266 | DF5: =ABS(IFERROR(AH5,0))+ABS(IFERROR(AK5,0))+IFERROR(W5,0) -> 71.98 | DG5: =IFERROR(M5,0)+IFERROR(N5,0)+IFERROR(O5,0)+IFERROR(P5,0) -> 594.035 | DH5: 2758.832
A6: 8752499712 | B6: 10752538871 | C6: 45943.449 | D6: 45946.55 | E6: BETYDRSS77160920 | F6: 2150 | G6: 0 | H6: 2150 | I6: 5500 | J6: 3144 | K6: Inter-State | L6: 5 | M6: 102.38 | N6: 0 | O6: 0 | P6: 10.238 | Q6: 2.048 | R6: 31.86 | S6: 684.99 | T6: -684.99 | U6: -697.276 | V6: -71.98 | W6: 0 | X6: 61 | Y6: 0 | Z6: 10.98 | AA6: 1 | AB6: ZONAL | AC6: 2356 | AD6: 1380.744 | AE6: 1380.744 | AF6: 0 | AG6: -697.276 | AH6: -71.98 | AI6: 2150 | AJ6: 0 | AL6: 0 | AM6: 45960 | AN6: 45960 | AO6: 45960 | AP6: 0 | AQ6: 2047.62 | AR6: 5 | AS6: 0 | AT6: 0 | AU6: 0.5 | AV6: 0 | AW6: 0 | AX6: 0.1 | AY6: BETTY | AZ6: Dresses | BA6: 31.86 | BB6: 0 | BC6: 684.99 | BD6: -684.99 | BE6: 0 | BF6: 0 | BG6: 0 | BH6: 3144 | BI6: 2.04762 | BL6: 0 | BM6: 0 | BN6: 0 | BO6: 0 | BP6: 0 | BS6: 345d8774-a51e-42c7-b137-0272cd9ee960 | BT6: 10.238 | BU6: 0 | BV6: 2.048 | BW6: 0 | BX6: 0 | BY6: 0 | BZ6: 0 | CA6: 0 | CB6: 0 | CC6: 0 | CD6: 0 | CE6: 0 | CF6: 0 | CG6: 0 | CH6: 0 | CI6: 0 | CJ6: 0 | CK6: 0 | CL6: 0 | CM6: 1380.744 | CN6: 0 | CO6: 0 | CP6: 0 | CQ6: 0 | CR6: 0 | CS6: 0 | CT6: 0 | CU6: 0 | CV6: 0 | CW6: 0 | CX6: 0 | CY6: 0 | CZ6: 0 | DA6: 0 | DB6: 0 | DC6: =IFERROR(G6,0)+IFERROR(H6,0) -> 2150 | DD6: =ABS(IFERROR(T6,0)) -> 684.99 | DE6: =ABS(IFERROR(P6,0)+IFERROR(Q6,0)) -> 12.286 | DF6: =ABS(IFERROR(AH6,0))+ABS(IFERROR(AK6,0))+IFERROR(W6,0) -> 71.98 | DG6: =IFERROR(M6,0)+IFERROR(N6,0)+IFERROR(O6,0)+IFERROR(P6,0) -> 112.618 | DH6: 1380.744
A7: 8727502935 | B7: 10727456914 | C7: 45933.481 | D7: 45935.695 | E7: TIKIDRSS113553908 | F7: 3119 | G7: 3119 | H7: 0 | I7: 3500 | J7: 175 | K7: Intra-State | L7: 18 | M7: 0 | N7: 237.89 | O7: 237.89 | P7: 13.216 | Q7: 2.643 | R7: 21.24 | S7: 662.476 | T7: -662.476 | U7: -678.335 | V7: -71.98 | W7: 0 | X7: 61 | Y7: 0 | Z7: 10.98 | AA7: 1 | AB7: LOCAL | AC7: 3325 | AD7: 2368.685 | AE7: 2368.685 | AF7: 0 | AG7: 0 | AI7: 0 | AJ7: -678.335 | AK7: -71.98 | AL7: 3119 | AP7: 0 | AQ7: 2643.22 | AR7: 0 | AS7: 9 | AT7: 9 | AU7: 0 | AV7: 0.25 | AW7: 0.25 | AX7: 0.1 | AY7: Tiny Kingdom | AZ7: Dresses | BC7: 0 | BD7: 0 | BE7: 0 | BF7: 0 | BG7: 0 | BJ7: 21.24 | BK7: 0 | BL7: 662.476 | BM7: -662.476 | BN7: 0 | BO7: 0 | BP7: 0 | BQ7: 175 | BR7: 2.64322 | BS7: 4fb2c573-ee87-49ef-a5e5-dc738d4bf435 | BT7: 0 | BU7: 13.216 | BV7: 0 | BW7: 2.643 | BX7: 0 | BY7: 0 | BZ7: 0 | CA7: 0 | CB7: 0 | CC7: 0 | CD7: 0 | CE7: 0 | CF7: 0 | CG7: 0 | CH7: 2368.685 | CI7: 0 | CJ7: 0 | CK7: 0 | CL7: 0 | CM7: 0 | CN7: 0 | CO7: 0 | CP7: 0 | CQ7: 0 | CR7: 0 | CS7: 0 | CT7: 0 | CU7: 0 | CV7: 0 | CW7: 0 | CX7: 0 | CY7: 0 | CZ7: 0 | DA7: 0 | DB7: 0 | DC7: =IFERROR(G7,0)+IFERROR(H7,0) -> 3119 | DD7: =ABS(IFERROR(T7,0)) -> 662.476 | DE7: =ABS(IFERROR(P7,0)+IFERROR(Q7,0)) -> 15.859 | DF7: =ABS(IFERROR(AH7,0))+ABS(IFERROR(AK7,0))+IFERROR(W7,0) -> 71.98 | DG7: =IFERROR(M7,0)+IFERROR(N7,0)+IFERROR(O7,0)+IFERROR(P7,0) -> 488.996 | DH7: 2368.685
A8: 8663926203 | B8: 10663850265 | C8: 45912.803 | D8: 45916.753 | E8: TIKIDRSS97455131 | F8: 1454 | G8: 1454 | H8: 0 | I8: 3250 | J8: 1625 | K8: Inter-State | L8: 12 | M8: 155.79 | N8: 0 | O8: 0 | P8: 6.491 | Q8: 1.298 | R8: 22.42 | S8: 325.987 | T8: -325.987 | U8: -333.776 | V8: -53.1 | W8: 0 | X8: 45 | Y8: 0 | Z8: 8.1 | AA8: 1 | AB8: NATIONAL | AC8: 1625 | AD8: 1067.124 | AE8: 1067.124 | AF8: 0 | AG8: 0 | AI8: 0 | AJ8: -333.776 | AK8: -53.1 | AL8: 1454 | AP8: 0 | AQ8: 1298.21 | AR8: 12 | AS8: 0 | AT8: 0 | AU8: 0.5 | AV8: 0 | AW8: 0 | AX8: 0.1 | AY8: Tiny Kingdom | AZ8: Dresses | BC8: 0 | BD8: 0 | BE8: 0 | BF8: 0 | BG8: 0 | BJ8: 22.42 | BK8: 0 | BL8: 325.987 | BM8: -325.987 | BN8: 0 | BO8: 0 | BP8: 0 | BQ8: 1625 | BR8: 1.29821 | BS8: 020eb887-9733-4981-833d-54a0cda5413d | BT8: 0 | BU8: 6.491 | BV8: 0 | BW8: 1.298 | BX8: 1067.124 | BY8: 0 | BZ8: 0 | CA8: 0 | CB8: 0 | CC8: 0 | CD8: 0 | CE8: 0 | CF8: 0 | CG8: 0 | CH8: 0 | CI8: 0 | CJ8: 0 | CK8: 0 | CL8: 0 | CM8: 0 | CN8: 0 | CO8: 0 | CP8: 0 | CQ8: 0 | CR8: 0 | CS8: 0 | CT8: 0 | CU8: 0 | CV8: 0 | CW8: 0 | CX8: 0 | CY8: 0 | CZ8: 0 | DA8: 0 | DB8: 0 | DC8: =IFERROR(G8,0)+IFERROR(H8,0) -> 1454 | DD8: =ABS(IFERROR(T8,0)) -> 325.987 | DE8: =ABS(IFERROR(P8,0)+IFERROR(Q8,0)) -> 7.789 | DF8: =ABS(IFERROR(AH8,0))+ABS(IFERROR(AK8,0))+IFERROR(W8,0) -> 53.1 | DG8: =IFERROR(M8,0)+IFERROR(N8,0)+IFERROR(O8,0)+IFERROR(P8,0) -> 162.281 | DH8: 1067.124
A9: 8689247485 | B9: 10689175468 | C9: 45922.443 | D9: 45926.408 | E9: TIKICLST112314232 | F9: 3564 | G9: 0 | H9: 3564 | I9: 4000 | J9: 230 | K9: Inter-State | L9: 18 | M9: 543.66 | N9: 0 | O9: 0 | P9: 15.102 | Q9: 3.02 | R9: 24.78 | S9: 883.159 | T9: -883.159 | U9: -901.281 | V9: -71.98 | W9: 0 | X9: 61 | Y9: 0 | Z9: 10.98 | AA9: 1 | AB9: NATIONAL | AC9: 3770 | AD9: 2590.739 | AE9: 2590.739 | AF9: 0 | AG9: -901.281 | AH9: -71.98 | AI9: 3564 | AJ9: 0 | AL9: 0 | AM9: 45940 | AN9: 45940 | AO9: 45940 | AP9: 0 | AQ9: 3020.34 | AR9: 18 | AS9: 0 | AT9: 0 | AU9: 0.5 | AV9: 0 | AW9: 0 | AX9: 0.1 | AY9: Tiny Kingdom | AZ9: Clothing Set | BA9: 24.78 | BB9: 0 | BC9: 883.159 | BD9: -883.159 | BE9: 0 | BF9: 0 | BG9: 0 | BH9: 230 | BI9: 3.02034 | BL9: 0 | BM9: 0 | BN9: 0 | BO9: 0 | BP9: 0 | BS9: ef20eac0-eb9e-4fa8-9c55-50cc8c975f8d | BT9: 15.102 | BU9: 0 | BV9: 3.02 | BW9: 0 | BX9: 0 | BY9: 0 | BZ9: 0 | CA9: 0 | CB9: 2590.739 | CC9: 0 | CD9: 0 | CE9: 0 | CF9: 0 | CG9: 0 | CH9: 0 | CI9: 0 | CJ9: 0 | CK9: 0 | CL9: 0 | CM9: 0 | CN9: 0 | CO9: 0 | CP9: 0 | CQ9: 0 | CR9: 0 | CS9: 0 | CT9: 0 | CU9: 0 | CV9: 0 | CW9: 0 | CX9: 0 | CY9: 0 | CZ9: 0 | DA9: 0 | DB9: 0 | DC9: =IFERROR(G9,0)+IFERROR(H9,0) -> 3564 | DD9: =ABS(IFERROR(T9,0)) -> 883.159 | DE9: =ABS(IFERROR(P9,0)+IFERROR(Q9,0)) -> 18.122 | DF9: =ABS(IFERROR(AH9,0))+ABS(IFERROR(AK9,0))+IFERROR(W9,0) -> 71.98 | DG9: =IFERROR(M9,0)+IFERROR(N9,0)+IFERROR(O9,0)+IFERROR(P9,0) -> 558.762 | DH9: 2590.739
A10: 8694687361 | B10: 10694615798 | C10: 45922.443 | D10: 45925.467 | E10: TIKIDRSS101406984 | F10: 3143 | G10: 0 | H10: 3142.99 | I10: 4000 | J10: 651 | K10: Intra-State | L10: 18 | M10: 0 | N10: 239.72 | O10: 239.72 | P10: 13.318 | Q10: 2.664 | R10: 21.24 | S10: 667.571 | T10: -667.571 | U10: -683.553 | V10: -71.98 | W10: 0 | X10: 61 | Y10: 0 | Z10: 10.98 | AA10: 1 | AB10: ZONAL | AC10: 3349 | AD10: 2387.457 | AE10: 2387.457 | AF10: 0 | AG10: -683.553 | AH10: -71.98 | AI10: 3142.99 | AJ10: 0 | AL10: 0 | AM10: 45939 | AN10: 45939 | AO10: 45939 | AP10: 0 | AQ10: 2663.56 | AR10: 0 | AS10: 9 | AT10: 9 | AU10: 0 | AV10: 0.25 | AW10: 0.25 | AX10: 0.1 | AY10: Tiny Kingdom | AZ10: Dresses | BA10: 21.24 | BB10: 0 | BC10: 667.571 | BD10: -667.571 | BE10: 0 | BF10: 0 | BG10: 0 | BH10: 651 | BI10: 2.66356 | BL10: 0 | BM10: 0 | BN10: 0 | BO10: 0 | BP10: 0 | BS10: 8104d6da-dfc6-471e-9550-5e477814e850 | BT10: 13.318 | BU10: 0 | BV10: 2.664 | BW10: 0 | BX10: 0 | BY10: 0 | BZ10: 0 | CA10: 2387.457 | CB10: 0 | CC10: 0 | CD10: 0 | CE10: 0 | CF10: 0 | CG10: 0 | CH10: 0 | CI10: 0 | CJ10: 0 | CK10: 0 | CL10: 0 | CM10: 0 | CN10: 0 | CO10: 0 | CP10: 0 | CQ10: 0 | CR10: 0 | CS10: 0 | CT10: 0 | CU10: 0 | CV10: 0 | CW10: 0 | CX10: 0 | CY10: 0 | CZ10: 0 | DA10: 0 | DB10: 0 | DC10: =IFERROR(G10,0)+IFERROR(H10,0) -> 3142.99 | DD10: =ABS(IFERROR(T10,0)) -> 667.571 | DE10: =ABS(IFERROR(P10,0)+IFERROR(Q10,0)) -> 15.982 | DF10: =ABS(IFERROR(AH10,0))+ABS(IFERROR(AK10,0))+IFERROR(W10,0) -> 71.98 | DG10: =IFERROR(M10,0)+IFERROR(N10,0)+IFERROR(O10,0)+IFERROR(P10,0) -> 492.758 | DH10: 2387.457
A11: 8687587807 | B11: 10687515231 | C11: 45922.443 | D11: 45927.651 | E11: TIKICLST113026327 | F11: 3104 | G11: 0 | H11: 3104 | I11: 3500 | J11: 190 | K11: Inter-State | L11: 18 | M11: 473.49 | N11: 0 | O11: 0 | P11: 13.153 | Q11: 2.631 | R11: 24.78 | S11: 769.171 | T11: -769.171 | U11: -784.955 | V11: -71.98 | W11: 0 | X11: 61 | Y11: 0 | Z11: 10.98 | AA11: 1 | AB11: NATIONAL | AC11: 3310 | AD11: 2247.065 | AE11: 2247.065 | AF11: 0 | AG11: -784.955 | AH11: -71.98 | AI11: 3104 | AJ11: 0 | AL11: 0 | AM11: 45943 | AN11: 45943 | AO11: 45943 | AP11: 0 | AQ11: 2630.51 | AR11: 18 | AS11: 0 | AT11: 0 | AU11: 0.5 | AV11: 0 | AW11: 0 | AX11: 0.1 | AY11: Tiny Kingdom | AZ11: Clothing Set | BA11: 24.78 | BB11: 0 | BC11: 769.171 | BD11: -769.171 | BE11: 0 | BF11: 0 | BG11: 0 | BH11: 190 | BI11: 2.63051 | BL11: 0 | BM11: 0 | BN11: 0 | BO11: 0 | BP11: 0 | BS11: 768f2142-4660-434c-94b3-30311bd81658 | BT11: 13.153 | BU11: 0 | BV11: 2.631 | BW11: 0 | BX11: 0 | BY11: 0 | BZ11: 0 | CA11: 0 | CB11: 0 | CC11: 2247.065 | CD11: 0 | CE11: 0 | CF11: 0 | CG11: 0 | CH11: 0 | CI11: 0 | CJ11: 0 | CK11: 0 | CL11: 0 | CM11: 0 | CN11: 0 | CO11: 0 | CP11: 0 | CQ11: 0 | CR11: 0 | CS11: 0 | CT11: 0 | CU11: 0 | CV11: 0 | CW11: 0 | CX11: 0 | CY11: 0 | CZ11: 0 | DA11: 0 | DB11: 0 | DC11: =IFERROR(G11,0)+IFERROR(H11,0) -> 3104 | DD11: =ABS(IFERROR(T11,0)) -> 769.171 | DE11: =ABS(IFERROR(P11,0)+IFERROR(Q11,0)) -> 15.784 | DF11: =ABS(IFERROR(AH11,0))+ABS(IFERROR(AK11,0))+IFERROR(W11,0) -> 71.98 | DG11: =IFERROR(M11,0)+IFERROR(N11,0)+IFERROR(O11,0)+IFERROR(P11,0) -> 486.643 | DH11: 2247.065
A12: 8688316765 | B12: 10688244480 | C12: 45922.443 | D12: 45927.529 | E12: TIKIDRSS103325542 | F12: 2594 | G12: 0 | H12: 2594 | I12: 3500 | J12: 700 | K12: Inter-State | L12: 5 | M12: 123.52 | N12: 0 | O12: 0 | P12: 12.352 | Q12: 2.47 | R12: 21.24 | S12: 550.966 | T12: -550.966 | U12: -565.788 | V12: -71.98 | W12: 0 | X12: 61 | Y12: 0 | Z12: 10.98 | AA12: 1 | AB12: NATIONAL | AC12: 2800 | AD12: 1956.232 | AE12: 1956.232 | AF12: 0 | AG12: -565.788 | AH12: -71.98 | AI12: 2594 | AJ12: 0 | AL12: 0 | AM12: 45943 | AN12: 45943 | AO12: 45943 | AP12: 0 | AQ12: 2470.48 | AR12: 5 | AS12: 0 | AT12: 0 | AU12: 0.5 | AV12: 0 | AW12: 0 | AX12: 0.1 | AY12: Tiny Kingdom | AZ12: Dresses | BA12: 21.24 | BB12: 0 | BC12: 550.966 | BD12: -550.966 | BE12: 0 | BF12: 0 | BG12: 0 | BH12: 700 | BI12: 2.47048 | BL12: 0 | BM12: 0 | BN12: 0 | BO12: 0 | BP12: 0 | BS12: 15c4a032-8fd2-4971-aa2f-d5d0a02f3f28 | BT12: 12.352 | BU12: 0 | BV12: 2.47 | BW12: 0 | BX12: 0 | BY12: 0 | BZ12: 0 | CA12: 0 | CB12: 0 | CC12: 1956.232 | CD12: 0 | CE12: 0 | CF12: 0 | CG12: 0 | CH12: 0 | CI12: 0 | CJ12: 0 | CK12: 0 | CL12: 0 | CM12: 0 | CN12: 0 | CO12: 0 | CP12: 0 | CQ12: 0 | CR12: 0 | CS12: 0 | CT12: 0 | CU12: 0 | CV12: 0 | CW12: 0 | CX12: 0 | CY12: 0 | CZ12: 0 | DA12: 0 | DB12: 0 | DC12: =IFERROR(G12,0)+IFERROR(H12,0) -> 2594 | DD12: =ABS(IFERROR(T12,0)) -> 550.966 | DE12: =ABS(IFERROR(P12,0)+IFERROR(Q12,0)) -> 14.822 | DF12: =ABS(IFERROR(AH12,0))+ABS(IFERROR(AK12,0))+IFERROR(W12,0) -> 71.98 | DG12: =IFERROR(M12,0)+IFERROR(N12,0)+IFERROR(O12,0)+IFERROR(P12,0) -> 135.872 | DH12: 1956.232
A13: 8717002058 | B13: 10716943116 | C13: 45930.615 | D13: 45934.626 | E13: TIKIDRSS106641723 | F13: 3119 | G13: 0 | H13: 3118.99 | I13: 3750 | J13: 425 | K13: Inter-State | L13: 18 | M13: 475.78 | N13: 0 | O13: 0 | P13: 13.216 | Q13: 2.643 | R13: 21.24 | S13: 662.473 | T13: -662.473 | U13: -678.332 | V13: -71.98 | W13: 0 | X13: 61 | Y13: 0 | Z13: 10.98 | AA13: 1 | AB13: ZONAL | AC13: 3325 | AD13: 2368.678 | AE13: 2368.678 | AF13: 0 | AG13: -678.332 | AH13: -71.98 | AI13: 3118.99 | AJ13: 0 | AL13: 0 | AM13: 45953 | AN13: 45953 | AO13: 45953 | AP13: 0 | AQ13: 2643.22 | AR13: 18 | AS13: 0 | AT13: 0 | AU13: 0.5 | AV13: 0 | AW13: 0 | AX13: 0.1 | AY13: Tiny Kingdom | AZ13: Dresses | BA13: 21.24 | BB13: 0 | BC13: 662.473 | BD13: -662.473 | BE13: 0 | BF13: 0 | BG13: 0 | BH13: 425 | BI13: 2.64322 | BL13: 0 | BM13: 0 | BN13: 0 | BO13: 0 | BP13: 0 | BS13: 4c3bf5af-4258-40fa-bbbf-029941cc4ade | BT13: 13.216 | BU13: 0 | BV13: 2.643 | BW13: 0 | BX13: 0 | BY13: 0 | BZ13: 0 | CA13: 0 | CB13: 0 | CC13: 0 | CD13: 0 | CE13: 0 | CF13: 0 | CG13: 0 | CH13: 2368.678 | CI13: 0 | CJ13: 0 | CK13: 0 | CL13: 0 | CM13: 0 | CN13: 0 | CO13: 0 | CP13: 0 | CQ13: 0 | CR13: 0 | CS13: 0 | CT13: 0 | CU13: 0 | CV13: 0 | CW13: 0 | CX13: 0 | CY13: 0 | CZ13: 0 | DA13: 0 | DB13: 0 | DC13: =IFERROR(G13,0)+IFERROR(H13,0) -> 3118.99 | DD13: =ABS(IFERROR(T13,0)) -> 662.473 | DE13: =ABS(IFERROR(P13,0)+IFERROR(Q13,0)) -> 15.859 | DF13: =ABS(IFERROR(AH13,0))+ABS(IFERROR(AK13,0))+IFERROR(W13,0) -> 71.98 | DG13: =IFERROR(M13,0)+IFERROR(N13,0)+IFERROR(O13,0)+IFERROR(P13,0) -> 488.996 | DH13: 2368.678
A14: 8670163180 | B14: 10670087339 | C14: 45915.472 | D14: 45918.742 | E14: TIKIDRSS101150929 | F14: 1610 | G14: 0 | H14: 1610 | I14: 3750 | J14: 1875 | K14: Inter-State | L14: 12 | M14: 172.5 | N14: 0 | O14: 0 | P14: 7.188 | Q14: 1.438 | R14: 22.42 | S14: 360.962 | T14: -360.962 | U14: -369.588 | V14: -53.1 | W14: 0 | X14: 45 | Y14: 0 | Z14: 8.1 | AA14: 1 | AB14: NATIONAL | AC14: 1781 | AD14: 1187.312 | AE14: 1187.312 | AF14: 0 | AG14: -369.588 | AH14: -53.1 | AI14: 1610 | AJ14: 0 | AL14: 0 | AM14: 45933 | AN14: 45933 | AO14: 45933 | AP14: 0 | AQ14: 1437.5 | AR14: 12 | AS14: 0 | AT14: 0 | AU14: 0.5 | AV14: 0 | AW14: 0 | AX14: 0.1 | AY14: Tiny Kingdom | AZ14: Dresses | BA14: 22.42 | BB14: 0 | BC14: 360.962 | BD14: -360.962 | BE14: 0 | BF14: 0 | BG14: 0 | BH14: 1875 | BI14: 1.4375 | BL14: 0 | BM14: 0 | BN14: 0 | BO14: 0 | BP14: 0 | BS14: 80f9d3f0-c04f-4328-aa94-90b539e7b635 | BT14: 7.188 | BU14: 0 | BV14: 1.438 | BW14: 0 | BX14: 1187.312 | BY14: 0 | BZ14: 0 | CA14: 0 | CB14: 0 | CC14: 0 | CD14: 0 | CE14: 0 | CF14: 0 | CG14: 0 | CH14: 0 | CI14: 0 | CJ14: 0 | CK14: 0 | CL14: 0 | CM14: 0 | CN14: 0 | CO14: 0 | CP14: 0 | CQ14: 0 | CR14: 0 | CS14: 0 | CT14: 0 | CU14: 0 | CV14: 0 | CW14: 0 | CX14: 0 | CY14: 0 | CZ14: 0 | DA14: 0 | DB14: 0 | DC14: =IFERROR(G14,0)+IFERROR(H14,0) -> 1610 | DD14: =ABS(IFERROR(T14,0)) -> 360.962 | DE14: =ABS(IFERROR(P14,0)+IFERROR(Q14,0)) -> 8.626 | DF14: =ABS(IFERROR(AH14,0))+ABS(IFERROR(AK14,0))+IFERROR(W14,0) -> 53.1 | DG14: =IFERROR(M14,0)+IFERROR(N14,0)+IFERROR(O14,0)+IFERROR(P14,0) -> 179.688 | DH14: 1187.312
A15: 8741339872 | B15: 10741334937 | C15: 45938.423 | D15: 45942.46 | E15: TNBYCLST96884745 | F15: 1421 | G15: 0 | H15: 1421 | I15: 2250 | J15: 658 | K15: Inter-State | L15: 5 | M15: 67.67 | N15: 0 | O15: 0 | P15: 6.767 | Q15: 1.353 | R15: 27.14 | S15: 385.659 | T15: -385.659 | U15: -393.779 | V15: -53.1 | W15: 0 | X15: 45 | Y15: 0 | Z15: 8.1 | AA15: 1 | AB15: NATIONAL | AC15: 1592 | AD15: 974.121 | AE15: 974.121 | AF15: 0 | AG15: -393.779 | AH15: -53.1 | AI15: 1421 | AJ15: 0 | AL15: 0 | AM15: 45957 | AN15: 45957 | AO15: 45957 | AP15: 0 | AQ15: 1353.33 | AR15: 5 | AS15: 0 | AT15: 0 | AU15: 0.5 | AV15: 0 | AW15: 0 | AX15: 0.1 | AY15: Tiny Baby | AZ15: Clothing Set | BA15: 27.14 | BB15: 0 | BC15: 385.659 | BD15: -385.659 | BE15: 0 | BF15: 0 | BG15: 0 | BH15: 658 | BI15: 1.35333 | BL15: 0 | BM15: 0 | BN15: 0 | BO15: 0 | BP15: 0 | BS15: 3302034f-f15d-4331-b7e5-a128b83e4254 | BT15: 6.767 | BU15: 0 | BV15: 1.353 | BW15: 0 | BX15: 0 | BY15: 0 | BZ15: 0 | CA15: 0 | CB15: 0 | CC15: 0 | CD15: 0 | CE15: 0 | CF15: 0 | CG15: 0 | CH15: 0 | CI15: 0 | CJ15: 974.121 | CK15: 0 | CL15: 0 | CM15: 0 | CN15: 0 | CO15: 0 | CP15: 0 | CQ15: 0 | CR15: 0 | CS15: 0 | CT15: 0 | CU15: 0 | CV15: 0 | CW15: 0 | CX15: 0 | CY15: 0 | CZ15: 0 | DA15: 0 | DB15: 0 | DC15: =IFERROR(G15,0)+IFERROR(H15,0) -> 1421 | DD15: =ABS(IFERROR(T15,0)) -> 385.659 | DE15: =ABS(IFERROR(P15,0)+IFERROR(Q15,0)) -> 8.12 | DF15: =ABS(IFERROR(AH15,0))+ABS(IFERROR(AK15,0))+IFERROR(W15,0) -> 53.1 | DG15: =IFERROR(M15,0)+IFERROR(N15,0)+IFERROR(O15,0)+IFERROR(P15,0) -> 74.437 | DH15: 974.121
A16: 8720752290 | B16: 10720697209 | C16: 45930.615 | D16: 45936.703 | E16: TIKILHNC103613408 | F16: 2944.01 | G16: 0 | H16: 2944 | I16: 4500 | J16: 1350 | K16: Inter-State | L16: 18 | M16: 449.09 | N16: 0 | O16: 0 | P16: 12.475 | Q16: 2.495 | R16: 24.78 | S16: 729.523 | T16: -729.523 | U16: -744.493 | V16: -71.98 | W16: 0 | X16: 61 | Y16: 0 | Z16: 10.98 | AA16: 1 | AB16: ZONAL | AC16: 3150 | AD16: 2127.527 | AE16: 2127.527 | AF16: 0 | AG16: -744.493 | AH16: -71.98 | AI16: 2944 | AJ16: 0 | AL16: 0 | AM16: 45953 | AN16: 45953 | AO16: 45953 | AP16: 0 | AQ16: 2494.92 | AR16: 18 | AS16: 0 | AT16: 0 | AU16: 0.5 | AV16: 0 | AW16: 0 | AX16: 0.1 | AY16: Tiny Kingdom | AZ16: Lehenga Choli | BA16: 24.78 | BB16: 0 | BC16: 729.523 | BD16: -729.523 | BE16: 0 | BF16: 0 | BG16: 0 | BH16: 1350 | BI16: 2.49492 | BL16: 0 | BM16: 0 | BN16: 0 | BO16: 0 | BP16: 0 | BS16: ba6710b6-1db2-40c5-898c-0e75736adc14 | BT16: 12.475 | BU16: 0 | BV16: 2.495 | BW16: 0 | BX16: 0 | BY16: 0 | BZ16: 0 | CA16: 0 | CB16: 0 | CC16: 0 | CD16: 0 | CE16: 0 | CF16: 0 | CG16: 0 | CH16: 2127.527 | CI16: 0 | CJ16: 0 | CK16: 0 | CL16: 0 | CM16: 0 | CN16: 0 | CO16: 0 | CP16: 0 | CQ16: 0 | CR16: 0 | CS16: 0 | CT16: 0 | CU16: 0 | CV16: 0 | CW16: 0 | CX16: 0 | CY16: 0 | CZ16: 0 | DA16: 0 | DB16: 0 | DC16: =IFERROR(G16,0)+IFERROR(H16,0) -> 2944 | DD16: =ABS(IFERROR(T16,0)) -> 729.523 | DE16: =ABS(IFERROR(P16,0)+IFERROR(Q16,0)) -> 14.97 | DF16: =ABS(IFERROR(AH16,0))+ABS(IFERROR(AK16,0))+IFERROR(W16,0) -> 71.98 | DG16: =IFERROR(M16,0)+IFERROR(N16,0)+IFERROR(O16,0)+IFERROR(P16,0) -> 461.565 | DH16: 2127.527
A17: 8657021789 | B17: 10656945910 | C17: 45909.456 | D17: 45919.637 | E17: TNBYDRSS60563528 | F17: 706 | G17: 0 | H17: 706 | I17: 2000 | J17: 1200 | K17: Inter-State | L17: 5 | M17: 33.62 | N17: 0 | O17: 0 | P17: 3.362 | Q17: 0.672 | R17: 29.5 | S17: 208.27 | T17: -208.27 | U17: -212.304 | V17: -31.86 | W17: 0 | X17: 27 | Y17: 0 | Z17: 4.86 | AA17: 1 | AB17: NATIONAL | AC17: 800 | AD17: 461.836 | AE17: 461.836 | AF17: 0 | AG17: -212.304 | AH17: -31.86 | AI17: 706 | AJ17: 0 | AL17: 0 | AM17: 45933 | AN17: 45933 | AO17: 45933 | AP17: 0 | AQ17: 672.38 | AR17: 5 | AS17: 0 | AT17: 0 | AU17: 0.5 | AV17: 0 | AW17: 0 | AX17: 0.1 | AY17: Tiny Baby | AZ17: Dresses | BA17: 29.5 | BB17: 0 | BC17: 208.27 | BD17: -208.27 | BE17: 0 | BF17: 0 | BG17: 0 | BH17: 1200 | BI17: 0.67238 | BL17: 0 | BM17: 0 | BN17: 0 | BO17: 0 | BP17: 0 | BS17: d591f506-0e15-4a76-a50a-5e05cc4f7e7b | BT17: 3.362 | BU17: 0 | BV17: 0.672 | BW17: 0 | BX17: 461.836 | BY17: 0 | BZ17: 0 | CA17: 0 | CB17: 0 | CC17: 0 | CD17: 0 | CE17: 0 | CF17: 0 | CG17: 0 | CH17: 0 | CI17: 0 | CJ17: 0 | CK17: 0 | CL17: 0 | CM17: 0 | CN17: 0 | CO17: 0 | CP17: 0 | CQ17: 0 | CR17: 0 | CS17: 0 | CT17: 0 | CU17: 0 | CV17: 0 | CW17: 0 | CX17: 0 | CY17: 0 | CZ17: 0 | DA17: 0 | DB17: 0 | DC17: =IFERROR(G17,0)+IFERROR(H17,0) -> 706 | DD17: =ABS(IFERROR(T17,0)) -> 208.27 | DE17: =ABS(IFERROR(P17,0)+IFERROR(Q17,0)) -> 4.034 | DF17: =ABS(IFERROR(AH17,0))+ABS(IFERROR(AK17,0))+IFERROR(W17,0) -> 31.86 | DG17: =IFERROR(M17,0)+IFERROR(N17,0)+IFERROR(O17,0)+IFERROR(P17,0) -> 36.982 | DH17: 461.836
A18: 8737192003 | B18: 10737169109 | C18: 45936.455 | D18: 45942.791 | E18: BETYDRSS67133154 | F18: 391 | G18: 0 | H18: 391 | I18: 2750 | J18: 2300 | K18: Inter-State | L18: 5 | M18: 18.62 | N18: 0 | O18: 0 | P18: 1.862 | Q18: 0.372 | R18: 2.36 | S18: 9.228 | T18: -9.228 | U18: -11.462 | V18: -31.86 | W18: 0 | X18: 27 | Y18: 0 | Z18: 4.86 | AA18: 1 | AB18: NATIONAL | AC18: 450 | AD18: 347.678 | AE18: 347.678 | AF18: 0 | AG18: -11.462 | AH18: -31.86 | AI18: 391 | AJ18: 0 | AL18: 0 | AM18: 45957 | AN18: 45957 | AO18: 45957 | AP18: 0 | AQ18: 372.38 | AR18: 5 | AS18: 0 | AT18: 0 | AU18: 0.5 | AV18: 0 | AW18: 0 | AX18: 0.1 | AY18: BETTY | AZ18: Dresses | BA18: 2.36 | BB18: 0 | BC18: 9.228 | BD18: -9.228 | BE18: 0 | BF18: 0 | BG18: 0 | BH18: 2300 | BI18: 0.37238 | BL18: 0 | BM18: 0 | BN18: 0 | BO18: 0 | BP18: 0 | BS18: 63c321aa-b3a4-4801-8fdf-df8a1e196647 | BT18: 1.862 | BU18: 0 | BV18: 0.372 | BW18: 0 | BX18: 0 | BY18: 0 | BZ18: 0 | CA18: 0 | CB18: 0 | CC18: 0 | CD18: 0 | CE18: 0 | CF18: 0 | CG18: 0 | CH18: 0 | CI18: 0 | CJ18: 347.678 | CK18: 0 | CL18: 0 | CM18: 0 | CN18: 0 | CO18: 0 | CP18: 0 | CQ18: 0 | CR18: 0 | CS18: 0 | CT18: 0 | CU18: 0 | CV18: 0 | CW18: 0 | CX18: 0 | CY18: 0 | CZ18: 0 | DA18: 0 | DB18: 0 | DC18: =IFERROR(G18,0)+IFERROR(H18,0) -> 391 | DD18: =ABS(IFERROR(T18,0)) -> 9.228 | DE18: =ABS(IFERROR(P18,0)+IFERROR(Q18,0)) -> 2.234 | DF18: =ABS(IFERROR(AH18,0))+ABS(IFERROR(AK18,0))+IFERROR(W18,0) -> 31.86 | DG18: =IFERROR(M18,0)+IFERROR(N18,0)+IFERROR(O18,0)+IFERROR(P18,0) -> 20.482 | DH18: 347.678
A19: 8715339734 | B19: 10715279507 | C19: 45929.449 | D19: 45935.676 | E19: BETYDRSS100320371 | F19: 3470 | G19: 0 | H19: 3470 | I19: 5000 | J19: 1324 | K19: Inter-State | L19: 18 | M19: 529.32 | N19: 0 | O19: 0 | P19: 14.703 | Q19: 2.941 | R19: 31.86 | S19: 1105.542 | T19: -1105.542 | U19: -1123.186 | V19: -71.98 | W19: 0 | X19: 61 | Y19: 0 | Z19: 10.98 | AA19: 1 | AB19: NATIONAL | AC19: 3676 | AD19: 2274.834 | AE19: 2274.834 | AF19: 0 | AG19: -1123.186 | AH19: -71.98 | AI19: 3470 | AJ19: 0 | AL19: 0 | AM19: 45953 | AN19: 45953 | AO19: 45953 | AP19: 0 | AQ19: 2940.68 | AR19: 18 | AS19: 0 | AT19: 0 | AU19: 0.5 | AV19: 0 | AW19: 0 | AX19: 0.1 | AY19: BETTY | AZ19: Dresses | BA19: 31.86 | BB19: 0 | BC19: 1105.542 | BD19: -1105.542 | BE19: 0 | BF19: 0 | BG19: 0 | BH19: 1324 | BI19: 2.94068 | BL19: 0 | BM19: 0 | BN19: 0 | BO19: 0 | BP19: 0 | BS19: de0e3b21-d9fd-4455-877e-a1b99f2775bd | BT19: 14.703 | BU19: 0 | BV19: 2.941 | BW19: 0 | BX19: 0 | BY19: 0 | BZ19: 0 | CA19: 0 | CB19: 0 | CC19: 0 | CD19: 0 | CE19: 0 | CF19: 0 | CG19: 0 | CH19: 2274.834 | CI19: 0 | CJ19: 0 | CK19: 0 | CL19: 0 | CM19: 0 | CN19: 0 | CO19: 0 | CP19: 0 | CQ19: 0 | CR19: 0 | CS19: 0 | CT19: 0 | CU19: 0 | CV19: 0 | CW19: 0 | CX19: 0 | CY19: 0 | CZ19: 0 | DA19: 0 | DB19: 0 | DC19: =IFERROR(G19,0)+IFERROR(H19,0) -> 3470 | DD19: =ABS(IFERROR(T19,0)) -> 1105.542 | DE19: =ABS(IFERROR(P19,0)+IFERROR(Q19,0)) -> 17.644 | DF19: =ABS(IFERROR(AH19,0))+ABS(IFERROR(AK19,0))+IFERROR(W19,0) -> 71.98 | DG19: =IFERROR(M19,0)+IFERROR(N19,0)+IFERROR(O19,0)+IFERROR(P19,0) -> 544.023 | DH19: 2274.834
A20: 8697412249 | B20: 10697341267 | C20: 45922.78 | D20: 45927.78 | E20: TIKIDRSS113039558 | F20: 3109.01 | G20: 0 | H20: 3109 | I20: 3500 | J20: 185 | K20: Inter-State | L20: 18 | M20: 474.26 | N20: 0 | O20: 0 | P20: 13.174 | Q20: 2.635 | R20: 21.24 | S20: 660.352 | T20: -660.352 | U20: -676.161 | V20: -71.98 | W20: 0 | X20: 61 | Y20: 0 | Z20: 10.98 | AA20: 1 | AB20: NATIONAL | AC20: 3315 | AD20: 2360.859 | AE20: 2360.859 | AF20: 0 | AG20: -676.161 | AH20: -71.98 | AI20: 3109 | AJ20: 0 | AL20: 0 | AM20: 45943 | AN20: 45943 | AO20: 45943 | AP20: 0 | AQ20: 2634.75 | AR20: 18 | AS20: 0 | AT20: 0 | AU20: 0.5 | AV20: 0 | AW20: 0 | AX20: 0.1 | AY20: Tiny Kingdom | AZ20: Dresses | BA20: 21.24 | BB20: 0 | BC20: 660.352 | BD20: -660.352 | BE20: 0 | BF20: 0 | BG20: 0 | BH20: 185 | BI20: 2.63475 | BL20: 0 | BM20: 0 | BN20: 0 | BO20: 0 | BP20: 0 | BS20: 88ea3330-ee26-44ae-bbd4-56ef53849b2c | BT20: 13.174 | BU20: 0 | BV20: 2.635 | BW20: 0 | BX20: 0 | BY20: 0 | BZ20: 0 | CA20: 0 | CB20: 0 | CC20: 2360.859 | CD20: 0 | CE20: 0 | CF20: 0 | CG20: 0 | CH20: 0 | CI20: 0 | CJ20: 0 | CK20: 0 | CL20: 0 | CM20: 0 | CN20: 0 | CO20: 0 | CP20: 0 | CQ20: 0 | CR20: 0 | CS20: 0 | CT20: 0 | CU20: 0 | CV20: 0 | CW20: 0 | CX20: 0 | CY20: 0 | CZ20: 0 | DA20: 0 | DB20: 0 | DC20: =IFERROR(G20,0)+IFERROR(H20,0) -> 3109 | DD20: =ABS(IFERROR(T20,0)) -> 660.352 | DE20: =ABS(IFERROR(P20,0)+IFERROR(Q20,0)) -> 15.809 | DF20: =ABS(IFERROR(AH20,0))+ABS(IFERROR(AK20,0))+IFERROR(W20,0) -> 71.98 | DG20: =IFERROR(M20,0)+IFERROR(N20,0)+IFERROR(O20,0)+IFERROR(P20,0) -> 487.434 | DH20: 2360.859
... A22: 8715259067 | B22: 10715198840 | C22: 45929.449 | D22: 45933.717 | E22: BETYDRSS81635448 | F22: 2150 | G22: 0 | H22: 2150 | I22: 5000 | J22: 2644 | K22: Inter-State | L22: 5 | M22: 102.38 | N22: 0 | O22: 0 | P22: 10.238 | Q22: 2.048 | R22: 31.86 | S22: 684.99 | T22: -684.99 | U22: -697.276 | V22: -71.98 | W22: 0 | X22: 61 | Y22: 0 | Z22: 10.98 | AA22: 1 | AB22: NATIONAL | AC22: 2356 | AD22: 1380.744 | AE22: 1380.744 | AF22: 0 | AG22: -697.276 | AH22: -71.98 | AI22: 2150 | AJ22: 0 | AL22: 0 | AM22: 45947 | AN22: 45947 | AO22: 45947 | AP22: 0 | AQ22: 2047.62 | AR22: 5 | AS22: 0 | AT22: 0 | AU22: 0.5 | AV22: 0 | AW22: 0 | AX22: 0.1 | AY22: BETTY | AZ22: Dresses | BA22: 31.86 | BB22: 0 | BC22: 684.99 | BD22: -684.99 | BE22: 0 | BF22: 0 | BG22: 0 | BH22: 2644 | BI22: 2.04762 | BL22: 0 | BM22: 0 | BN22: 0 | BO22: 0 | BP22: 0 | BS22: 23383067-8dba-40c1-a010-f4bd43daabf1 | BT22: 10.238 | BU22: 0 | BV22: 2.048 | BW22: 0 | BX22: 0 | BY22: 0 | BZ22: 0 | CA22: 0 | CB22: 0 | CC22: 0 | CD22: 0 | CE22: 0 | CF22: 0 | CG22: 1380.744 | CH22: 0 | CI22: 0 | CJ22: 0 | CK22: 0 | CL22: 0 | CM22: 0 | CN22: 0 | CO22: 0 | CP22: 0 | CQ22: 0 | CR22: 0 | CS22: 0 | CT22: 0 | CU22: 0 | CV22: 0 | CW22: 0 | CX22: 0 | CY22: 0 | CZ22: 0 | DA22: 0 | DB22: 0 | DC22: =IFERROR(G22,0)+IFERROR(H22,0) -> 2150 | DD22: =ABS(IFERROR(T22,0)) -> 684.99 | DE22: =ABS(IFERROR(P22,0)+IFERROR(Q22,0)) -> 12.286 | DF22: =ABS(IFERROR(AH22,0))+ABS(IFERROR(AK22,0))+IFERROR(W22,0) -> 71.98 | DG22: =IFERROR(M22,0)+IFERROR(N22,0)+IFERROR(O22,0)+IFERROR(P22,0) -> 112.618 | DH22: 1380.744
A23: 8742176123 | B23: 10742175834 | C23: 45938.519 | D23: 45942.705 | E23: TNBYCLST106795158 | F23: 2198 | G23: 2198 | H23: 0 | I23: 3000 | J23: 596 | K23: Inter-State | L23: 5 | M23: 104.67 | N23: 0 | O23: 0 | P23: 10.467 | Q23: 2.093 | R23: 25.96 | S23: 570.601 | T23: -570.601 | U23: -583.161 | V23: -71.98 | W23: 0 | X23: 61 | Y23: 0 | Z23: 10.98 | AA23: 1 | AB23: NATIONAL | AC23: 2404 | AD23: 1542.859 | AE23: 1542.859 | AF23: 0 | AG23: 0 | AI23: 0 | AJ23: -583.161 | AK23: -71.98 | AL23: 2198 | AP23: 0 | AQ23: 2093.33 | AR23: 5 | AS23: 0 | AT23: 0 | AU23: 0.5 | AV23: 0 | AW23: 0 | AX23: 0.1 | AY23: Tiny Baby | AZ23: Clothing Set | BC23: 0 | BD23: 0 | BE23: 0 | BF23: 0 | BG23: 0 | BJ23: 25.96 | BK23: 0 | BL23: 570.601 | BM23: -570.601 | BN23: 0 | BO23: 0 | BP23: 0 | BQ23: 596 | BR23: 2.09333 | BS23: f2dce908-898d-4405-9bd8-3b51ef3ee483 | BT23: 0 | BU23: 10.467 | BV23: 0 | BW23: 2.093 | BX23: 0 | BY23: 0 | BZ23: 0 | CA23: 0 | CB23: 0 | CC23: 0 | CD23: 0 | CE23: 0 | CF23: 0 | CG23: 0 | CH23: 0 | CI23: 0 | CJ23: 1542.859 | CK23: 0 | CL23: 0 | CM23: 0 | CN23: 0 | CO23: 0 | CP23: 0 | CQ23: 0 | CR23: 0 | CS23: 0 | CT23: 0 | CU23: 0 | CV23: 0 | CW23: 0 | CX23: 0 | CY23: 0 | CZ23: 0 | DA23: 0 | DB23: 0 | DC23: =IFERROR(G23,0)+IFERROR(H23,0) -> 2198 | DD23: =ABS(IFERROR(T23,0)) -> 570.601 | DE23: =ABS(IFERROR(P23,0)+IFERROR(Q23,0)) -> 12.56 | DF23: =ABS(IFERROR(AH23,0))+ABS(IFERROR(AK23,0))+IFERROR(W23,0) -> 71.98 | DG23: =IFERROR(M23,0)+IFERROR(N23,0)+IFERROR(O23,0)+IFERROR(P23,0) -> 115.137 | DH23: 1542.859
A24: 8682082418 | B24: 10682009123 | C24: 45919.525 | D24: 45924.545 | E24: BETYLHNC96459192 | F24: 1694 | G24: 1694 | H24: 0 | I24: 4000 | J24: 2000 | K24: Inter-State | L24: 12 | M24: 181.5 | N24: 0 | O24: 0 | P24: 7.562 | Q24: 1.512 | R24: 29.5 | S24: 499.73 | T24: -499.73 | U24: -508.804 | V24: -53.1 | W24: 0 | X24: 45 | Y24: 0 | Z24: 8.1 | AA24: 1 | AB24: NATIONAL | AC24: 1900 | AD24: 1132.096 | AE24: 1132.096 | AF24: 0 | AG24: 0 | AI24: 0 | AJ24: -508.804 | AK24: -53.1 | AL24: 1694 | AP24: 0 | AQ24: 1512.5 | AR24: 12 | AS24: 0 | AT24: 0 | AU24: 0.5 | AV24: 0 | AW24: 0 | AX24: 0.1 | AY24: BETTY | AZ24: Lehenga Choli | BC24: 0 | BD24: 0 | BE24: 0 | BF24: 0 | BG24: 0 | BJ24: 29.5 | BK24: 0 | BL24: 499.73 | BM24: -499.73 | BN24: 0 | BO24: 0 | BP24: 0 | BQ24: 2000 | BR24: 1.5125 | BS24: ed104123-a92e-42f9-9f20-ee6a6406ea0d | BT24: 0 | BU24: 7.562 | BV24: 0 | BW24: 1.512 | BX24: 0 | BY24: 0 | BZ24: 1132.096 | CA24: 0 | CB24: 0 | CC24: 0 | CD24: 0 | CE24: 0 | CF24: 0 | CG24: 0 | CH24: 0 | CI24: 0 | CJ24: 0 | CK24: 0 | CL24: 0 | CM24: 0 | CN24: 0 | CO24: 0 | CP24: 0 | CQ24: 0 | CR24: 0 | CS24: 0 | CT24: 0 | CU24: 0 | CV24: 0 | CW24: 0 | CX24: 0 | CY24: 0 | CZ24: 0 | DA24: 0 | DB24: 0 | DC24: =IFERROR(G24,0)+IFERROR(H24,0) -> 1694 | DD24: =ABS(IFERROR(T24,0)) -> 499.73 | DE24: =ABS(IFERROR(P24,0)+IFERROR(Q24,0)) -> 9.074 | DF24: =ABS(IFERROR(AH24,0))+ABS(IFERROR(AK24,0))+IFERROR(W24,0) -> 53.1 | DG24: =IFERROR(M24,0)+IFERROR(N24,0)+IFERROR(O24,0)+IFERROR(P24,0) -> 189.062 | DH24: 1132.096
A25: 8747034027 | B25: 10747055015 | C25: 45941.44 | D25: 45946.79 | E25: TIKILHNC115963256 | F25: 3564 | G25: 0 | H25: 3564 | I25: 4000 | J25: 230 | K25: Inter-State | L25: 18 | M25: 543.66 | N25: 0 | O25: 0 | P25: 15.102 | Q25: 3.02 | R25: 24.78 | S25: 883.159 | T25: -883.159 | U25: -901.281 | V25: -71.98 | W25: 0 | X25: 61 | Y25: 0 | Z25: 10.98 | AA25: 1 | AB25: NATIONAL | AC25: 3770 | AD25: 2590.739 | AE25: 2590.739 | AF25: 0 | AG25: -901.281 | AH25: -71.98 | AI25: 3564 | AJ25: 0 | AL25: 0 | AM25: 45960 | AN25: 45960 | AO25: 45960 | AP25: 0 | AQ25: 3020.34 | AR25: 18 | AS25: 0 | AT25: 0 | AU25: 0.5 | AV25: 0 | AW25: 0 | AX25: 0.1 | AY25: Tiny Kingdom | AZ25: Lehenga Choli | BA25: 24.78 | BB25: 0 | BC25: 883.159 | BD25: -883.159 | BE25: 0 | BF25: 0 | BG25: 0 | BH25: 230 | BI25: 3.02034 | BL25: 0 | BM25: 0 | BN25: 0 | BO25: 0 | BP25: 0 | BS25: 70eae005-72af-4558-b677-ff3604b0322e | BT25: 15.102 | BU25: 0 | BV25: 3.02 | BW25: 0 | BX25: 0 | BY25: 0 | BZ25: 0 | CA25: 0 | CB25: 0 | CC25: 0 | CD25: 0 | CE25: 0 | CF25: 0 | CG25: 0 | CH25: 0 | CI25: 0 | CJ25: 0 | CK25: 0 | CL25: 0 | CM25: 2590.739 | CN25: 0 | CO25: 0 | CP25: 0 | CQ25: 0 | CR25: 0 | CS25: 0 | CT25: 0 | CU25: 0 | CV25: 0 | CW25: 0 | CX25: 0 | CY25: 0 | CZ25: 0 | DA25: 0 | DB25: 0 | DC25: =IFERROR(G25,0)+IFERROR(H25,0) -> 3564 | DD25: =ABS(IFERROR(T25,0)) -> 883.159 | DE25: =ABS(IFERROR(P25,0)+IFERROR(Q25,0)) -> 18.122 | DF25: =ABS(IFERROR(AH25,0))+ABS(IFERROR(AK25,0))+IFERROR(W25,0) -> 71.98 | DG25: =IFERROR(M25,0)+IFERROR(N25,0)+IFERROR(O25,0)+IFERROR(P25,0) -> 558.762 | DH25: 2590.739
A26: 8737583490 | B26: 10737560594 | C26: 45936.455 | D26: 45940.683 | E26: BETYDRSS74936962 | F26: 1644 | G26: 0 | H26: 1644 | I26: 3850 | J26: 2035 | K26: Inter-State | L26: 5 | M26: 78.29 | N26: 0 | O26: 0 | P26: 7.829 | Q26: 1.566 | R26: 33.04 | S26: 543.178 | T26: -543.178 | U26: -552.573 | V26: -53.1 | W26: 0 | X26: 45 | Y26: 0 | Z26: 8.1 | AA26: 1 | AB26: NATIONAL | AC26: 1815 | AD26: 1038.327 | AE26: 1038.327 | AF26: 0 | AG26: -552.573 | AH26: -53.1 | AI26: 1644 | AJ26: 0 | AL26: 0 | AM26: 45954 | AN26: 45954 | AO26: 45954 | AP26: 0 | AQ26: 1565.71 | AR26: 5 | AS26: 0 | AT26: 0 | AU26: 0.5 | AV26: 0 | AW26: 0 | AX26: 0.1 | AY26: BETTY | AZ26: Dresses | BA26: 33.04 | BB26: 0 | BC26: 543.178 | BD26: -543.178 | BE26: 0 | BF26: 0 | BG26: 0 | BH26: 2035 | BI26: 1.56571 | BL26: 0 | BM26: 0 | BN26: 0 | BO26: 0 | BP26: 0 | BS26: 4d6c19b3-e810-4b37-acec-4ec133be471d | BT26: 7.829 | BU26: 0 | BV26: 1.566 | BW26: 0 | BX26: 0 | BY26: 0 | BZ26: 0 | CA26: 0 | CB26: 0 | CC26: 0 | CD26: 0 | CE26: 0 | CF26: 0 | CG26: 0 | CH26: 0 | CI26: 1038.327 | CJ26: 0 | CK26: 0 | CL26: 0 | CM26: 0 | CN26: 0 | CO26: 0 | CP26: 0 | CQ26: 0 | CR26: 0 | CS26: 0 | CT26: 0 | CU26: 0 | CV26: 0 | CW26: 0 | CX26: 0 | CY26: 0 | CZ26: 0 | DA26: 0 | DB26: 0 | DC26: =IFERROR(G26,0)+IFERROR(H26,0) -> 1644 | DD26: =ABS(IFERROR(T26,0)) -> 543.178 | DE26: =ABS(IFERROR(P26,0)+IFERROR(Q26,0)) -> 9.395 | DF26: =ABS(IFERROR(AH26,0))+ABS(IFERROR(AK26,0))+IFERROR(W26,0) -> 53.1 | DG26: =IFERROR(M26,0)+IFERROR(N26,0)+IFERROR(O26,0)+IFERROR(P26,0) -> 86.119 | DH26: 1038.327
A27: 8739466534 | B27: 10739452262 | C27: 45937.468 | D27: 45943.627 | E27: TIKILHNC106661968 | F27: 4445 | G27: 4445 | H27: 0 | I27: 5000 | J27: 349 | K27: Inter-State | L27: 18 | M27: 678.05 | N27: 0 | O27: 0 | P27: 18.835 | Q27: 3.767 | R27: 24.78 | S27: 1101.471 | T27: -1101.471 | U27: -1124.073 | V27: -71.98 | W27: 0 | X27: 61 | Y27: 0 | Z27: 10.98 | AA27: 1 | AB27: NATIONAL | AC27: 4651 | AD27: 3248.947 | AE27: 3248.947 | AF27: 0 | AG27: 0 | AI27: 0 | AJ27: -1124.073 | AK27: -71.98 | AL27: 4445 | AP27: 0 | AQ27: 3766.95 | AR27: 18 | AS27: 0 | AT27: 0 | AU27: 0.5 | AV27: 0 | AW27: 0 | AX27: 0.1 | AY27: Tiny Kingdom | AZ27: Lehenga Choli | BC27: 0 | BD27: 0 | BE27: 0 | BF27: 0 | BG27: 0 | BJ27: 24.78 | BK27: 0 | BL27: 1101.471 | BM27: -1101.471 | BN27: 0 | BO27: 0 | BP27: 0 | BQ27: 349 | BR27: 3.76695 | BS27: 9eefd143-11dc-4cde-8651-e07aad739bc9 | BT27: 0 | BU27: 18.835 | BV27: 0 | BW27: 3.767 | BX27: 0 | BY27: 0 | BZ27: 0 | CA27: 0 | CB27: 0 | CC27: 0 | CD27: 0 | CE27: 0 | CF27: 0 | CG27: 0 | CH27: 0 | CI27: 0 | CJ27: 3248.947 | CK27: 0 | CL27: 0 | CM27: 0 | CN27: 0 | CO27: 0 | CP27: 0 | CQ27: 0 | CR27: 0 | CS27: 0 | CT27: 0 | CU27: 0 | CV27: 0 | CW27: 0 | CX27: 0 | CY27: 0 | CZ27: 0 | DA27: 0 | DB27: 0 | DC27: =IFERROR(G27,0)+IFERROR(H27,0) -> 4445 | DD27: =ABS(IFERROR(T27,0)) -> 1101.471 | DE27: =ABS(IFERROR(P27,0)+IFERROR(Q27,0)) -> 22.602 | DF27: =ABS(IFERROR(AH27,0))+ABS(IFERROR(AK27,0))+IFERROR(W27,0) -> 71.98 | DG27: =IFERROR(M27,0)+IFERROR(N27,0)+IFERROR(O27,0)+IFERROR(P27,0) -> 696.885 | DH27: 3248.947
A28: 8735054496 | B28: 10735026688 | C28: 45935.461 | D28: 45938.422 | E28: TIKILHNC115963235 | F28: 3169 | G28: 0 | H28: 3169 | I28: 3750 | J28: 375 | K28: Inter-State | L28: 18 | M28: 483.41 | N28: 0 | O28: 0 | P28: 13.428 | Q28: 2.686 | R28: 24.78 | S28: 785.278 | T28: -785.278 | U28: -801.392 | V28: -71.98 | W28: 0 | X28: 61 | Y28: 0 | Z28: 10.98 | AA28: 1 | AB28: ZONAL | AC28: 3375 | AD28: 2295.628 | AE28: 2295.628 | AF28: 0 | AG28: -801.392 | AH28: -71.98 | AI28: 3169 | AJ28: 0 | AL28: 0 | AM28: 45953 | AN28: 45953 | AO28: 45953 | AP28: 0 | AQ28: 2685.59 | AR28: 18 | AS28: 0 | AT28: 0 | AU28: 0.5 | AV28: 0 | AW28: 0 | AX28: 0.1 | AY28: Tiny Kingdom | AZ28: Lehenga Choli | BA28: 24.78 | BB28: 0 | BC28: 785.278 | BD28: -785.278 | BE28: 0 | BF28: 0 | BG28: 0 | BH28: 375 | BI28: 2.68559 | BL28: 0 | BM28: 0 | BN28: 0 | BO28: 0 | BP28: 0 | BS28: b5836731-4725-4be0-981d-cc011944ecce | BT28: 13.428 | BU28: 0 | BV28: 2.686 | BW28: 0 | BX28: 0 | BY28: 0 | BZ28: 0 | CA28: 0 | CB28: 0 | CC28: 0 | CD28: 0 | CE28: 0 | CF28: 0 | CG28: 0 | CH28: 2295.628 | CI28: 0 | CJ28: 0 | CK28: 0 | CL28: 0 | CM28: 0 | CN28: 0 | CO28: 0 | CP28: 0 | CQ28: 0 | CR28: 0 | CS28: 0 | CT28: 0 | CU28: 0 | CV28: 0 | CW28: 0 | CX28: 0 | CY28: 0 | CZ28: 0 | DA28: 0 | DB28: 0 | DC28: =IFERROR(G28,0)+IFERROR(H28,0) -> 3169 | DD28: =ABS(IFERROR(T28,0)) -> 785.278 | DE28: =ABS(IFERROR(P28,0)+IFERROR(Q28,0)) -> 16.114 | DF28: =ABS(IFERROR(AH28,0))+ABS(IFERROR(AK28,0))+IFERROR(W28,0) -> 71.98 | DG28: =IFERROR(M28,0)+IFERROR(N28,0)+IFERROR(O28,0)+IFERROR(P28,0) -> 496.838 | DH28: 2295.628
A29: 8675097215 | B29: 10675021810 | C29: 45916.56 | D29: 45919.669 | E29: TIKILHNC112303900 | F29: 2794 | G29: 0 | H29: 2794 | I29: 3750 | J29: 750 | K29: Inter-State | L29: 12 | M29: 299.36 | N29: 0 | O29: 0 | P29: 12.473 | Q29: 2.495 | R29: 24.78 | S29: 692.353 | T29: -692.353 | U29: -707.321 | V29: -71.98 | W29: 0 | X29: 61 | Y29: 0 | Z29: 10.98 | AA29: 1 | AB29: ZONAL | AC29: 3000 | AD29: 2014.699 | AE29: 2014.699 | AF29: 0 | AG29: -707.321 | AH29: -71.98 | AI29: 2794 | AJ29: 0 | AL29: 0 | AM29: 45933 | AN29: 45933 | AO29: 45933 | AP29: 0 | AQ29: 2494.64 | AR29: 12 | AS29: 0 | AT29: 0 | AU29: 0.5 | AV29: 0 | AW29: 0 | AX29: 0.1 | AY29: Tiny Kingdom | AZ29: Lehenga Choli | BA29: 24.78 | BB29: 0 | BC29: 692.353 | BD29: -692.353 | BE29: 0 | BF29: 0 | BG29: 0 | BH29: 750 | BI29: 2.49464 | BL29: 0 | BM29: 0 | BN29: 0 | BO29: 0 | BP29: 0 | BS29: d2796cf4-07b6-4a5a-b022-7cf9338a29b1 | BT29: 12.473 | BU29: 0 | BV29: 2.495 | BW29: 0 | BX29: 2014.699 | BY29: 0 | BZ29: 0 | CA29: 0 | CB29: 0 | CC29: 0 | CD29: 0 | CE29: 0 | CF29: 0 | CG29: 0 | CH29: 0 | CI29: 0 | CJ29: 0 | CK29: 0 | CL29: 0 | CM29: 0 | CN29: 0 | CO29: 0 | CP29: 0 | CQ29: 0 | CR29: 0 | CS29: 0 | CT29: 0 | CU29: 0 | CV29: 0 | CW29: 0 | CX29: 0 | CY29: 0 | CZ29: 0 | DA29: 0 | DB29: 0 | DC29: =IFERROR(G29,0)+IFERROR(H29,0) -> 2794 | DD29: =ABS(IFERROR(T29,0)) -> 692.353 | DE29: =ABS(IFERROR(P29,0)+IFERROR(Q29,0)) -> 14.968 | DF29: =ABS(IFERROR(AH29,0))+ABS(IFERROR(AK29,0))+IFERROR(W29,0) -> 71.98 | DG29: =IFERROR(M29,0)+IFERROR(N29,0)+IFERROR(O29,0)+IFERROR(P29,0) -> 311.833 | DH29: 2014.699
A30: 8599978899 | B30: 10599905055 | C30: 45873.626 | D30: 45876.476 | E30: TIKILHNC99304399 | F30: 1179 | G30: 1179 | H30: 0 | I30: 4500 | J30: 3150 | K30: Inter-State | L30: 12 | M30: 126.32 | N30: 0 | O30: 0 | P30: 5.263 | Q30: 1.053 | R30: 24.78 | S30: 292.156 | T30: -292.156 | U30: -298.472 | V30: -53.1 | W30: 0 | X30: 45 | Y30: 0 | Z30: 8.1 | AA30: 1 | AB30: ZONAL | AC30: 1350 | AD30: 827.428 | AE30: 827.428 | AF30: 0 | AG30: 0 | AI30: 0 | AJ30: -298.472 | AK30: -53.1 | AL30: 1179 | AP30: 0 | AQ30: 1052.68 | AR30: 12 | AS30: 0 | AT30: 0 | AU30: 0.5 | AV30: 0 | AW30: 0 | AX30: 0.1 | AY30: Tiny Kingdom | AZ30: Lehenga Choli | BC30: 0 | BD30: 0 | BE30: 0 | BF30: 0 | BG30: 0 | BJ30: 24.78 | BK30: 0 | BL30: 292.156 | BM30: -292.156 | BN30: 0 | BO30: 0 | BP30: 0 | BQ30: 3150 | BR30: 1.05268 | BS30: f904280d-7fc3-4611-9396-855af41a3fe7 | BT30: 0 | BU30: 5.263 | BV30: 0 | BW30: 1.053 | BX30: 827.428 | BY30: 0 | BZ30: 0 | CA30: 0 | CB30: 0 | CC30: 0 | CD30: 0 | CE30: 0 | CF30: 0 | CG30: 0 | CH30: 0 | CI30: 0 | CJ30: 0 | CK30: 0 | CL30: 0 | CM30: 0 | CN30: 0 | CO30: 0 | CP30: 0 | CQ30: 0 | CR30: 0 | CS30: 0 | CT30: 0 | CU30: 0 | CV30: 0 | CW30: 0 | CX30: 0 | CY30: 0 | CZ30: 0 | DA30: 0 | DB30: 0 | DC30: =IFERROR(G30,0)+IFERROR(H30,0) -> 1179 | DD30: =ABS(IFERROR(T30,0)) -> 292.156 | DE30: =ABS(IFERROR(P30,0)+IFERROR(Q30,0)) -> 6.316 | DF30: =ABS(IFERROR(AH30,0))+ABS(IFERROR(AK30,0))+IFERROR(W30,0) -> 53.1 | DG30: =IFERROR(M30,0)+IFERROR(N30,0)+IFERROR(O30,0)+IFERROR(P30,0) -> 131.583 | DH30: 827.428
A31: 8744260042 | B31: 10744268480 | C31: 45939.576 | D31: 45945.792 | E31: TNBYCLST116455372 | F31: 3102 | G31: 0 | H31: 3102 | I31: 3500 | J31: 192 | K31: Inter-State | L31: 18 | M31: 473.19 | N31: 0 | O31: 0 | P31: 13.144 | Q31: 2.629 | R31: 25.96 | S31: 805.279 | T31: -805.279 | U31: -821.052 | V31: -71.98 | W31: 0 | X31: 61 | Y31: 0 | Z31: 10.98 | AA31: 1 | AB31: NATIONAL | AC31: 3308 | AD31: 2208.968 | AE31: 2208.968 | AF31: 0 | AG31: -821.052 | AH31: -71.98 | AI31: 3102 | AJ31: 0 | AL31: 0 | AM31: 45959 | AN31: 45959 | AO31: 45959 | AP31: 0 | AQ31: 2628.81 | AR31: 18 | AS31: 0 | AT31: 0 | AU31: 0.5 | AV31: 0 | AW31: 0 | AX31: 0.1 | AY31: Tiny Baby | AZ31: Clothing Set | BA31: 25.96 | BB31: 0 | BC31: 805.279 | BD31: -805.279 | BE31: 0 | BF31: 0 | BG31: 0 | BH31: 192 | BI31: 2.62881 | BL31: 0 | BM31: 0 | BN31: 0 | BO31: 0 | BP31: 0 | BS31: 9db4bc3d-779d-419c-9e0b-9fca42469f0b | BT31: 13.144 | BU31: 0 | BV31: 2.629 | BW31: 0 | BX31: 0 | BY31: 0 | BZ31: 0 | CA31: 0 | CB31: 0 | CC31: 0 | CD31: 0 | CE31: 0 | CF31: 0 | CG31: 0 | CH31: 0 | CI31: 0 | CJ31: 0 | CK31: 0 | CL31: 2208.968 | CM31: 0 | CN31: 0 | CO31: 0 | CP31: 0 | CQ31: 0 | CR31: 0 | CS31: 0 | CT31: 0 | CU31: 0 | CV31: 0 | CW31: 0 | CX31: 0 | CY31: 0 | CZ31: 0 | DA31: 0 | DB31: 0 | DC31: =IFERROR(G31,0)+IFERROR(H31,0) -> 3102 | DD31: =ABS(IFERROR(T31,0)) -> 805.279 | DE31: =ABS(IFERROR(P31,0)+IFERROR(Q31,0)) -> 15.773 | DF31: =ABS(IFERROR(AH31,0))+ABS(IFERROR(AK31,0))+IFERROR(W31,0) -> 71.98 | DG31: =IFERROR(M31,0)+IFERROR(N31,0)+IFERROR(O31,0)+IFERROR(P31,0) -> 486.334 | DH31: 2208.968
A32: 8691422928 | B32: 10691351165 | C32: 45922.443 | D32: 45927.498 | E32: TIKILHNC113049608 | F32: 3564 | G32: 0 | H32: 3564 | I32: 4000 | J32: 230 | K32: Inter-State | L32: 18 | M32: 543.66 | N32: 0 | O32: 0 | P32: 15.102 | Q32: 3.02 | R32: 24.78 | S32: 883.159 | T32: -883.159 | U32: -901.281 | V32: -71.98 | W32: 0 | X32: 61 | Y32: 0 | Z32: 10.98 | AA32: 1 | AB32: ZONAL | AC32: 3770 | AD32: 2590.739 | AE32: 2590.739 | AF32: 0 | AG32: -901.281 | AH32: -71.98 | AI32: 3564 | AJ32: 0 | AL32: 0 | AM32: 45943 | AN32: 45943 | AO32: 45943 | AP32: 0 | AQ32: 3020.34 | AR32: 18 | AS32: 0 | AT32: 0 | AU32: 0.5 | AV32: 0 | AW32: 0 | AX32: 0.1 | AY32: Tiny Kingdom | AZ32: Lehenga Choli | BA32: 24.78 | BB32: 0 | BC32: 883.159 | BD32: -883.159 | BE32: 0 | BF32: 0 | BG32: 0 | BH32: 230 | BI32: 3.02034 | BL32: 0 | BM32: 0 | BN32: 0 | BO32: 0 | BP32: 0 | BS32: 15894860-f24f-4ec8-b4a5-016708217bcc | BT32: 15.102 | BU32: 0 | BV32: 3.02 | BW32: 0 | BX32: 0 | BY32: 0 | BZ32: 0 | CA32: 0 | CB32: 0 | CC32: 2590.739 | CD32: 0 | CE32: 0 | CF32: 0 | CG32: 0 | CH32: 0 | CI32: 0 | CJ32: 0 | CK32: 0 | CL32: 0 | CM32: 0 | CN32: 0 | CO32: 0 | CP32: 0 | CQ32: 0 | CR32: 0 | CS32: 0 | CT32: 0 | CU32: 0 | CV32: 0 | CW32: 0 | CX32: 0 | CY32: 0 | CZ32: 0 | DA32: 0 | DB32: 0 | DC32: =IFERROR(G32,0)+IFERROR(H32,0) -> 3564 | DD32: =ABS(IFERROR(T32,0)) -> 883.159 | DE32: =ABS(IFERROR(P32,0)+IFERROR(Q32,0)) -> 18.122 | DF32: =ABS(IFERROR(AH32,0))+ABS(IFERROR(AK32,0))+IFERROR(W32,0) -> 71.98 | DG32: =IFERROR(M32,0)+IFERROR(N32,0)+IFERROR(O32,0)+IFERROR(P32,0) -> 558.762 | DH32: 2590.739
A33: 8694664241 | B33: 10694592678 | C33: 45922.443 | D33: 45925.558 | E33: BETYDRSS67468522 | F33: 2293 | G33: 190.722 | H33: 2102.278 | I33: 4500 | J33: 2001 | K33: Intra-State | L33: 5 | M33: 0 | N33: 54.6 | O33: 54.6 | P33: 10.919 | Q33: 2.184 | R33: 31.86 | S33: 730.55 | T33: -730.55 | U33: -743.653 | V33: -71.98 | W33: 0 | X33: 61 | Y33: 0 | Z33: 10.98 | AA33: 1 | AB33: LOCAL | AC33: 2499 | AD33: 1477.367 | AE33: 1477.367 | AF33: 0 | AG33: -681.799 | AH33: -65.99268 | AI33: 2102.278 | AJ33: -61.854 | AK33: -5.98732 | AL33: 190.722 | AM33: 45939 | AN33: 45939 | AO33: 45939 | AP33: 175 | AQ33: 2183.8 | AR33: 0 | AS33: 2.5 | AT33: 2.5 | AU33: 0 | AV33: 0.25 | AW33: 0.25 | AX33: 0.1 | AY33: BETTY | AZ33: Dresses | BA33: 31.86 | BB33: 0 | BC33: 669.786 | BD33: -669.786 | BE33: 0 | BF33: 0 | BG33: 0 | BH33: 2001 | BI33: 2.1838 | BJ33: 31.86 | BK33: 0 | BL33: 60.764 | BM33: -60.764 | BN33: 0 | BO33: 0 | BP33: 0 | BQ33: 2001 | BR33: 2.1838 | BS33: 1ac17d49-ac26-47ec-9b63-d58b111dad1d | BT33: 10.011 | BU33: 0.908 | BV33: 2.002 | BW33: 0.182 | BX33: 0 | BY33: 0 | BZ33: 0 | CA33: 1477.367 | CB33: 0 | CC33: 0 | CD33: 0 | CE33: 0 | CF33: 0 | CG33: 0 | CH33: 0 | CI33: 0 | CJ33: 0 | CK33: 0 | CL33: 0 | CM33: 0 | CN33: 0 | CO33: 0 | CP33: 0 | CQ33: 0 | CR33: 0 | CS33: 0 | CT33: 0 | CU33: 0 | CV33: 0 | CW33: 0 | CX33: 0 | CY33: 0 | CZ33: 0 | DA33: 0 | DB33: 0 | DC33: =IFERROR(G33,0)+IFERROR(H33,0) -> 2293 | DD33: =ABS(IFERROR(T33,0)) -> 730.55 | DE33: =ABS(IFERROR(P33,0)+IFERROR(Q33,0)) -> 13.103 | DF33: =ABS(IFERROR(AH33,0))+ABS(IFERROR(AK33,0))+IFERROR(W33,0) -> 71.98 | DG33: =IFERROR(M33,0)+IFERROR(N33,0)+IFERROR(O33,0)+IFERROR(P33,0) -> 120.119 | DH33: 1477.367
A34: 8686235629 | B34: 10686163041 | C34: 45920.474 | D34: 45925.708 | E34: TIKILHNC115963237 | F34: 4219 | G34: 0 | H34: 4219 | I34: 4750 | J34: 325 | K34: Inter-State | L34: 12 | M34: 452.04 | N34: 0 | O34: 0 | P34: 18.835 | Q34: 3.767 | R34: 24.78 | S34: 1045.468 | T34: -1045.468 | U34: -1068.07 | V34: -71.98 | W34: 0 | X34: 61 | Y34: 0 | Z34: 10.98 | AA34: 1 | AB34: NATIONAL | AC34: 4425 | AD34: 3078.95 | AE34: 3078.95 | AF34: 0 | AG34: -1068.07 | AH34: -71.98 | AI34: 4219 | AJ34: 0 | AL34: 0 | AM34: 45939 | AN34: 45939 | AO34: 45939 | AP34: 0 | AQ34: 3766.96 | AR34: 12 | AS34: 0 | AT34: 0 | AU34: 0.5 | AV34: 0 | AW34: 0 | AX34: 0.1 | AY34: Tiny Kingdom | AZ34: Lehenga Choli | BA34: 24.78 | BB34: 0 | BC34: 1045.468 | BD34: -1045.468 | BE34: 0 | BF34: 0 | BG34: 0 | BH34: 325 | BI34: 3.76696 | BL34: 0 | BM34: 0 | BN34: 0 | BO34: 0 | BP34: 0 | BS34: bd29d170-44c4-4a5a-999e-3c5583be8674 | BT34: 18.835 | BU34: 0 | BV34: 3.767 | BW34: 0 | BX34: 0 | BY34: 0 | BZ34: 0 | CA34: 3078.95 | CB34: 0 | CC34: 0 | CD34: 0 | CE34: 0 | CF34: 0 | CG34: 0 | CH34: 0 | CI34: 0 | CJ34: 0 | CK34: 0 | CL34: 0 | CM34: 0 | CN34: 0 | CO34: 0 | CP34: 0 | CQ34: 0 | CR34: 0 | CS34: 0 | CT34: 0 | CU34: 0 | CV34: 0 | CW34: 0 | CX34: 0 | CY34: 0 | CZ34: 0 | DA34: 0 | DB34: 0 | DC34: =IFERROR(G34,0)+IFERROR(H34,0) -> 4219 | DD34: =ABS(IFERROR(T34,0)) -> 1045.468 | DE34: =ABS(IFERROR(P34,0)+IFERROR(Q34,0)) -> 22.602 | DF34: =ABS(IFERROR(AH34,0))+ABS(IFERROR(AK34,0))+IFERROR(W34,0) -> 71.98 | DG34: =IFERROR(M34,0)+IFERROR(N34,0)+IFERROR(O34,0)+IFERROR(P34,0) -> 470.875 | DH34: 3078.95
A35: 8743152600 | B35: 10743157156 | C35: 45939.449 | D35: 45943.626 | E35: TIKICLST113026329 | F35: 2410 | G35: 0 | H35: 2409.99 | I35: 3500 | J35: 884 | K35: Inter-State | L35: 5 | M35: 114.76 | N35: 0 | O35: 0 | P35: 11.476 | Q35: 2.295 | R35: 24.78 | S35: 597.196 | T35: -597.196 | U35: -610.967 | V35: -71.98 | W35: 0 | X35: 61 | Y35: 0 | Z35: 10.98 | AA35: 1 | AB35: ZONAL | AC35: 2616 | AD35: 1727.043 | AE35: 1727.043 | AF35: 0 | AG35: -610.967 | AH35: -71.98 | AI35: 2409.99 | AJ35: 0 | AL35: 0 | AM35: 45957 | AN35: 45957 | AO35: 45957 | AP35: 0 | AQ35: 2295.24 | AR35: 5 | AS35: 0 | AT35: 0 | AU35: 0.5 | AV35: 0 | AW35: 0 | AX35: 0.1 | AY35: Tiny Kingdom | AZ35: Clothing Set | BA35: 24.78 | BB35: 0 | BC35: 597.196 | BD35: -597.196 | BE35: 0 | BF35: 0 | BG35: 0 | BH35: 884 | BI35: 2.29524 | BL35: 0 | BM35: 0 | BN35: 0 | BO35: 0 | BP35: 0 | BS35: 9463124e-fb61-4e91-9e67-3b928c14486b | BT35: 11.476 | BU35: 0 | BV35: 2.295 | BW35: 0 | BX35: 0 | BY35: 0 | BZ35: 0 | CA35: 0 | CB35: 0 | CC35: 0 | CD35: 0 | CE35: 0 | CF35: 0 | CG35: 0 | CH35: 0 | CI35: 0 | CJ35: 1727.043 | CK35: 0 | CL35: 0 | CM35: 0 | CN35: 0 | CO35: 0 | CP35: 0 | CQ35: 0 | CR35: 0 | CS35: 0 | CT35: 0 | CU35: 0 | CV35: 0 | CW35: 0 | CX35: 0 | CY35: 0 | CZ35: 0 | DA35: 0 | DB35: 0 | DC35: =IFERROR(G35,0)+IFERROR(H35,0) -> 2409.99 | DD35: =ABS(IFERROR(T35,0)) -> 597.196 | DE35: =ABS(IFERROR(P35,0)+IFERROR(Q35,0)) -> 13.771 | DF35: =ABS(IFERROR(AH35,0))+ABS(IFERROR(AK35,0))+IFERROR(W35,0) -> 71.98 | DG35: =IFERROR(M35,0)+IFERROR(N35,0)+IFERROR(O35,0)+IFERROR(P35,0) -> 126.236 | DH35: 1727.043
A36: 8745416575 | B36: 10745429075 | C36: 45940.445 | D36: 45944.478 | E36: BETYDRSS51730850 | F36: 416 | G36: 0 | H36: 416 | I36: 2600 | J36: 2125 | K36: Inter-State | L36: 5 | M36: 19.81 | N36: 0 | O36: 0 | P36: 1.981 | Q36: 0.396 | R36: 8.26 | S36: 34.362 | T36: -34.362 | U36: -36.739 | V36: -31.86 | W36: 0 | X36: 27 | Y36: 0 | Z36: 4.86 | AA36: 1 | AB36: ZONAL | AC36: 475 | AD36: 347.401 | AE36: 347.401 | AF36: 0 | AG36: -36.739 | AH36: -31.86 | AI36: 416 | AJ36: 0 | AL36: 0 | AM36: 45958 | AN36: 45958 | AO36: 45958 | AP36: 0 | AQ36: 396.19 | AR36: 5 | AS36: 0 | AT36: 0 | AU36: 0.5 | AV36: 0 | AW36: 0 | AX36: 0.1 | AY36: BETTY | AZ36: Ethnic Dresses | BA36: 8.26 | BB36: 0 | BC36: 34.362 | BD36: -34.362 | BE36: 0 | BF36: 0 | BG36: 0 | BH36: 2125 | BI36: 0.39619 | BL36: 0 | BM36: 0 | BN36: 0 | BO36: 0 | BP36: 0 | BS36: af4528c0-1ab2-4623-a251-5a3b5fdb202a | BT36: 1.981 | BU36: 0 | BV36: 0.396 | BW36: 0 | BX36: 0 | BY36: 0 | BZ36: 0 | CA36: 0 | CB36: 0 | CC36: 0 | CD36: 0 | CE36: 0 | CF36: 0 | CG36: 0 | CH36: 0 | CI36: 0 | CJ36: 0 | CK36: 347.401 | CL36: 0 | CM36: 0 | CN36: 0 | CO36: 0 | CP36: 0 | CQ36: 0 | CR36: 0 | CS36: 0 | CT36: 0 | CU36: 0 | CV36: 0 | CW36: 0 | CX36: 0 | CY36: 0 | CZ36: 0 | DA36: 0 | DB36: 0 | DC36: =IFERROR(G36,0)+IFERROR(H36,0) -> 416 | DD36: =ABS(IFERROR(T36,0)) -> 34.362 | DE36: =ABS(IFERROR(P36,0)+IFERROR(Q36,0)) -> 2.377 | DF36: =ABS(IFERROR(AH36,0))+ABS(IFERROR(AK36,0))+IFERROR(W36,0) -> 31.86 | DG36: =IFERROR(M36,0)+IFERROR(N36,0)+IFERROR(O36,0)+IFERROR(P36,0) -> 21.791 | DH36: 347.401
A37: 8717347916 | B37: 10717288970 | C37: 45930.615 | D37: 45936.674 | E37: TIKIDRSS106641770 | F37: 3119 | G37: 0 | H37: 3119 | I37: 3750 | J37: 425 | K37: Inter-State | L37: 18 | M37: 475.78 | N37: 0 | O37: 0 | P37: 13.216 | Q37: 2.643 | R37: 21.24 | S37: 662.476 | T37: -662.476 | U37: -678.335 | V37: -71.98 | W37: 0 | X37: 61 | Y37: 0 | Z37: 10.98 | AA37: 1 | AB37: NATIONAL | AC37: 3325 | AD37: 2368.685 | AE37: 2368.685 | AF37: 0 | AG37: -678.335 | AH37: -71.98 | AI37: 3119 | AJ37: 0 | AL37: 0 | AM37: 45953 | AN37: 45953 | AO37: 45953 | AP37: 0 | AQ37: 2643.22 | AR37: 18 | AS37: 0 | AT37: 0 | AU37: 0.5 | AV37: 0 | AW37: 0 | AX37: 0.1 | AY37: Tiny Kingdom | AZ37: Dresses | BA37: 21.24 | BB37: 0 | BC37: 662.476 | BD37: -662.476 | BE37: 0 | BF37: 0 | BG37: 0 | BH37: 425 | BI37: 2.64322 | BL37: 0 | BM37: 0 | BN37: 0 | BO37: 0 | BP37: 0 | BS37: 6749a4da-1024-4e5b-b0d1-a406db8a17a8 | BT37: 13.216 | BU37: 0 | BV37: 2.643 | BW37: 0 | BX37: 0 | BY37: 0 | BZ37: 0 | CA37: 0 | CB37: 0 | CC37: 0 | CD37: 0 | CE37: 0 | CF37: 0 | CG37: 0 | CH37: 2368.685 | CI37: 0 | CJ37: 0 | CK37: 0 | CL37: 0 | CM37: 0 | CN37: 0 | CO37: 0 | CP37: 0 | CQ37: 0 | CR37: 0 | CS37: 0 | CT37: 0 | CU37: 0 | CV37: 0 | CW37: 0 | CX37: 0 | CY37: 0 | CZ37: 0 | DA37: 0 | DB37: 0 | DC37: =IFERROR(G37,0)+IFERROR(H37,0) -> 3119 | DD37: =ABS(IFERROR(T37,0)) -> 662.476 | DE37: =ABS(IFERROR(P37,0)+IFERROR(Q37,0)) -> 15.859 | DF37: =ABS(IFERROR(AH37,0))+ABS(IFERROR(AK37,0))+IFERROR(W37,0) -> 71.98 | DG37: =IFERROR(M37,0)+IFERROR(N37,0)+IFERROR(O37,0)+IFERROR(P37,0) -> 488.996 | DH37: 2368.685
A38: 8681243759 | B38: 10681169730 | C38: 45919.434 | D38: 45923.548 | E38: TIKICLST98837547 | F38: 2275 | G38: 0 | H38: 2275 | I38: 4750 | J38: 2138 | K38: Inter-State | L38: 12 | M38: 243.75 | N38: 0 | O38: 0 | P38: 10.156 | Q38: 2.031 | R38: 24.78 | S38: 563.745 | T38: -563.745 | U38: -575.932 | V38: -71.98 | W38: 0 | X38: 61 | Y38: 0 | Z38: 10.98 | AA38: 1 | AB38: NATIONAL | AC38: 2481 | AD38: 1627.088 | AE38: 1627.088 | AF38: 0 | AG38: -575.932 | AH38: -71.98 | AI38: 2275 | AJ38: 0 | AL38: 0 | AM38: 45938 | AN38: 45938 | AO38: 45938 | AP38: 0 | AQ38: 2031.25 | AR38: 12 | AS38: 0 | AT38: 0 | AU38: 0.5 | AV38: 0 | AW38: 0 | AX38: 0.1 | AY38: Tiny Kingdom | AZ38: Clothing Set | BA38: 24.78 | BB38: 0 | BC38: 563.745 | BD38: -563.745 | BE38: 0 | BF38: 0 | BG38: 0 | BH38: 2138 | BI38: 2.03125 | BL38: 0 | BM38: 0 | BN38: 0 | BO38: 0 | BP38: 0 | BS38: 0c5bf0f2-507f-470d-858a-0222f525feb5 | BT38: 10.156 | BU38: 0 | BV38: 2.031 | BW38: 0 | BX38: 0 | BY38: 0 | BZ38: 1627.088 | CA38: 0 | CB38: 0 | CC38: 0 | CD38: 0 | CE38: 0 | CF38: 0 | CG38: 0 | CH38: 0 | CI38: 0 | CJ38: 0 | CK38: 0 | CL38: 0 | CM38: 0 | CN38: 0 | CO38: 0 | CP38: 0 | CQ38: 0 | CR38: 0 | CS38: 0 | CT38: 0 | CU38: 0 | CV38: 0 | CW38: 0 | CX38: 0 | CY38: 0 | CZ38: 0 | DA38: 0 | DB38: 0 | DC38: =IFERROR(G38,0)+IFERROR(H38,0) -> 2275 | DD38: =ABS(IFERROR(T38,0)) -> 563.745 | DE38: =ABS(IFERROR(P38,0)+IFERROR(Q38,0)) -> 12.187 | DF38: =ABS(IFERROR(AH38,0))+ABS(IFERROR(AK38,0))+IFERROR(W38,0) -> 71.98 | DG38: =IFERROR(M38,0)+IFERROR(N38,0)+IFERROR(O38,0)+IFERROR(P38,0) -> 253.906 | DH38: 1627.088
A39: 8707877371 | B39: 10707811233 | C39: 45925.776 | D39: 45933.485 | E39: TIKICLST113026329 | F39: 3104 | G39: 3104 | H39: 0 | I39: 3500 | J39: 190 | K39: Inter-State | L39: 18 | M39: 473.49 | N39: 0 | O39: 0 | P39: 13.153 | Q39: 2.63 | R39: 24.78 | S39: 769.171 | T39: -769.171 | U39: -784.955 | V39: -71.98 | W39: 0 | X39: 61 | Y39: 0 | Z39: 10.98 | AA39: 1 | AB39: NATIONAL | AC39: 3310 | AD39: 2247.065 | AE39: 2247.065 | AF39: 0 | AG39: -704.054 | AH39: -64.56134 | AI39: 2784.09 | AJ39: -80.901 | AK39: -7.41866 | AL39: 319.91 | AM39: 45947 | AN39: 45947 | AO39: 45947 | AP39: 300 | AQ39: 2630.51 | AR39: 18 | AS39: 0 | AT39: 0 | AU39: 0.5 | AV39: 0 | AW39: 0 | AX39: 0.1 | AY39: Tiny Kingdom | AZ39: Clothing Set | BC39: 0 | BD39: 0 | BE39: 0 | BF39: 0 | BG39: 0 | BJ39: 24.78 | BK39: 0 | BL39: 769.171 | BM39: -769.171 | BN39: 0 | BO39: 0 | BP39: 0 | BQ39: 190 | BR39: 2.63051 | BS39: 700c0553-2296-4d34-8f2a-e0cf0593659c | BT39: 11.797 | BU39: 1.356 | BV39: 2.359 | BW39: 0.271 | BX39: 0 | BY39: 0 | BZ39: 0 | CA39: 0 | CB39: 0 | CC39: 0 | CD39: 0 | CE39: 0 | CF39: 0 | CG39: 2247.065 | CH39: 0 | CI39: 0 | CJ39: 0 | CK39: 0 | CL39: 0 | CM39: 0 | CN39: 0 | CO39: 0 | CP39: 0 | CQ39: 0 | CR39: 0 | CS39: 0 | CT39: 0 | CU39: 0 | CV39: 0 | CW39: 0 | CX39: 0 | CY39: 0 | CZ39: 0 | DA39: 0 | DB39: 0 | DC39: =IFERROR(G39,0)+IFERROR(H39,0) -> 3104 | DD39: =ABS(IFERROR(T39,0)) -> 769.171 | DE39: =ABS(IFERROR(P39,0)+IFERROR(Q39,0)) -> 15.783 | DF39: =ABS(IFERROR(AH39,0))+ABS(IFERROR(AK39,0))+IFERROR(W39,0) -> 71.98 | DG39: =IFERROR(M39,0)+IFERROR(N39,0)+IFERROR(O39,0)+IFERROR(P39,0) -> 486.643 | DH39: 2247.066
A40: 8748140593 | B40: 10748165924 | C40: 45941.551 | D40: 45944.607 | E40: TIKICLST116340919 | F40: 3743 | G40: 0 | H40: 3743 | I40: 4000 | J40: 51 | K40: Inter-State | L40: 18 | M40: 570.97 | N40: 0 | O40: 0 | P40: 15.86 | Q40: 3.172 | R40: 24.78 | S40: 927.515 | T40: -927.515 | U40: -946.547 | V40: -71.98 | W40: 0 | X40: 61 | Y40: 0 | Z40: 10.98 | AA40: 1 | AB40: ZONAL | AC40: 3949 | AD40: 2724.473 | AE40: 2724.473 | AF40: 0 | AG40: -946.547 | AH40: -71.98 | AI40: 3743 | AJ40: 0 | AL40: 0 | AM40: 45958 | AN40: 45958 | AO40: 45958 | AP40: 0 | AQ40: 3172.03 | AR40: 18 | AS40: 0 | AT40: 0 | AU40: 0.5 | AV40: 0 | AW40: 0 | AX40: 0.1 | AY40: Tiny Kingdom | AZ40: Clothing Set | BA40: 24.78 | BB40: 0 | BC40: 927.515 | BD40: -927.515 | BE40: 0 | BF40: 0 | BG40: 0 | BH40: 51 | BI40: 3.17203 | BL40: 0 | BM40: 0 | BN40: 0 | BO40: 0 | BP40: 0 | BS40: 7686f9d4-421a-4f4d-b72e-8be2bbe982cd | BT40: 15.86 | BU40: 0 | BV40: 3.172 | BW40: 0 | BX40: 0 | BY40: 0 | BZ40: 0 | CA40: 0 | CB40: 0 | CC40: 0 | CD40: 0 | CE40: 0 | CF40: 0 | CG40: 0 | CH40: 0 | CI40: 0 | CJ40: 0 | CK40: 2724.473 | CL40: 0 | CM40: 0 | CN40: 0 | CO40: 0 | CP40: 0 | CQ40: 0 | CR40: 0 | CS40: 0 | CT40: 0 | CU40: 0 | CV40: 0 | CW40: 0 | CX40: 0 | CY40: 0 | CZ40: 0 | DA40: 0 | DB40: 0 | DC40: =IFERROR(G40,0)+IFERROR(H40,0) -> 3743 | DD40: =ABS(IFERROR(T40,0)) -> 927.515 | DE40: =ABS(IFERROR(P40,0)+IFERROR(Q40,0)) -> 19.032 | DF40: =ABS(IFERROR(AH40,0))+ABS(IFERROR(AK40,0))+IFERROR(W40,0) -> 71.98 | DG40: =IFERROR(M40,0)+IFERROR(N40,0)+IFERROR(O40,0)+IFERROR(P40,0) -> 586.83 | DH40: 2724.473
A41: 8742706323 | B41: 10742710878 | C41: 45938.797 | D41: 45943.68 | E41: BETYDRSS63786092 | F41: 368 | G41: 0 | H41: 368 | I41: 2500 | J41: 2050 | K41: Inter-State | L41: 5 | M41: 17.52 | N41: 0 | O41: 0 | P41: 1.752 | Q41: 0.35 | R41: 2.36 | S41: 8.685 | T41: -8.685 | U41: -10.787 | V41: -31.86 | W41: 0 | X41: 27 | Y41: 0 | Z41: 4.86 | AA41: 1 | AB41: ZONAL | AC41: 427 | AD41: 325.353 | AE41: 325.353 | AF41: 0 | AG41: -10.787 | AH41: -31.86 | AI41: 368 | AJ41: 0 | AL41: 0 | AM41: 45957 | AN41: 45957 | AO41: 45957 | AP41: 0 | AQ41: 350.48 | AR41: 5 | AS41: 0 | AT41: 0 | AU41: 0.5 | AV41: 0 | AW41: 0 | AX41: 0.1 | AY41: BETTY | AZ41: Dresses | BA41: 2.36 | BB41: 0 | BC41: 8.685 | BD41: -8.685 | BE41: 0 | BF41: 0 | BG41: 0 | BH41: 2050 | BI41: 0.35048 | BL41: 0 | BM41: 0 | BN41: 0 | BO41: 0 | BP41: 0 | BS41: 313fb93b-dd20-4ddf-8db9-ad81fb348b96 | BT41: 1.752 | BU41: 0 | BV41: 0.35 | BW41: 0 | BX41: 0 | BY41: 0 | BZ41: 0 | CA41: 0 | CB41: 0 | CC41: 0 | CD41: 0 | CE41: 0 | CF41: 0 | CG41: 0 | CH41: 0 | CI41: 0 | CJ41: 325.353 | CK41: 0 | CL41: 0 | CM41: 0 | CN41: 0 | CO41: 0 | CP41: 0 | CQ41: 0 | CR41: 0 | CS41: 0 | CT41: 0 | CU41: 0 | CV41: 0 | CW41: 0 | CX41: 0 | CY41: 0 | CZ41: 0 | DA41: 0 | DB41: 0 | DC41: =IFERROR(G41,0)+IFERROR(H41,0) -> 368 | DD41: =ABS(IFERROR(T41,0)) -> 8.685 | DE41: =ABS(IFERROR(P41,0)+IFERROR(Q41,0)) -> 2.102 | DF41: =ABS(IFERROR(AH41,0))+ABS(IFERROR(AK41,0))+IFERROR(W41,0) -> 31.86 | DG41: =IFERROR(M41,0)+IFERROR(N41,0)+IFERROR(O41,0)+IFERROR(P41,0) -> 19.272 | DH41: 325.353
A42: 8725349158 | B42: 10725299335 | C42: 45931.8 | D42: 45937.683 | E42: TNBYCLST106795162 | F42: 2198 | G42: 2198 | H42: 0 | I42: 3000 | J42: 596 | K42: Inter-State | L42: 5 | M42: 104.67 | N42: 0 | O42: 0 | P42: 10.467 | Q42: 2.093 | R42: 25.96 | S42: 570.601 | T42: -570.601 | U42: -583.161 | V42: -71.98 | W42: 0 | X42: 61 | Y42: 0 | Z42: 10.98 | AA42: 1 | AB42: NATIONAL | AC42: 2404 | AD42: 1542.859 | AE42: 1542.859 | AF42: 0 | AG42: 0 | AI42: 0 | AJ42: -583.161 | AK42: -71.98 | AL42: 2198 | AP42: 0 | AQ42: 2093.33 | AR42: 5 | AS42: 0 | AT42: 0 | AU42: 0.5 | AV42: 0 | AW42: 0 | AX42: 0.1 | AY42: Tiny Baby | AZ42: Clothing Set | BC42: 0 | BD42: 0 | BE42: 0 | BF42: 0 | BG42: 0 | BJ42: 25.96 | BK42: 0 | BL42: 570.601 | BM42: -570.601 | BN42: 0 | BO42: 0 | BP42: 0 | BQ42: 596 | BR42: 2.09333 | BS42: 2e5a5599-0327-46b2-942d-634e7edf3534 | BT42: 0 | BU42: 10.467 | BV42: 0 | BW42: 2.093 | BX42: 0 | BY42: 0 | BZ42: 0 | CA42: 0 | CB42: 0 | CC42: 0 | CD42: 0 | CE42: 0 | CF42: 0 | CG42: 0 | CH42: 1542.859 | CI42: 0 | CJ42: 0 | CK42: 0 | CL42: 0 | CM42: 0 | CN42: 0 | CO42: 0 | CP42: 0 | CQ42: 0 | CR42: 0 | CS42: 0 | CT42: 0 | CU42: 0 | CV42: 0 | CW42: 0 | CX42: 0 | CY42: 0 | CZ42: 0 | DA42: 0 | DB42: 0 | DC42: =IFERROR(G42,0)+IFERROR(H42,0) -> 2198 | DD42: =ABS(IFERROR(T42,0)) -> 570.601 | DE42: =ABS(IFERROR(P42,0)+IFERROR(Q42,0)) -> 12.56 | DF42: =ABS(IFERROR(AH42,0))+ABS(IFERROR(AK42,0))+IFERROR(W42,0) -> 71.98 | DG42: =IFERROR(M42,0)+IFERROR(N42,0)+IFERROR(O42,0)+IFERROR(P42,0) -> 115.137 | DH42: 1542.859
A43: 8664301435 | B43: 10664225483 | C43: 45913.451 | D43: 45916.729 | E43: TIKIDRSS112925102 | F43: 1109 | G43: 0 | H43: 1108.99 | I43: 1600 | J43: 320 | K43: Inter-State | L43: 12 | M43: 118.82 | N43: 0 | O43: 0 | P43: 4.951 | Q43: 0.99 | R43: 22.42 | S43: 248.636 | T43: -248.636 | U43: -254.577 | V43: -53.1 | W43: 0 | X43: 45 | Y43: 0 | Z43: 8.1 | AA43: 1 | AB43: ZONAL | AC43: 1280 | AD43: 801.313 | AE43: 801.313 | AF43: 0 | AG43: -254.577 | AH43: -53.1 | AI43: 1108.99 | AJ43: 0 | AL43: 0 | AM43: 45933 | AN43: 45933 | AO43: 45933 | AP43: 0 | AQ43: 990.18 | AR43: 12 | AS43: 0 | AT43: 0 | AU43: 0.5 | AV43: 0 | AW43: 0 | AX43: 0.1 | AY43: Tiny Kingdom | AZ43: Dresses | BA43: 22.42 | BB43: 0 | BC43: 248.636 | BD43: -248.636 | BE43: 0 | BF43: 0 | BG43: 0 | BH43: 320 | BI43: 0.99018 | BL43: 0 | BM43: 0 | BN43: 0 | BO43: 0 | BP43: 0 | BS43: 2b9fac36-7605-4535-8f2e-dd58338ef099 | BT43: 4.951 | BU43: 0 | BV43: 0.99 | BW43: 0 | BX43: 801.313 | BY43: 0 | BZ43: 0 | CA43: 0 | CB43: 0 | CC43: 0 | CD43: 0 | CE43: 0 | CF43: 0 | CG43: 0 | CH43: 0 | CI43: 0 | CJ43: 0 | CK43: 0 | CL43: 0 | CM43: 0 | CN43: 0 | CO43: 0 | CP43: 0 | CQ43: 0 | CR43: 0 | CS43: 0 | CT43: 0 | CU43: 0 | CV43: 0 | CW43: 0 | CX43: 0 | CY43: 0 | CZ43: 0 | DA43: 0 | DB43: 0 | DC43: =IFERROR(G43,0)+IFERROR(H43,0) -> 1108.99 | DD43: =ABS(IFERROR(T43,0)) -> 248.636 | DE43: =ABS(IFERROR(P43,0)+IFERROR(Q43,0)) -> 5.941 | DF43: =ABS(IFERROR(AH43,0))+ABS(IFERROR(AK43,0))+IFERROR(W43,0) -> 53.1 | DG43: =IFERROR(M43,0)+IFERROR(N43,0)+IFERROR(O43,0)+IFERROR(P43,0) -> 123.771 | DH43: 801.313
A44: 8740468522 | B44: 10740458982 | C44: 45937.797 | D44: 45942.542 | E44: BETYDRSS67133042 | F44: 391 | G44: 0 | H44: 391 | I44: 2750 | J44: 2300 | K44: Inter-State | L44: 5 | M44: 18.62 | N44: 0 | O44: 0 | P44: 1.862 | Q44: 0.372 | R44: 2.36 | S44: 9.228 | T44: -9.228 | U44: -11.462 | V44: -31.86 | W44: 0 | X44: 27 | Y44: 0 | Z44: 4.86 | AA44: 1 | AB44: NATIONAL | AC44: 450 | AD44: 347.678 | AE44: 347.678 | AF44: 0 | AG44: -11.462 | AH44: -31.86 | AI44: 391 | AJ44: 0 | AL44: 0 | AM44: 45957 | AN44: 45957 | AO44: 45957 | AP44: 0 | AQ44: 372.38 | AR44: 5 | AS44: 0 | AT44: 0 | AU44: 0.5 | AV44: 0 | AW44: 0 | AX44: 0.1 | AY44: BETTY | AZ44: Dresses | BA44: 2.36 | BB44: 0 | BC44: 9.228 | BD44: -9.228 | BE44: 0 | BF44: 0 | BG44: 0 | BH44: 2300 | BI44: 0.37238 | BL44: 0 | BM44: 0 | BN44: 0 | BO44: 0 | BP44: 0 | BS44: 7d239310-09b8-4446-bd35-802722d6def0 | BT44: 1.862 | BU44: 0 | BV44: 0.372 | BW44: 0 | BX44: 0 | BY44: 0 | BZ44: 0 | CA44: 0 | CB44: 0 | CC44: 0 | CD44: 0 | CE44: 0 | CF44: 0 | CG44: 0 | CH44: 0 | CI44: 0 | CJ44: 347.678 | CK44: 0 | CL44: 0 | CM44: 0 | CN44: 0 | CO44: 0 | CP44: 0 | CQ44: 0 | CR44: 0 | CS44: 0 | CT44: 0 | CU44: 0 | CV44: 0 | CW44: 0 | CX44: 0 | CY44: 0 | CZ44: 0 | DA44: 0 | DB44: 0 | DC44: =IFERROR(G44,0)+IFERROR(H44,0) -> 391 | DD44: =ABS(IFERROR(T44,0)) -> 9.228 | DE44: =ABS(IFERROR(P44,0)+IFERROR(Q44,0)) -> 2.234 | DF44: =ABS(IFERROR(AH44,0))+ABS(IFERROR(AK44,0))+IFERROR(W44,0) -> 31.86 | DG44: =IFERROR(M44,0)+IFERROR(N44,0)+IFERROR(O44,0)+IFERROR(P44,0) -> 20.482 | DH44: 347.678
A45: 8700420125 | B45: 10700350426 | C45: 45923.447 | D45: 45926.744 | E45: TIKIDRSS113553895 | F45: 3119 | G45: 3119 | H45: 0 | I45: 3500 | J45: 175 | K45: Inter-State | L45: 18 | M45: 475.78 | N45: 0 | O45: 0 | P45: 13.216 | Q45: 2.643 | R45: 21.24 | S45: 662.476 | T45: -662.476 | U45: -678.335 | V45: -71.98 | W45: 0 | X45: 61 | Y45: 0 | Z45: 10.98 | AA45: 1 | AB45: ZONAL | AC45: 3325 | AD45: 2368.685 | AE45: 2368.685 | AF45: 0 | AG45: 0 | AI45: 0 | AJ45: -678.335 | AK45: -71.98 | AL45: 3119 | AP45: 0 | AQ45: 2643.22 | AR45: 18 | AS45: 0 | AT45: 0 | AU45: 0.5 | AV45: 0 | AW45: 0 | AX45: 0.1 | AY45: Tiny Kingdom | AZ45: Dresses | BC45: 0 | BD45: 0 | BE45: 0 | BF45: 0 | BG45: 0 | BJ45: 21.24 | BK45: 0 | BL45: 662.476 | BM45: -662.476 | BN45: 0 | BO45: 0 | BP45: 0 | BQ45: 175 | BR45: 2.64322 | BS45: de44f70f-6853-4073-8c20-f5d3922a46ec | BT45: 0 | BU45: 13.216 | BV45: 0 | BW45: 2.643 | BX45: 0 | BY45: 0 | BZ45: 0 | CA45: 0 | CB45: 2368.685 | CC45: 0 | CD45: 0 | CE45: 0 | CF45: 0 | CG45: 0 | CH45: 0 | CI45: 0 | CJ45: 0 | CK45: 0 | CL45: 0 | CM45: 0 | CN45: 0 | CO45: 0 | CP45: 0 | CQ45: 0 | CR45: 0 | CS45: 0 | CT45: 0 | CU45: 0 | CV45: 0 | CW45: 0 | CX45: 0 | CY45: 0 | CZ45: 0 | DA45: 0 | DB45: 0 | DC45: =IFERROR(G45,0)+IFERROR(H45,0) -> 3119 | DD45: =ABS(IFERROR(T45,0)) -> 662.476 | DE45: =ABS(IFERROR(P45,0)+IFERROR(Q45,0)) -> 15.859 | DF45: =ABS(IFERROR(AH45,0))+ABS(IFERROR(AK45,0))+IFERROR(W45,0) -> 71.98 | DG45: =IFERROR(M45,0)+IFERROR(N45,0)+IFERROR(O45,0)+IFERROR(P45,0) -> 488.996 | DH45: 2368.685
A46: 8717347910 | B46: 10717288964 | C46: 45930.615 | D46: 45936.674 | E46: TIKIDRSS106641774 | F46: 3119 | G46: 0 | H46: 3119 | I46: 3750 | J46: 425 | K46: Inter-State | L46: 18 | M46: 475.78 | N46: 0 | O46: 0 | P46: 13.216 | Q46: 2.643 | R46: 21.24 | S46: 662.476 | T46: -662.476 | U46: -678.335 | V46: -71.98 | W46: 0 | X46: 61 | Y46: 0 | Z46: 10.98 | AA46: 1 | AB46: NATIONAL | AC46: 3325 | AD46: 2368.685 | AE46: 2368.685 | AF46: 0 | AG46: -678.335 | AH46: -71.98 | AI46: 3119 | AJ46: 0 | AL46: 0 | AM46: 45953 | AN46: 45953 | AO46: 45953 | AP46: 0 | AQ46: 2643.22 | AR46: 18 | AS46: 0 | AT46: 0 | AU46: 0.5 | AV46: 0 | AW46: 0 | AX46: 0.1 | AY46: Tiny Kingdom | AZ46: Dresses | BA46: 21.24 | BB46: 0 | BC46: 662.476 | BD46: -662.476 | BE46: 0 | BF46: 0 | BG46: 0 | BH46: 425 | BI46: 2.64322 | BL46: 0 | BM46: 0 | BN46: 0 | BO46: 0 | BP46: 0 | BS46: 6749a4da-1024-4e5b-b0d1-a406db8a17a8 | BT46: 13.216 | BU46: 0 | BV46: 2.643 | BW46: 0 | BX46: 0 | BY46: 0 | BZ46: 0 | CA46: 0 | CB46: 0 | CC46: 0 | CD46: 0 | CE46: 0 | CF46: 0 | CG46: 0 | CH46: 2368.685 | CI46: 0 | CJ46: 0 | CK46: 0 | CL46: 0 | CM46: 0 | CN46: 0 | CO46: 0 | CP46: 0 | CQ46: 0 | CR46: 0 | CS46: 0 | CT46: 0 | CU46: 0 | CV46: 0 | CW46: 0 | CX46: 0 | CY46: 0 | CZ46: 0 | DA46: 0 | DB46: 0 | DC46: =IFERROR(G46,0)+IFERROR(H46,0) -> 3119 | DD46: =ABS(IFERROR(T46,0)) -> 662.476 | DE46: =ABS(IFERROR(P46,0)+IFERROR(Q46,0)) -> 15.859 | DF46: =ABS(IFERROR(AH46,0))+ABS(IFERROR(AK46,0))+IFERROR(W46,0) -> 71.98 | DG46: =IFERROR(M46,0)+IFERROR(N46,0)+IFERROR(O46,0)+IFERROR(P46,0) -> 488.996 | DH46: 2368.685
A47: 8695924416 | B47: 10695853086 | C47: 45922.443 | D47: 45926.883 | E47: TNBYCLST90488948 | F47: 2244 | G47: 2244 | H47: 0 | I47: 3250 | J47: 800 | K47: Inter-State | L47: 5 | M47: 106.86 | N47: 0 | O47: 0 | P47: 10.686 | Q47: 2.137 | R47: 25.96 | S47: 582.542 | T47: -582.542 | U47: -595.365 | V47: -71.98 | W47: 0 | X47: 61 | Y47: 0 | Z47: 10.98 | AA47: 1 | AB47: NATIONAL | AC47: 2450 | AD47: 1576.655 | AE47: 1576.655 | AF47: 0 | AG47: 0 | AI47: 0 | AJ47: -595.365 | AK47: -71.98 | AL47: 2244 | AP47: 0 | AQ47: 2137.14 | AR47: 5 | AS47: 0 | AT47: 0 | AU47: 0.5 | AV47: 0 | AW47: 0 | AX47: 0.1 | AY47: Tiny Baby | AZ47: Clothing Set | BC47: 0 | BD47: 0 | BE47: 0 | BF47: 0 | BG47: 0 | BJ47: 25.96 | BK47: 0 | BL47: 582.542 | BM47: -582.542 | BN47: 0 | BO47: 0 | BP47: 0 | BQ47: 800 | BR47: 2.13714 | BS47: 63c671fa-00c3-4177-9307-bdcc0459c1dc | BT47: 0 | BU47: 10.686 | BV47: 0 | BW47: 2.137 | BX47: 0 | BY47: 0 | BZ47: 0 | CA47: 0 | CB47: 1576.655 | CC47: 0 | CD47: 0 | CE47: 0 | CF47: 0 | CG47: 0 | CH47: 0 | CI47: 0 | CJ47: 0 | CK47: 0 | CL47: 0 | CM47: 0 | CN47: 0 | CO47: 0 | CP47: 0 | CQ47: 0 | CR47: 0 | CS47: 0 | CT47: 0 | CU47: 0 | CV47: 0 | CW47: 0 | CX47: 0 | CY47: 0 | CZ47: 0 | DA47: 0 | DB47: 0 | DC47: =IFERROR(G47,0)+IFERROR(H47,0) -> 2244 | DD47: =ABS(IFERROR(T47,0)) -> 582.542 | DE47: =ABS(IFERROR(P47,0)+IFERROR(Q47,0)) -> 12.823 | DF47: =ABS(IFERROR(AH47,0))+ABS(IFERROR(AK47,0))+IFERROR(W47,0) -> 71.98 | DG47: =IFERROR(M47,0)+IFERROR(N47,0)+IFERROR(O47,0)+IFERROR(P47,0) -> 117.546 | DH47: 1576.655
A48: 8672940065 | B48: 10672864489 | C48: 45916.46 | D48: 45920.706 | E48: TIKICLST103607743 | F48: 3544 | G48: 0 | H48: 3544 | I48: 5000 | J48: 1250 | K48: Inter-State | L48: 12 | M48: 379.71 | N48: 0 | O48: 0 | P48: 15.821 | Q48: 3.164 | R48: 25.96 | S48: 920.022 | T48: -920.022 | U48: -939.007 | V48: -71.98 | W48: 0 | X48: 61 | Y48: 0 | Z48: 10.98 | AA48: 1 | AB48: NATIONAL | AC48: 3750 | AD48: 2533.013 | AE48: 2533.013 | AF48: 0 | AG48: -939.007 | AH48: -71.98 | AI48: 3544 | AJ48: 0 | AL48: 0 | AM48: 45936 | AN48: 45936 | AO48: 45936 | AP48: 0 | AQ48: 3164.29 | AR48: 12 | AS48: 0 | AT48: 0 | AU48: 0.5 | AV48: 0 | AW48: 0 | AX48: 0.1 | AY48: Tiny Kingdom | AZ48: Kurta Sets | BA48: 25.96 | BB48: 0 | BC48: 920.022 | BD48: -920.022 | BE48: 0 | BF48: 0 | BG48: 0 | BH48: 1250 | BI48: 3.16429 | BL48: 0 | BM48: 0 | BN48: 0 | BO48: 0 | BP48: 0 | BS48: 1aa0507a-edd9-4086-a30f-60ba68a7568e | BT48: 15.821 | BU48: 0 | BV48: 3.164 | BW48: 0 | BX48: 0 | BY48: 2533.013 | BZ48: 0 | CA48: 0 | CB48: 0 | CC48: 0 | CD48: 0 | CE48: 0 | CF48: 0 | CG48: 0 | CH48: 0 | CI48: 0 | CJ48: 0 | CK48: 0 | CL48: 0 | CM48: 0 | CN48: 0 | CO48: 0 | CP48: 0 | CQ48: 0 | CR48: 0 | CS48: 0 | CT48: 0 | CU48: 0 | CV48: 0 | CW48: 0 | CX48: 0 | CY48: 0 | CZ48: 0 | DA48: 0 | DB48: 0 | DC48: =IFERROR(G48,0)+IFERROR(H48,0) -> 3544 | DD48: =ABS(IFERROR(T48,0)) -> 920.022 | DE48: =ABS(IFERROR(P48,0)+IFERROR(Q48,0)) -> 18.985 | DF48: =ABS(IFERROR(AH48,0))+ABS(IFERROR(AK48,0))+IFERROR(W48,0) -> 71.98 | DG48: =IFERROR(M48,0)+IFERROR(N48,0)+IFERROR(O48,0)+IFERROR(P48,0) -> 395.531 | DH48: 2533.013
A49: 8690064005 | B49: 10689992017 | C49: 45922.443 | D49: 45926.485 | E49: TNBYDRSS112709048 | F49: 2719 | G49: 2719 | H49: 0 | I49: 3250 | J49: 325 | K49: Inter-State | L49: 18 | M49: 414.76 | N49: 0 | O49: 0 | P49: 11.521 | Q49: 2.304 | R49: 25.96 | S49: 705.852 | T49: -705.852 | U49: -719.677 | V49: -71.98 | W49: 0 | X49: 61 | Y49: 0 | Z49: 10.98 | AA49: 1 | AB49: ZONAL | AC49: 2925 | AD49: 1927.343 | AE49: 1927.343 | AF49: 0 | AG49: 0 | AI49: 0 | AJ49: -719.677 | AK49: -71.98 | AL49: 2719 | AP49: 0 | AQ49: 2304.24 | AR49: 18 | AS49: 0 | AT49: 0 | AU49: 0.5 | AV49: 0 | AW49: 0 | AX49: 0.1 | AY49: Tiny Baby | AZ49: Dresses | BC49: 0 | BD49: 0 | BE49: 0 | BF49: 0 | BG49: 0 | BJ49: 25.96 | BK49: 0 | BL49: 705.852 | BM49: -705.852 | BN49: 0 | BO49: 0 | BP49: 0 | BQ49: 325 | BR49: 2.30424 | BS49: 2edf0875-4250-4b18-a5e0-56e3c2334a12 | BT49: 0 | BU49: 11.521 | BV49: 0 | BW49: 2.304 | BX49: 0 | BY49: 0 | BZ49: 0 | CA49: 0 | CB49: 1927.343 | CC49: 0 | CD49: 0 | CE49: 0 | CF49: 0 | CG49: 0 | CH49: 0 | CI49: 0 | CJ49: 0 | CK49: 0 | CL49: 0 | CM49: 0 | CN49: 0 | CO49: 0 | CP49: 0 | CQ49: 0 | CR49: 0 | CS49: 0 | CT49: 0 | CU49: 0 | CV49: 0 | CW49: 0 | CX49: 0 | CY49: 0 | CZ49: 0 | DA49: 0 | DB49: 0 | DC49: =IFERROR(G49,0)+IFERROR(H49,0) -> 2719 | DD49: =ABS(IFERROR(T49,0)) -> 705.852 | DE49: =ABS(IFERROR(P49,0)+IFERROR(Q49,0)) -> 13.825 | DF49: =ABS(IFERROR(AH49,0))+ABS(IFERROR(AK49,0))+IFERROR(W49,0) -> 71.98 | DG49: =IFERROR(M49,0)+IFERROR(N49,0)+IFERROR(O49,0)+IFERROR(P49,0) -> 426.281 | DH49: 1927.343
A50: 8681830415 | B50: 10681756867 | C50: 45919.434 | D50: 45924.49 | E50: TIKICLST103607778 | F50: 3544 | G50: 0 | H50: 3544 | I50: 5000 | J50: 1250 | K50: Inter-State | L50: 12 | M50: 379.71 | N50: 0 | O50: 0 | P50: 15.821 | Q50: 3.164 | R50: 25.96 | S50: 920.022 | T50: -920.022 | U50: -939.007 | V50: -71.98 | W50: 0 | X50: 61 | Y50: 0 | Z50: 10.98 | AA50: 1 | AB50: NATIONAL | AC50: 3750 | AD50: 2533.013 | AE50: 2533.013 | AF50: 0 | AG50: -939.007 | AH50: -71.98 | AI50: 3544 | AJ50: 0 | AL50: 0 | AM50: 45938 | AN50: 45938 | AO50: 45938 | AP50: 0 | AQ50: 3164.29 | AR50: 12 | AS50: 0 | AT50: 0 | AU50: 0.5 | AV50: 0 | AW50: 0 | AX50: 0.1 | AY50: Tiny Kingdom | AZ50: Kurta Sets | BA50: 25.96 | BB50: 0 | BC50: 920.022 | BD50: -920.022 | BE50: 0 | BF50: 0 | BG50: 0 | BH50: 1250 | BI50: 3.16429 | BL50: 0 | BM50: 0 | BN50: 0 | BO50: 0 | BP50: 0 | BS50: 97d3377e-f48f-4085-b65a-8a54cbc97858 | BT50: 15.821 | BU50: 0 | BV50: 3.164 | BW50: 0 | BX50: 0 | BY50: 0 | BZ50: 2533.013 | CA50: 0 | CB50: 0 | CC50: 0 | CD50: 0 | CE50: 0 | CF50: 0 | CG50: 0 | CH50: 0 | CI50: 0 | CJ50: 0 | CK50: 0 | CL50: 0 | CM50: 0 | CN50: 0 | CO50: 0 | CP50: 0 | CQ50: 0 | CR50: 0 | CS50: 0 | CT50: 0 | CU50: 0 | CV50: 0 | CW50: 0 | CX50: 0 | CY50: 0 | CZ50: 0 | DA50: 0 | DB50: 0 | DC50: =IFERROR(G50,0)+IFERROR(H50,0) -> 3544 | DD50: =ABS(IFERROR(T50,0)) -> 920.022 | DE50: =ABS(IFERROR(P50,0)+IFERROR(Q50,0)) -> 18.985 | DF50: =ABS(IFERROR(AH50,0))+ABS(IFERROR(AK50,0))+IFERROR(W50,0) -> 71.98 | DG50: =IFERROR(M50,0)+IFERROR(N50,0)+IFERROR(O50,0)+IFERROR(P50,0) -> 395.531 | DH50: 2533.013
A51: 8663980354 | B51: 10663904414 | C51: 45912.803 | D51: 45916.449 | E51: BETYDRSS112339715 | F51: 4194 | G51: 0 | H51: 4193.99 | I51: 5500 | J51: 1100 | K51: Inter-State | L51: 12 | M51: 449.36 | N51: 0 | O51: 0 | P51: 18.723 | Q51: 3.745 | R51: 31.86 | S51: 1336.205 | T51: -1336.205 | U51: -1358.673 | V51: -71.98 | W51: 0 | X51: 61 | Y51: 0 | Z51: 10.98 | AA51: 1 | AB51: NATIONAL | AC51: 4400 | AD51: 2763.337 | AE51: 2763.337 | AF51: 0 | AG51: -1358.673 | AH51: -71.98 | AI51: 4193.99 | AJ51: 0 | AL51: 0 | AM51: 45933 | AN51: 45933 | AO51: 45933 | AP51: 0 | AQ51: 3744.64 | AR51: 12 | AS51: 0 | AT51: 0 | AU51: 0.5 | AV51: 0 | AW51: 0 | AX51: 0.1 | AY51: BETTY | AZ51: Dresses | BA51: 31.86 | BB51: 0 | BC51: 1336.205 | BD51: -1336.205 | BE51: 0 | BF51: 0 | BG51: 0 | BH51: 1100 | BI51: 3.74464 | BL51: 0 | BM51: 0 | BN51: 0 | BO51: 0 | BP51: 0 | BS51: 51133a83-1f5e-476d-a465-fe950a2200c6 | BT51: 18.723 | BU51: 0 | BV51: 3.745 | BW51: 0 | BX51: 2763.337 | BY51: 0 | BZ51: 0 | CA51: 0 | CB51: 0 | CC51: 0 | CD51: 0 | CE51: 0 | CF51: 0 | CG51: 0 | CH51: 0 | CI51: 0 | CJ51: 0 | CK51: 0 | CL51: 0 | CM51: 0 | CN51: 0 | CO51: 0 | CP51: 0 | CQ51: 0 | CR51: 0 | CS51: 0 | CT51: 0 | CU51: 0 | CV51: 0 | CW51: 0 | CX51: 0 | CY51: 0 | CZ51: 0 | DA51: 0 | DB51: 0 | DC51: =IFERROR(G51,0)+IFERROR(H51,0) -> 4193.99 | DD51: =ABS(IFERROR(T51,0)) -> 1336.205 | DE51: =ABS(IFERROR(P51,0)+IFERROR(Q51,0)) -> 22.468 | DF51: =ABS(IFERROR(AH51,0))+ABS(IFERROR(AK51,0))+IFERROR(W51,0) -> 71.98 | DG51: =IFERROR(M51,0)+IFERROR(N51,0)+IFERROR(O51,0)+IFERROR(P51,0) -> 468.083 | DH51: 2763.337
A52: 8737492325 | B52: 10737469429 | C52: 45936.455 | D52: 45940.501 | E52: TIKIDRSS113491284 | F52: 3013 | G52: 0 | H52: 3013 | I52: 3750 | J52: 531 | K52: Inter-State | L52: 18 | M52: 459.61 | N52: 0 | O52: 0 | P52: 12.767 | Q52: 2.553 | R52: 21.24 | S52: 639.961 | T52: -639.961 | U52: -655.281 | V52: -71.98 | W52: 0 | X52: 61 | Y52: 0 | Z52: 10.98 | AA52: 1 | AB52: ZONAL | AC52: 3219 | AD52: 2285.739 | AE52: 2285.739 | AF52: 0 | AG52: -655.281 | AH52: -71.98 | AI52: 3013 | AJ52: 0 | AL52: 0 | AM52: 45954 | AN52: 45954 | AO52: 45954 | AP52: 0 | AQ52: 2553.39 | AR52: 18 | AS52: 0 | AT52: 0 | AU52: 0.5 | AV52: 0 | AW52: 0 | AX52: 0.1 | AY52: Tiny Kingdom | AZ52: Dresses | BA52: 21.24 | BB52: 0 | BC52: 639.961 | BD52: -639.961 | BE52: 0 | BF52: 0 | BG52: 0 | BH52: 531 | BI52: 2.55339 | BL52: 0 | BM52: 0 | BN52: 0 | BO52: 0 | BP52: 0 | BS52: 16f92cb4-e2f3-4842-90e6-c0401e2c6bce | BT52: 12.767 | BU52: 0 | BV52: 2.553 | BW52: 0 | BX52: 0 | BY52: 0 | BZ52: 0 | CA52: 0 | CB52: 0 | CC52: 0 | CD52: 0 | CE52: 0 | CF52: 0 | CG52: 0 | CH52: 0 | CI52: 2285.739 | CJ52: 0 | CK52: 0 | CL52: 0 | CM52: 0 | CN52: 0 | CO52: 0 | CP52: 0 | CQ52: 0 | CR52: 0 | CS52: 0 | CT52: 0 | CU52: 0 | CV52: 0 | CW52: 0 | CX52: 0 | CY52: 0 | CZ52: 0 | DA52: 0 | DB52: 0 | DC52: =IFERROR(G52,0)+IFERROR(H52,0) -> 3013 | DD52: =ABS(IFERROR(T52,0)) -> 639.961 | DE52: =ABS(IFERROR(P52,0)+IFERROR(Q52,0)) -> 15.32 | DF52: =ABS(IFERROR(AH52,0))+ABS(IFERROR(AK52,0))+IFERROR(W52,0) -> 71.98 | DG52: =IFERROR(M52,0)+IFERROR(N52,0)+IFERROR(O52,0)+IFERROR(P52,0) -> 472.377 | DH52: 2285.739
A53: 8683798730 | B53: 10683725740 | C53: 45920.474 | D53: 45924.72 | E53: BETYDRSS85575444 | F53: 2293 | G53: 190.722 | H53: 2102.278 | I53: 4750 | J53: 2251 | K53: Inter-State | L53: 12 | M53: 245.68 | N53: 0 | O53: 0 | P53: 10.236 | Q53: 2.047 | R53: 31.86 | S53: 730.55 | T53: -730.55 | U53: -742.833 | V53: -71.98 | W53: 0 | X53: 61 | Y53: 0 | Z53: 10.98 | AA53: 1 | AB53: NATIONAL | AC53: 2499 | AD53: 1478.187 | AE53: 1478.187 | AF53: 0 | AG53: -681.048 | AH53: -65.99268 | AI53: 2102.278 | AJ53: -61.785 | AK53: -5.98732 | AL53: 190.722 | AM53: 45938 | AN53: 45938 | AO53: 45938 | AP53: 175 | AQ53: 2047.32 | AR53: 12 | AS53: 0 | AT53: 0 | AU53: 0.5 | AV53: 0 | AW53: 0 | AX53: 0.1 | AY53: BETTY | AZ53: Dresses | BA53: 31.86 | BB53: 0 | BC53: 669.786 | BD53: -669.786 | BE53: 0 | BF53: 0 | BG53: 0 | BH53: 2251 | BI53: 2.04732 | BJ53: 31.86 | BK53: 0 | BL53: 60.764 | BM53: -60.764 | BN53: 0 | BO53: 0 | BP53: 0 | BQ53: 2251 | BR53: 2.04732 | BS53: 8a44c65f-68a6-4bd5-95be-72dfc2e11523 | BT53: 9.385 | BU53: 0.851 | BV53: 1.877 | BW53: 0.17 | BX53: 0 | BY53: 0 | BZ53: 1478.187 | CA53: 0 | CB53: 0 | CC53: 0 | CD53: 0 | CE53: 0 | CF53: 0 | CG53: 0 | CH53: 0 | CI53: 0 | CJ53: 0 | CK53: 0 | CL53: 0 | CM53: 0 | CN53: 0 | CO53: 0 | CP53: 0 | CQ53: 0 | CR53: 0 | CS53: 0 | CT53: 0 | CU53: 0 | CV53: 0 | CW53: 0 | CX53: 0 | CY53: 0 | CZ53: 0 | DA53: 0 | DB53: 0 | DC53: =IFERROR(G53,0)+IFERROR(H53,0) -> 2293 | DD53: =ABS(IFERROR(T53,0)) -> 730.55 | DE53: =ABS(IFERROR(P53,0)+IFERROR(Q53,0)) -> 12.283 | DF53: =ABS(IFERROR(AH53,0))+ABS(IFERROR(AK53,0))+IFERROR(W53,0) -> 71.98 | DG53: =IFERROR(M53,0)+IFERROR(N53,0)+IFERROR(O53,0)+IFERROR(P53,0) -> 255.916 | DH53: 1478.187
A54: 8741406110 | B54: 10741401175 | C54: 45938.424 | D54: 45942.59 | E54: TIKICLST112314152 | F54: 3594 | G54: 0 | H54: 3593.99 | I54: 4000 | J54: 200 | K54: Inter-State | L54: 18 | M54: 548.24 | N54: 0 | O54: 0 | P54: 15.229 | Q54: 3.046 | R54: 25.96 | S54: 933 | T54: -933 | U54: -951.275 | V54: -71.98 | W54: 0 | X54: 61 | Y54: 0 | Z54: 10.98 | AA54: 1 | AB54: NATIONAL | AC54: 3800 | AD54: 2570.735 | AE54: 2570.735 | AF54: 0 | AG54: -951.275 | AH54: -71.98 | AI54: 3593.99 | AJ54: 0 | AL54: 0 | AM54: 45957 | AN54: 45957 | AO54: 45957 | AP54: 0 | AQ54: 3045.76 | AR54: 18 | AS54: 0 | AT54: 0 | AU54: 0.5 | AV54: 0 | AW54: 0 | AX54: 0.1 | AY54: Tiny Kingdom | AZ54: Kurta Sets | BA54: 25.96 | BB54: 0 | BC54: 933 | BD54: -933 | BE54: 0 | BF54: 0 | BG54: 0 | BH54: 200 | BI54: 3.04576 | BL54: 0 | BM54: 0 | BN54: 0 | BO54: 0 | BP54: 0 | BS54: ac96149e-7bfa-44a0-8b0a-54e7f554d9ab | BT54: 15.229 | BU54: 0 | BV54: 3.046 | BW54: 0 | BX54: 0 | BY54: 0 | BZ54: 0 | CA54: 0 | CB54: 0 | CC54: 0 | CD54: 0 | CE54: 0 | CF54: 0 | CG54: 0 | CH54: 0 | CI54: 0 | CJ54: 2570.735 | CK54: 0 | CL54: 0 | CM54: 0 | CN54: 0 | CO54: 0 | CP54: 0 | CQ54: 0 | CR54: 0 | CS54: 0 | CT54: 0 | CU54: 0 | CV54: 0 | CW54: 0 | CX54: 0 | CY54: 0 | CZ54: 0 | DA54: 0 | DB54: 0 | DC54: =IFERROR(G54,0)+IFERROR(H54,0) -> 3593.99 | DD54: =ABS(IFERROR(T54,0)) -> 933 | DE54: =ABS(IFERROR(P54,0)+IFERROR(Q54,0)) -> 18.275 | DF54: =ABS(IFERROR(AH54,0))+ABS(IFERROR(AK54,0))+IFERROR(W54,0) -> 71.98 | DG54: =IFERROR(M54,0)+IFERROR(N54,0)+IFERROR(O54,0)+IFERROR(P54,0) -> 563.469 | DH54: 2570.735
A55: 8714990694 | B55: 10714930449 | C55: 45929.449 | D55: 45934.753 | E55: TIKILHNC106661942 | F55: 2150 | G55: 0 | H55: 2150 | I55: 4500 | J55: 2144 | K55: Inter-State | L55: 5 | M55: 102.38 | N55: 0 | O55: 0 | P55: 10.238 | Q55: 2.048 | R55: 24.78 | S55: 532.77 | T55: -532.77 | U55: -545.056 | V55: -71.98 | W55: 0 | X55: 61 | Y55: 0 | Z55: 10.98 | AA55: 1 | AB55: NATIONAL | AC55: 2356 | AD55: 1532.964 | AE55: 1532.964 | AF55: 0 | AG55: -545.056 | AH55: -71.98 | AI55: 2150 | AJ55: 0 | AL55: 0 | AM55: 45953 | AN55: 45953 | AO55: 45953 | AP55: 0 | AQ55: 2047.62 | AR55: 5 | AS55: 0 | AT55: 0 | AU55: 0.5 | AV55: 0 | AW55: 0 | AX55: 0.1 | AY55: Tiny Kingdom | AZ55: Lehenga Choli | BA55: 24.78 | BB55: 0 | BC55: 532.77 | BD55: -532.77 | BE55: 0 | BF55: 0 | BG55: 0 | BH55: 2144 | BI55: 2.04762 | BL55: 0 | BM55: 0 | BN55: 0 | BO55: 0 | BP55: 0 | BS55: 18d85bc5-bb14-4977-baae-98d9fe5e5b44 | BT55: 10.238 | BU55: 0 | BV55: 2.048 | BW55: 0 | BX55: 0 | BY55: 0 | BZ55: 0 | CA55: 0 | CB55: 0 | CC55: 0 | CD55: 0 | CE55: 0 | CF55: 0 | CG55: 0 | CH55: 1532.964 | CI55: 0 | CJ55: 0 | CK55: 0 | CL55: 0 | CM55: 0 | CN55: 0 | CO55: 0 | CP55: 0 | CQ55: 0 | CR55: 0 | CS55: 0 | CT55: 0 | CU55: 0 | CV55: 0 | CW55: 0 | CX55: 0 | CY55: 0 | CZ55: 0 | DA55: 0 | DB55: 0 | DC55: =IFERROR(G55,0)+IFERROR(H55,0) -> 2150 | DD55: =ABS(IFERROR(T55,0)) -> 532.77 | DE55: =ABS(IFERROR(P55,0)+IFERROR(Q55,0)) -> 12.286 | DF55: =ABS(IFERROR(AH55,0))+ABS(IFERROR(AK55,0))+IFERROR(W55,0) -> 71.98 | DG55: =IFERROR(M55,0)+IFERROR(N55,0)+IFERROR(O55,0)+IFERROR(P55,0) -> 112.618 | DH55: 1532.964
A56: 8670260084 | B56: 10670184241 | C56: 45915.472 | D56: 45919.464 | E56: TIKICLST103607759 | F56: 3544 | G56: 0 | H56: 3544 | I56: 5000 | J56: 1250 | K56: Inter-State | L56: 12 | M56: 379.71 | N56: 0 | O56: 0 | P56: 15.821 | Q56: 3.164 | R56: 25.96 | S56: 920.022 | T56: -920.022 | U56: -939.007 | V56: -71.98 | W56: 0 | X56: 61 | Y56: 0 | Z56: 10.98 | AA56: 1 | AB56: NATIONAL | AC56: 3750 | AD56: 2533.013 | AE56: 2533.013 | AF56: 0 | AG56: -939.007 | AH56: -71.98 | AI56: 3544 | AJ56: 0 | AL56: 0 | AM56: 45933 | AN56: 45933 | AO56: 45933 | AP56: 0 | AQ56: 3164.29 | AR56: 12 | AS56: 0 | AT56: 0 | AU56: 0.5 | AV56: 0 | AW56: 0 | AX56: 0.1 | AY56: Tiny Kingdom | AZ56: Kurta Sets | BA56: 25.96 | BB56: 0 | BC56: 920.022 | BD56: -920.022 | BE56: 0 | BF56: 0 | BG56: 0 | BH56: 1250 | BI56: 3.16429 | BL56: 0 | BM56: 0 | BN56: 0 | BO56: 0 | BP56: 0 | BS56: d74487ed-253f-440b-8c9b-475b72951539 | BT56: 15.821 | BU56: 0 | BV56: 3.164 | BW56: 0 | BX56: 2533.013 | BY56: 0 | BZ56: 0 | CA56: 0 | CB56: 0 | CC56: 0 | CD56: 0 | CE56: 0 | CF56: 0 | CG56: 0 | CH56: 0 | CI56: 0 | CJ56: 0 | CK56: 0 | CL56: 0 | CM56: 0 | CN56: 0 | CO56: 0 | CP56: 0 | CQ56: 0 | CR56: 0 | CS56: 0 | CT56: 0 | CU56: 0 | CV56: 0 | CW56: 0 | CX56: 0 | CY56: 0 | CZ56: 0 | DA56: 0 | DB56: 0 | DC56: =IFERROR(G56,0)+IFERROR(H56,0) -> 3544 | DD56: =ABS(IFERROR(T56,0)) -> 920.022 | DE56: =ABS(IFERROR(P56,0)+IFERROR(Q56,0)) -> 18.985 | DF56: =ABS(IFERROR(AH56,0))+ABS(IFERROR(AK56,0))+IFERROR(W56,0) -> 71.98 | DG56: =IFERROR(M56,0)+IFERROR(N56,0)+IFERROR(O56,0)+IFERROR(P56,0) -> 395.531 | DH56: 2533.013
A57: 8695941287 | B57: 10695869958 | C57: 45922.443 | D57: 45925.786 | E57: TIKILHNC115963211 | F57: 3564 | G57: 0 | H57: 3564 | I57: 4000 | J57: 230 | K57: Inter-State | L57: 18 | M57: 543.66 | N57: 0 | O57: 0 | P57: 15.102 | Q57: 3.02 | R57: 24.78 | S57: 883.159 | T57: -883.159 | U57: -901.281 | V57: -71.98 | W57: 0 | X57: 61 | Y57: 0 | Z57: 10.98 | AA57: 1 | AB57: ZONAL | AC57: 3770 | AD57: 2590.739 | AE57: 2590.739 | AF57: 0 | AG57: -901.281 | AH57: -71.98 | AI57: 3564 | AJ57: 0 | AL57: 0 | AM57: 45939 | AN57: 45939 | AO57: 45939 | AP57: 0 | AQ57: 3020.34 | AR57: 18 | AS57: 0 | AT57: 0 | AU57: 0.5 | AV57: 0 | AW57: 0 | AX57: 0.1 | AY57: Tiny Kingdom | AZ57: Lehenga Choli | BA57: 24.78 | BB57: 0 | BC57: 883.159 | BD57: -883.159 | BE57: 0 | BF57: 0 | BG57: 0 | BH57: 230 | BI57: 3.02034 | BL57: 0 | BM57: 0 | BN57: 0 | BO57: 0 | BP57: 0 | BS57: 24a6849a-a746-4df0-a017-b8396c85e6fc | BT57: 15.102 | BU57: 0 | BV57: 3.02 | BW57: 0 | BX57: 0 | BY57: 0 | BZ57: 0 | CA57: 2590.739 | CB57: 0 | CC57: 0 | CD57: 0 | CE57: 0 | CF57: 0 | CG57: 0 | CH57: 0 | CI57: 0 | CJ57: 0 | CK57: 0 | CL57: 0 | CM57: 0 | CN57: 0 | CO57: 0 | CP57: 0 | CQ57: 0 | CR57: 0 | CS57: 0 | CT57: 0 | CU57: 0 | CV57: 0 | CW57: 0 | CX57: 0 | CY57: 0 | CZ57: 0 | DA57: 0 | DB57: 0 | DC57: =IFERROR(G57,0)+IFERROR(H57,0) -> 3564 | DD57: =ABS(IFERROR(T57,0)) -> 883.159 | DE57: =ABS(IFERROR(P57,0)+IFERROR(Q57,0)) -> 18.122 | DF57: =ABS(IFERROR(AH57,0))+ABS(IFERROR(AK57,0))+IFERROR(W57,0) -> 71.98 | DG57: =IFERROR(M57,0)+IFERROR(N57,0)+IFERROR(O57,0)+IFERROR(P57,0) -> 558.762 | DH57: 2590.739
A58: 8739963006 | B58: 10739950443 | C58: 45937.468 | D58: 45940.73 | E58: TIKICLST113026319 | F58: 2410 | G58: 0 | H58: 2410 | I58: 3500 | J58: 884 | K58: Intra-State | L58: 5 | M58: 0 | N58: 57.38 | O58: 57.38 | P58: 11.476 | Q58: 2.295 | R58: 24.78 | S58: 597.198 | T58: -597.198 | U58: -610.969 | V58: -71.98 | W58: 0 | X58: 61 | Y58: 0 | Z58: 10.98 | AA58: 1 | AB58: LOCAL | AC58: 2616 | AD58: 1727.051 | AE58: 1727.051 | AF58: 0 | AG58: -610.969 | AH58: -71.98 | AI58: 2410 | AJ58: 0 | AL58: 0 | AM58: 45954 | AN58: 45954 | AO58: 45954 | AP58: 0 | AQ58: 2295.24 | AR58: 0 | AS58: 2.5 | AT58: 2.5 | AU58: 0 | AV58: 0.25 | AW58: 0.25 | AX58: 0.1 | AY58: Tiny Kingdom | AZ58: Clothing Set | BA58: 24.78 | BB58: 0 | BC58: 597.198 | BD58: -597.198 | BE58: 0 | BF58: 0 | BG58: 0 | BH58: 884 | BI58: 2.29524 | BL58: 0 | BM58: 0 | BN58: 0 | BO58: 0 | BP58: 0 | BS58: afe0176e-4109-464c-9945-010744b55acb | BT58: 11.476 | BU58: 0 | BV58: 2.295 | BW58: 0 | BX58: 0 | BY58: 0 | BZ58: 0 | CA58: 0 | CB58: 0 | CC58: 0 | CD58: 0 | CE58: 0 | CF58: 0 | CG58: 0 | CH58: 0 | CI58: 1727.051 | CJ58: 0 | CK58: 0 | CL58: 0 | CM58: 0 | CN58: 0 | CO58: 0 | CP58: 0 | CQ58: 0 | CR58: 0 | CS58: 0 | CT58: 0 | CU58: 0 | CV58: 0 | CW58: 0 | CX58: 0 | CY58: 0 | CZ58: 0 | DA58: 0 | DB58: 0 | DC58: =IFERROR(G58,0)+IFERROR(H58,0) -> 2410 | DD58: =ABS(IFERROR(T58,0)) -> 597.198 | DE58: =ABS(IFERROR(P58,0)+IFERROR(Q58,0)) -> 13.771 | DF58: =ABS(IFERROR(AH58,0))+ABS(IFERROR(AK58,0))+IFERROR(W58,0) -> 71.98 | DG58: =IFERROR(M58,0)+IFERROR(N58,0)+IFERROR(O58,0)+IFERROR(P58,0) -> 126.236 | DH58: 1727.051
A59: 8728913393 | B59: 10728869603 | C59: 45933.481 | D59: 45935.515 | E59: BETYDRSS74936946 | F59: 1644 | G59: 0 | H59: 1644 | I59: 3850 | J59: 2035 | K59: Intra-State | L59: 5 | M59: 0 | N59: 39.14 | O59: 39.14 | P59: 7.829 | Q59: 1.566 | R59: 33.04 | S59: 543.178 | T59: -543.178 | U59: -552.573 | V59: -53.1 | W59: 0 | X59: 45 | Y59: 0 | Z59: 8.1 | AA59: 1 | AB59: LOCAL | AC59: 1815 | AD59: 1038.327 | AE59: 1038.327 | AF59: 0 | AG59: -552.573 | AH59: -53.1 | AI59: 1644 | AJ59: 0 | AL59: 0 | AM59: 45953 | AN59: 45953 | AO59: 45953 | AP59: 0 | AQ59: 1565.72 | AR59: 0 | AS59: 2.5 | AT59: 2.5 | AU59: 0 | AV59: 0.25 | AW59: 0.25 | AX59: 0.1 | AY59: BETTY | AZ59: Dresses | BA59: 33.04 | BB59: 0 | BC59: 543.178 | BD59: -543.178 | BE59: 0 | BF59: 0 | BG59: 0 | BH59: 2035 | BI59: 1.56572 | BL59: 0 | BM59: 0 | BN59: 0 | BO59: 0 | BP59: 0 | BS59: 4eecf3df-71fd-4af2-a494-8ff649206afb | BT59: 7.829 | BU59: 0 | BV59: 1.566 | BW59: 0 | BX59: 0 | BY59: 0 | BZ59: 0 | CA59: 0 | CB59: 0 | CC59: 0 | CD59: 0 | CE59: 0 | CF59: 0 | CG59: 0 | CH59: 1038.327 | CI59: 0 | CJ59: 0 | CK59: 0 | CL59: 0 | CM59: 0 | CN59: 0 | CO59: 0 | CP59: 0 | CQ59: 0 | CR59: 0 | CS59: 0 | CT59: 0 | CU59: 0 | CV59: 0 | CW59: 0 | CX59: 0 | CY59: 0 | CZ59: 0 | DA59: 0 | DB59: 0 | DC59: =IFERROR(G59,0)+IFERROR(H59,0) -> 1644 | DD59: =ABS(IFERROR(T59,0)) -> 543.178 | DE59: =ABS(IFERROR(P59,0)+IFERROR(Q59,0)) -> 9.395 | DF59: =ABS(IFERROR(AH59,0))+ABS(IFERROR(AK59,0))+IFERROR(W59,0) -> 53.1 | DG59: =IFERROR(M59,0)+IFERROR(N59,0)+IFERROR(O59,0)+IFERROR(P59,0) -> 86.109 | DH59: 1038.327
A60: 8746617713 | B60: 10746638683 | C60: 45940.808 | D60: 45943.475 | E60: BETYDRSS67133058 | F60: 391 | G60: 0 | H60: 391 | I60: 2750 | J60: 2300 | K60: Intra-State | L60: 5 | M60: 0 | N60: 9.31 | O60: 9.31 | P60: 1.862 | Q60: 0.372 | R60: 2.36 | S60: 9.228 | T60: -9.228 | U60: -11.462 | V60: -31.86 | W60: 0 | X60: 27 | Y60: 0 | Z60: 4.86 | AA60: 1 | AB60: LOCAL | AC60: 450 | AD60: 347.678 | AE60: 347.678 | AF60: 0 | AG60: -11.462 | AH60: -31.86 | AI60: 391 | AJ60: 0 | AL60: 0 | AM60: 45957 | AN60: 45957 | AO60: 45957 | AP60: 0 | AQ60: 372.38 | AR60: 0 | AS60: 2.5 | AT60: 2.5 | AU60: 0 | AV60: 0.25 | AW60: 0.25 | AX60: 0.1 | AY60: BETTY | AZ60: Dresses | BA60: 2.36 | BB60: 0 | BC60: 9.228 | BD60: -9.228 | BE60: 0 | BF60: 0 | BG60: 0 | BH60: 2300 | BI60: 0.37238 | BL60: 0 | BM60: 0 | BN60: 0 | BO60: 0 | BP60: 0 | BS60: 9f98fc48-bc35-4aae-b12c-74b92bd2514b | BT60: 1.862 | BU60: 0 | BV60: 0.372 | BW60: 0 | BX60: 0 | BY60: 0 | BZ60: 0 | CA60: 0 | CB60: 0 | CC60: 0 | CD60: 0 | CE60: 0 | CF60: 0 | CG60: 0 | CH60: 0 | CI60: 0 | CJ60: 347.678 | CK60: 0 | CL60: 0 | CM60: 0 | CN60: 0 | CO60: 0 | CP60: 0 | CQ60: 0 | CR60: 0 | CS60: 0 | CT60: 0 | CU60: 0 | CV60: 0 | CW60: 0 | CX60: 0 | CY60: 0 | CZ60: 0 | DA60: 0 | DB60: 0 | DC60: =IFERROR(G60,0)+IFERROR(H60,0) -> 391 | DD60: =ABS(IFERROR(T60,0)) -> 9.228 | DE60: =ABS(IFERROR(P60,0)+IFERROR(Q60,0)) -> 2.234 | DF60: =ABS(IFERROR(AH60,0))+ABS(IFERROR(AK60,0))+IFERROR(W60,0) -> 31.86 | DG60: =IFERROR(M60,0)+IFERROR(N60,0)+IFERROR(O60,0)+IFERROR(P60,0) -> 20.482 | DH60: 347.678
A61: 8749897675 | B61: 10749927557 | C61: 45942.467 | D61: 45945.435 | E61: TIKIDRSS116452710 | F61: 2610 | G61: 0 | H61: 2610 | I61: 3500 | J61: 535 | K61: Intra-State | L61: 5 | M61: 0 | N61: 62.14 | O61: 62.14 | P61: 12.429 | Q61: 2.486 | R61: 21.24 | S61: 554.364 | T61: -554.364 | U61: -569.279 | V61: -71.98 | W61: 0 | X61: 61 | Y61: 0 | Z61: 10.98 | AA61: 1 | AB61: LOCAL | AC61: 2816 | AD61: 1968.741 | AE61: 1968.741 | AF61: 0 | AG61: -569.279 | AH61: -71.98 | AI61: 2610 | AJ61: 0 | AL61: 0 | AM61: 45959 | AN61: 45959 | AO61: 45959 | AP61: 0 | AQ61: 2485.72 | AR61: 0 | AS61: 2.5 | AT61: 2.5 | AU61: 0 | AV61: 0.25 | AW61: 0.25 | AX61: 0.1 | AY61: Tiny Kingdom | AZ61: Dresses | BA61: 21.24 | BB61: 0 | BC61: 554.364 | BD61: -554.364 | BE61: 0 | BF61: 0 | BG61: 0 | BH61: 535 | BI61: 2.48572 | BL61: 0 | BM61: 0 | BN61: 0 | BO61: 0 | BP61: 0 | BS61: f1865d7a-c767-41ba-9f71-75f1def1bddf | BT61: 12.429 | BU61: 0 | BV61: 2.486 | BW61: 0 | BX61: 0 | BY61: 0 | BZ61: 0 | CA61: 0 | CB61: 0 | CC61: 0 | CD61: 0 | CE61: 0 | CF61: 0 | CG61: 0 | CH61: 0 | CI61: 0 | CJ61: 0 | CK61: 0 | CL61: 1968.741 | CM61: 0 | CN61: 0 | CO61: 0 | CP61: 0 | CQ61: 0 | CR61: 0 | CS61: 0 | CT61: 0 | CU61: 0 | CV61: 0 | CW61: 0 | CX61: 0 | CY61: 0 | CZ61: 0 | DA61: 0 | DB61: 0 | DC61: =IFERROR(G61,0)+IFERROR(H61,0) -> 2610 | DD61: =ABS(IFERROR(T61,0)) -> 554.364 | DE61: =ABS(IFERROR(P61,0)+IFERROR(Q61,0)) -> 14.915 | DF61: =ABS(IFERROR(AH61,0))+ABS(IFERROR(AK61,0))+IFERROR(W61,0) -> 71.98 | DG61: =IFERROR(M61,0)+IFERROR(N61,0)+IFERROR(O61,0)+IFERROR(P61,0) -> 136.709 | DH61: 1968.741
A62: 8730440748 | B62: 10730401529 | C62: 45933.806 | D62: 45938.649 | E62: TIKICLST113026340 | F62: 3594 | G62: 0 | H62: 3594 | I62: 4000 | J62: 200 | K62: Inter-State | L62: 18 | M62: 548.24 | N62: 0 | O62: 0 | P62: 15.229 | Q62: 3.046 | R62: 25.96 | S62: 933.002 | T62: -933.002 | U62: -951.277 | V62: -71.98 | W62: 0 | X62: 61 | Y62: 0 | Z62: 10.98 | AA62: 1 | AB62: NATIONAL | AC62: 3800 | AD62: 2570.743 | AE62: 2570.743 | AF62: 0 | AG62: -951.277 | AH62: -71.98 | AI62: 3594 | AJ62: 0 | AL62: 0 | AM62: 45953 | AN62: 45953 | AO62: 45953 | AP62: 0 | AQ62: 3045.76 | AR62: 18 | AS62: 0 | AT62: 0 | AU62: 0.5 | AV62: 0 | AW62: 0 | AX62: 0.1 | AY62: Tiny Kingdom | AZ62: Kurta Sets | BA62: 25.96 | BB62: 0 | BC62: 933.002 | BD62: -933.002 | BE62: 0 | BF62: 0 | BG62: 0 | BH62: 200 | BI62: 3.04576 | BL62: 0 | BM62: 0 | BN62: 0 | BO62: 0 | BP62: 0 | BS62: f57393c0-2ca0-4b9f-be1b-592abd1bdab8 | BT62: 15.229 | BU62: 0 | BV62: 3.046 | BW62: 0 | BX62: 0 | BY62: 0 | BZ62: 0 | CA62: 0 | CB62: 0 | CC62: 0 | CD62: 0 | CE62: 0 | CF62: 0 | CG62: 0 | CH62: 2570.743 | CI62: 0 | CJ62: 0 | CK62: 0 | CL62: 0 | CM62: 0 | CN62: 0 | CO62: 0 | CP62: 0 | CQ62: 0 | CR62: 0 | CS62: 0 | CT62: 0 | CU62: 0 | CV62: 0 | CW62: 0 | CX62: 0 | CY62: 0 | CZ62: 0 | DA62: 0 | DB62: 0 | DC62: =IFERROR(G62,0)+IFERROR(H62,0) -> 3594 | DD62: =ABS(IFERROR(T62,0)) -> 933.002 | DE62: =ABS(IFERROR(P62,0)+IFERROR(Q62,0)) -> 18.275 | DF62: =ABS(IFERROR(AH62,0))+ABS(IFERROR(AK62,0))+IFERROR(W62,0) -> 71.98 | DG62: =IFERROR(M62,0)+IFERROR(N62,0)+IFERROR(O62,0)+IFERROR(P62,0) -> 563.469 | DH62: 2570.743
A63: 8735756275 | B63: 10735729297 | C63: 45935.731 | D63: 45943.478 | E63: TNBYDRSS79060638 | F63: 1064 | G63: 301.786 | H63: 762.214 | I63: 2750 | J63: 1450 | K63: Inter-State | L63: 5 | M63: 50.67 | N63: 0 | O63: 0 | P63: 5.067 | Q63: 1.013 | R63: 27.14 | S63: 288.77 | T63: -288.77 | U63: -294.85 | V63: -53.1 | W63: 0 | X63: 45 | Y63: 0 | Z63: 8.1 | AA63: 1 | AB63: NATIONAL | AC63: 1235 | AD63: 716.05 | AE63: 716.05 | AF63: 0 | AG63: -211.221 | AH63: -38.03966 | AI63: 762.214 | AJ63: -83.629 | AK63: -15.06034 | AL63: 301.786 | AM63: 45957 | AN63: 45957 | AO63: 45957 | AP63: 260 | AQ63: 1013.33 | AR63: 5 | AS63: 0 | AT63: 0 | AU63: 0.5 | AV63: 0 | AW63: 0 | AX63: 0.1 | AY63: Tiny Baby | AZ63: Dresses | BA63: 27.14 | BB63: 0 | BC63: 206.865 | BD63: -206.865 | BE63: 0 | BF63: 0 | BG63: 0 | BH63: 1450 | BI63: 1.01333 | BJ63: 27.14 | BK63: 0 | BL63: 81.905 | BM63: -81.905 | BN63: 0 | BO63: 0 | BP63: 0 | BQ63: 1450 | BR63: 1.01333 | BS63: a5f78186-8500-4616-b52b-16db67d92e34 | BT63: 3.63 | BU63: 1.437 | BV63: 0.726 | BW63: 0.287 | BX63: 0 | BY63: 0 | BZ63: 0 | CA63: 0 | CB63: 0 | CC63: 0 | CD63: 0 | CE63: 0 | CF63: 0 | CG63: 0 | CH63: 0 | CI63: 0 | CJ63: 716.05 | CK63: 0 | CL63: 0 | CM63: 0 | CN63: 0 | CO63: 0 | CP63: 0 | CQ63: 0 | CR63: 0 | CS63: 0 | CT63: 0 | CU63: 0 | CV63: 0 | CW63: 0 | CX63: 0 | CY63: 0 | CZ63: 0 | DA63: 0 | DB63: 0 | DC63: =IFERROR(G63,0)+IFERROR(H63,0) -> 1064 | DD63: =ABS(IFERROR(T63,0)) -> 288.77 | DE63: =ABS(IFERROR(P63,0)+IFERROR(Q63,0)) -> 6.08 | DF63: =ABS(IFERROR(AH63,0))+ABS(IFERROR(AK63,0))+IFERROR(W63,0) -> 53.1 | DG63: =IFERROR(M63,0)+IFERROR(N63,0)+IFERROR(O63,0)+IFERROR(P63,0) -> 55.737 | DH63: 716.05
A64: 8727960588 | B64: 10727916751 | C64: 45933.481 | D64: 45937.579 | E64: TIKIDRSS103325542 | F64: 2432 | G64: 0 | H64: 2432 | I64: 3500 | J64: 862 | K64: Inter-State | L64: 5 | M64: 115.81 | N64: 0 | O64: 0 | P64: 11.581 | Q64: 2.316 | R64: 21.24 | S64: 516.557 | T64: -516.557 | U64: -530.454 | V64: -71.98 | W64: 0 | X64: 61 | Y64: 0 | Z64: 10.98 | AA64: 1 | AB64: ZONAL | AC64: 2638 | AD64: 1829.566 | AE64: 1829.566 | AF64: 0 | AG64: -530.454 | AH64: -71.98 | AI64: 2432 | AJ64: 0 | AL64: 0 | AM64: 45953 | AN64: 45953 | AO64: 45953 | AP64: 0 | AQ64: 2316.19 | AR64: 5 | AS64: 0 | AT64: 0 | AU64: 0.5 | AV64: 0 | AW64: 0 | AX64: 0.1 | AY64: Tiny Kingdom | AZ64: Dresses | BA64: 21.24 | BB64: 0 | BC64: 516.557 | BD64: -516.557 | BE64: 0 | BF64: 0 | BG64: 0 | BH64: 862 | BI64: 2.31619 | BL64: 0 | BM64: 0 | BN64: 0 | BO64: 0 | BP64: 0 | BS64: 7f4c55f5-2ef2-46b4-a3c1-6ed397f15375 | BT64: 11.581 | BU64: 0 | BV64: 2.316 | BW64: 0 | BX64: 0 | BY64: 0 | BZ64: 0 | CA64: 0 | CB64: 0 | CC64: 0 | CD64: 0 | CE64: 0 | CF64: 0 | CG64: 0 | CH64: 1829.566 | CI64: 0 | CJ64: 0 | CK64: 0 | CL64: 0 | CM64: 0 | CN64: 0 | CO64: 0 | CP64: 0 | CQ64: 0 | CR64: 0 | CS64: 0 | CT64: 0 | CU64: 0 | CV64: 0 | CW64: 0 | CX64: 0 | CY64: 0 | CZ64: 0 | DA64: 0 | DB64: 0 | DC64: =IFERROR(G64,0)+IFERROR(H64,0) -> 2432 | DD64: =ABS(IFERROR(T64,0)) -> 516.557 | DE64: =ABS(IFERROR(P64,0)+IFERROR(Q64,0)) -> 13.897 | DF64: =ABS(IFERROR(AH64,0))+ABS(IFERROR(AK64,0))+IFERROR(W64,0) -> 71.98 | DG64: =IFERROR(M64,0)+IFERROR(N64,0)+IFERROR(O64,0)+IFERROR(P64,0) -> 127.391 | DH64: 1829.566
A65: 8670314920 | B65: 10670239088 | C65: 45915.472 | D65: 45919.447 | E65: TIKITOPS58784564 | F65: 499 | G65: 0 | H65: 499 | I65: 1250 | J65: 625 | K65: Inter-State | L65: 5 | M65: 23.76 | N65: 0 | O65: 0 | P65: 2.376 | Q65: 0.475 | R65: 9.44 | S65: 47.106 | T65: -47.106 | U65: -49.957 | V65: -31.86 | W65: 0 | X65: 27 | Y65: 0 | Z65: 4.86 | AA65: 1 | AB65: NATIONAL | AC65: 593 | AD65: 417.183 | AE65: 417.183 | AF65: 0 | AG65: -49.957 | AH65: -31.86 | AI65: 499 | AJ65: 0 | AL65: 0 | AM65: 45933 | AN65: 45933 | AO65: 45933 | AP65: 0 | AQ65: 475.24 | AR65: 5 | AS65: 0 | AT65: 0 | AU65: 0.5 | AV65: 0 | AW65: 0 | AX65: 0.1 | AY65: Tiny Kingdom | AZ65: Tops | BA65: 9.44 | BB65: 0 | BC65: 47.106 | BD65: -47.106 | BE65: 0 | BF65: 0 | BG65: 0 | BH65: 625 | BI65: 0.47524 | BL65: 0 | BM65: 0 | BN65: 0 | BO65: 0 | BP65: 0 | BS65: 4231f75b-7655-43a4-91aa-07b1a301bd9e | BT65: 2.376 | BU65: 0 | BV65: 0.475 | BW65: 0 | BX65: 417.183 | BY65: 0 | BZ65: 0 | CA65: 0 | CB65: 0 | CC65: 0 | CD65: 0 | CE65: 0 | CF65: 0 | CG65: 0 | CH65: 0 | CI65: 0 | CJ65: 0 | CK65: 0 | CL65: 0 | CM65: 0 | CN65: 0 | CO65: 0 | CP65: 0 | CQ65: 0 | CR65: 0 | CS65: 0 | CT65: 0 | CU65: 0 | CV65: 0 | CW65: 0 | CX65: 0 | CY65: 0 | CZ65: 0 | DA65: 0 | DB65: 0 | DC65: =IFERROR(G65,0)+IFERROR(H65,0) -> 499 | DD65: =ABS(IFERROR(T65,0)) -> 47.106 | DE65: =ABS(IFERROR(P65,0)+IFERROR(Q65,0)) -> 2.851 | DF65: =ABS(IFERROR(AH65,0))+ABS(IFERROR(AK65,0))+IFERROR(W65,0) -> 31.86 | DG65: =IFERROR(M65,0)+IFERROR(N65,0)+IFERROR(O65,0)+IFERROR(P65,0) -> 26.136 | DH65: 417.183
A66: 8673166572 | B66: 10673091014 | C66: 45916.46 | D66: 45922.498 | E66: TNBYDRSS63052850 | F66: 1204 | G66: 1204 | H66: 0 | I66: 2750 | J66: 1375 | K66: Inter-State | L66: 12 | M66: 129 | N66: 0 | O66: 0 | P66: 5.375 | Q66: 1.075 | R66: 27.14 | S66: 326.766 | T66: -326.766 | U66: -333.216 | V66: -53.1 | W66: 0 | X66: 45 | Y66: 0 | Z66: 8.1 | AA66: 1 | AB66: NATIONAL | AC66: 1375 | AD66: 817.684 | AE66: 817.684 | AF66: 0 | AG66: 0 | AI66: 0 | AJ66: -333.216 | AK66: -53.1 | AL66: 1204 | AP66: 0 | AQ66: 1075 | AR66: 12 | AS66: 0 | AT66: 0 | AU66: 0.5 | AV66: 0 | AW66: 0 | AX66: 0.1 | AY66: Tiny Baby | AZ66: Dresses | BC66: 0 | BD66: 0 | BE66: 0 | BF66: 0 | BG66: 0 | BJ66: 27.14 | BK66: 0 | BL66: 326.766 | BM66: -326.766 | BN66: 0 | BO66: 0 | BP66: 0 | BQ66: 1375 | BR66: 1.075 | BS66: 91fed8ac-d147-4a8b-99d4-e93aa2304cc1 | BT66: 0 | BU66: 5.375 | BV66: 0 | BW66: 1.075 | BX66: 0 | BY66: 817.684 | BZ66: 0 | CA66: 0 | CB66: 0 | CC66: 0 | CD66: 0 | CE66: 0 | CF66: 0 | CG66: 0 | CH66: 0 | CI66: 0 | CJ66: 0 | CK66: 0 | CL66: 0 | CM66: 0 | CN66: 0 | CO66: 0 | CP66: 0 | CQ66: 0 | CR66: 0 | CS66: 0 | CT66: 0 | CU66: 0 | CV66: 0 | CW66: 0 | CX66: 0 | CY66: 0 | CZ66: 0 | DA66: 0 | DB66: 0 | DC66: =IFERROR(G66,0)+IFERROR(H66,0) -> 1204 | DD66: =ABS(IFERROR(T66,0)) -> 326.766 | DE66: =ABS(IFERROR(P66,0)+IFERROR(Q66,0)) -> 6.45 | DF66: =ABS(IFERROR(AH66,0))+ABS(IFERROR(AK66,0))+IFERROR(W66,0) -> 53.1 | DG66: =IFERROR(M66,0)+IFERROR(N66,0)+IFERROR(O66,0)+IFERROR(P66,0) -> 134.375 | DH66: 817.684
A67: 8746509434 | B67: 10746528679 | C67: 45940.808 | D67: 45944.766 | E67: BETYLHNC82606732 | F67: 2619 | G67: 0 | H67: 2619 | I67: 5000 | J67: 2175 | K67: Inter-State | L67: 5 | M67: 124.71 | N67: 0 | O67: 0 | P67: 12.471 | Q67: 2.494 | R67: 30.68 | S67: 803.509 | T67: -803.509 | U67: -818.474 | V67: -71.98 | W67: 0 | X67: 61 | Y67: 0 | Z67: 10.98 | AA67: 1 | AB67: ZONAL | AC67: 2825 | AD67: 1728.546 | AE67: 1728.546 | AF67: 0 | AG67: -818.474 | AH67: -71.98 | AI67: 2619 | AJ67: 0 | AL67: 0 | AM67: 45958 | AN67: 45958 | AO67: 45958 | AP67: 0 | AQ67: 2494.29 | AR67: 5 | AS67: 0 | AT67: 0 | AU67: 0.5 | AV67: 0 | AW67: 0 | AX67: 0.1 | AY67: BETTY | AZ67: Lehenga Choli | BA67: 30.68 | BB67: 0 | BC67: 803.509 | BD67: -803.509 | BE67: 0 | BF67: 0 | BG67: 0 | BH67: 2175 | BI67: 2.49429 | BL67: 0 | BM67: 0 | BN67: 0 | BO67: 0 | BP67: 0 | BS67: 1c2f7348-5b79-423f-99ab-5d4d19f86c55 | BT67: 12.471 | BU67: 0 | BV67: 2.494 | BW67: 0 | BX67: 0 | BY67: 0 | BZ67: 0 | CA67: 0 | CB67: 0 | CC67: 0 | CD67: 0 | CE67: 0 | CF67: 0 | CG67: 0 | CH67: 0 | CI67: 0 | CJ67: 0 | CK67: 1728.546 | CL67: 0 | CM67: 0 | CN67: 0 | CO67: 0 | CP67: 0 | CQ67: 0 | CR67: 0 | CS67: 0 | CT67: 0 | CU67: 0 | CV67: 0 | CW67: 0 | CX67: 0 | CY67: 0 | CZ67: 0 | DA67: 0 | DB67: 0 | DC67: =IFERROR(G67,0)+IFERROR(H67,0) -> 2619 | DD67: =ABS(IFERROR(T67,0)) -> 803.509 | DE67: =ABS(IFERROR(P67,0)+IFERROR(Q67,0)) -> 14.965 | DF67: =ABS(IFERROR(AH67,0))+ABS(IFERROR(AK67,0))+IFERROR(W67,0) -> 71.98 | DG67: =IFERROR(M67,0)+IFERROR(N67,0)+IFERROR(O67,0)+IFERROR(P67,0) -> 137.181 | DH67: 1728.546
A68: 8728105852 | B68: 10728062054 | C68: 45933.481 | D68: 45935.855 | E68: TNBYDRSS112709047 | F68: 2549 | G68: 0 | H68: 2549 | I68: 3250 | J68: 495 | K68: Intra-State | L68: 5 | M68: 0 | N68: 60.69 | O68: 60.69 | P68: 12.138 | Q68: 2.428 | R68: 25.96 | S68: 661.72 | T68: -661.72 | U68: -676.286 | V68: -71.98 | W68: 0 | X68: 61 | Y68: 0 | Z68: 10.98 | AA68: 1 | AB68: LOCAL | AC68: 2755 | AD68: 1800.734 | AE68: 1800.734 | AF68: 0 | AG68: -676.286 | AH68: -71.98 | AI68: 2549 | AJ68: 0 | AL68: 0 | AM68: 45953 | AN68: 45953 | AO68: 45953 | AP68: 0 | AQ68: 2427.62 | AR68: 0 | AS68: 2.5 | AT68: 2.5 | AU68: 0 | AV68: 0.25 | AW68: 0.25 | AX68: 0.1 | AY68: Tiny Baby | AZ68: Dresses | BA68: 25.96 | BB68: 0 | BC68: 661.72 | BD68: -661.72 | BE68: 0 | BF68: 0 | BG68: 0 | BH68: 495 | BI68: 2.42762 | BL68: 0 | BM68: 0 | BN68: 0 | BO68: 0 | BP68: 0 | BS68: c270bbe8-8dbe-44e6-a129-c44fb7e0864a | BT68: 12.138 | BU68: 0 | BV68: 2.428 | BW68: 0 | BX68: 0 | BY68: 0 | BZ68: 0 | CA68: 0 | CB68: 0 | CC68: 0 | CD68: 0 | CE68: 0 | CF68: 0 | CG68: 0 | CH68: 1800.734 | CI68: 0 | CJ68: 0 | CK68: 0 | CL68: 0 | CM68: 0 | CN68: 0 | CO68: 0 | CP68: 0 | CQ68: 0 | CR68: 0 | CS68: 0 | CT68: 0 | CU68: 0 | CV68: 0 | CW68: 0 | CX68: 0 | CY68: 0 | CZ68: 0 | DA68: 0 | DB68: 0 | DC68: =IFERROR(G68,0)+IFERROR(H68,0) -> 2549 | DD68: =ABS(IFERROR(T68,0)) -> 661.72 | DE68: =ABS(IFERROR(P68,0)+IFERROR(Q68,0)) -> 14.566 | DF68: =ABS(IFERROR(AH68,0))+ABS(IFERROR(AK68,0))+IFERROR(W68,0) -> 71.98 | DG68: =IFERROR(M68,0)+IFERROR(N68,0)+IFERROR(O68,0)+IFERROR(P68,0) -> 133.518 | DH68: 1800.734
A69: 8680270452 | B69: 10680196035 | C69: 45918.544 | D69: 45923.828 | E69: TNBYCLST96143590 | F69: 1994 | G69: 1977.941 | H69: 16.059 | I69: 2750 | J69: 550 | K69: Inter-State | L69: 12 | M69: 213.64 | N69: 0 | O69: 0 | P69: 8.902 | Q69: 1.78 | R69: 27.14 | S69: 541.171 | T69: -541.171 | U69: -551.853 | V69: -53.1 | W69: 0 | X69: 45 | Y69: 0 | Z69: 8.1 | AA69: 1 | AB69: NATIONAL | AC69: 2200 | AD69: 1389.047 | AE69: 1389.047 | AF69: 0 | AG69: -4.444 | AH69: -0.42716 | AI69: 16.059 | AJ69: -547.409 | AK69: -52.67284 | AL69: 1977.941 | AM69: 45938 | AN69: 45938 | AO69: 45938 | AP69: 0 | AQ69: 1780.36 | AR69: 12 | AS69: 0 | AT69: 0 | AU69: 0.5 | AV69: 0 | AW69: 0 | AX69: 0.1 | AY69: Tiny Baby | AZ69: Clothing Set | BA69: 27.14 | BB69: 0 | BC69: 4.358 | BD69: -4.358 | BE69: 0 | BF69: 0 | BG69: 0 | BH69: 550 | BI69: 1.78036 | BJ69: 27.14 | BK69: 0 | BL69: 536.813 | BM69: -536.813 | BN69: 0 | BO69: 0 | BP69: 0 | BQ69: 550 | BR69: 1.78036 | BS69: 4ef0e60d-675f-4aab-af4d-b379e96f377b | BT69: 0.072 | BU69: 8.83 | BV69: 0.014 | BW69: 1.766 | BX69: 0 | BY69: 0 | BZ69: 1389.047 | CA69: 0 | CB69: 0 | CC69: 0 | CD69: 0 | CE69: 0 | CF69: 0 | CG69: 0 | CH69: 0 | CI69: 0 | CJ69: 0 | CK69: 0 | CL69: 0 | CM69: 0 | CN69: 0 | CO69: 0 | CP69: 0 | CQ69: 0 | CR69: 0 | CS69: 0 | CT69: 0 | CU69: 0 | CV69: 0 | CW69: 0 | CX69: 0 | CY69: 0 | CZ69: 0 | DA69: 0 | DB69: 0 | DC69: =IFERROR(G69,0)+IFERROR(H69,0) -> 1994 | DD69: =ABS(IFERROR(T69,0)) -> 541.171 | DE69: =ABS(IFERROR(P69,0)+IFERROR(Q69,0)) -> 10.682 | DF69: =ABS(IFERROR(AH69,0))+ABS(IFERROR(AK69,0))+IFERROR(W69,0) -> 53.1 | DG69: =IFERROR(M69,0)+IFERROR(N69,0)+IFERROR(O69,0)+IFERROR(P69,0) -> 222.542 | DH69: 1389.047
A70: 8673241096 | B70: 10673165555 | C70: 45916.46 | D70: 45920.501 | E70: TIKICLST103607750 | F70: 3169 | G70: 0 | H70: 3169 | I70: 4500 | J70: 1125 | K70: Intra-State | L70: 12 | M70: 0 | N70: 169.77 | O70: 169.77 | P70: 14.147 | Q70: 2.829 | R70: 25.96 | S70: 822.672 | T70: -822.672 | U70: -839.648 | V70: -71.98 | W70: 0 | X70: 61 | Y70: 0 | Z70: 10.98 | AA70: 1 | AB70: LOCAL | AC70: 3375 | AD70: 2257.372 | AE70: 2257.372 | AF70: 0 | AG70: -839.648 | AH70: -71.98 | AI70: 3169 | AJ70: 0 | AL70: 0 | AM70: 45936 | AN70: 45936 | AO70: 45936 | AP70: 0 | AQ70: 2829.46 | AR70: 0 | AS70: 6 | AT70: 6 | AU70: 0 | AV70: 0.25 | AW70: 0.25 | AX70: 0.1 | AY70: Tiny Kingdom | AZ70: Kurta Sets | BA70: 25.96 | BB70: 0 | BC70: 822.672 | BD70: -822.672 | BE70: 0 | BF70: 0 | BG70: 0 | BH70: 1125 | BI70: 2.82946 | BL70: 0 | BM70: 0 | BN70: 0 | BO70: 0 | BP70: 0 | BS70: ff87481d-59a5-4baf-a94a-3269c471d9c2 | BT70: 14.147 | BU70: 0 | BV70: 2.829 | BW70: 0 | BX70: 0 | BY70: 2257.372 | BZ70: 0 | CA70: 0 | CB70: 0 | CC70: 0 | CD70: 0 | CE70: 0 | CF70: 0 | CG70: 0 | CH70: 0 | CI70: 0 | CJ70: 0 | CK70: 0 | CL70: 0 | CM70: 0 | CN70: 0 | CO70: 0 | CP70: 0 | CQ70: 0 | CR70: 0 | CS70: 0 | CT70: 0 | CU70: 0 | CV70: 0 | CW70: 0 | CX70: 0 | CY70: 0 | CZ70: 0 | DA70: 0 | DB70: 0 | DC70: =IFERROR(G70,0)+IFERROR(H70,0) -> 3169 | DD70: =ABS(IFERROR(T70,0)) -> 822.672 | DE70: =ABS(IFERROR(P70,0)+IFERROR(Q70,0)) -> 16.976 | DF70: =ABS(IFERROR(AH70,0))+ABS(IFERROR(AK70,0))+IFERROR(W70,0) -> 71.98 | DG70: =IFERROR(M70,0)+IFERROR(N70,0)+IFERROR(O70,0)+IFERROR(P70,0) -> 353.687 | DH70: 2257.372
A71: 8667562183 | B71: 10667486277 | C71: 45915.472 | D71: 45918.497 | E71: TIKILHNC116454178 | F71: 2994 | G71: 0 | H71: 2994 | I71: 4000 | J71: 800 | K71: Intra-State | L71: 12 | M71: 0 | N71: 160.39 | O71: 160.39 | P71: 13.366 | Q71: 2.673 | R71: 24.78 | S71: 741.913 | T71: -741.913 | U71: -757.952 | V71: -71.98 | W71: 0 | X71: 61 | Y71: 0 | Z71: 10.98 | AA71: 1 | AB71: LOCAL | AC71: 3200 | AD71: 2164.068 | AE71: 2164.068 | AF71: 0 | AG71: -757.952 | AH71: -71.98 | AI71: 2994 | AJ71: 0 | AL71: 0 | AM71: 45933 | AN71: 45933 | AO71: 45933 | AP71: 0 | AQ71: 2673.22 | AR71: 0 | AS71: 6 | AT71: 6 | AU71: 0 | AV71: 0.25 | AW71: 0.25 | AX71: 0.1 | AY71: Tiny Kingdom | AZ71: Lehenga Choli | BA71: 24.78 | BB71: 0 | BC71: 741.913 | BD71: -741.913 | BE71: 0 | BF71: 0 | BG71: 0 | BH71: 800 | BI71: 2.67322 | BL71: 0 | BM71: 0 | BN71: 0 | BO71: 0 | BP71: 0 | BS71: 64ed14f8-e923-4676-8103-49ff2784d9a7 | BT71: 13.366 | BU71: 0 | BV71: 2.673 | BW71: 0 | BX71: 2164.068 | BY71: 0 | BZ71: 0 | CA71: 0 | CB71: 0 | CC71: 0 | CD71: 0 | CE71: 0 | CF71: 0 | CG71: 0 | CH71: 0 | CI71: 0 | CJ71: 0 | CK71: 0 | CL71: 0 | CM71: 0 | CN71: 0 | CO71: 0 | CP71: 0 | CQ71: 0 | CR71: 0 | CS71: 0 | CT71: 0 | CU71: 0 | CV71: 0 | CW71: 0 | CX71: 0 | CY71: 0 | CZ71: 0 | DA71: 0 | DB71: 0 | DC71: =IFERROR(G71,0)+IFERROR(H71,0) -> 2994 | DD71: =ABS(IFERROR(T71,0)) -> 741.913 | DE71: =ABS(IFERROR(P71,0)+IFERROR(Q71,0)) -> 16.039 | DF71: =ABS(IFERROR(AH71,0))+ABS(IFERROR(AK71,0))+IFERROR(W71,0) -> 71.98 | DG71: =IFERROR(M71,0)+IFERROR(N71,0)+IFERROR(O71,0)+IFERROR(P71,0) -> 334.146 | DH71: 2164.068
A72: 8674661455 | B72: 10674586005 | C72: 45916.46 | D72: 45927.621 | E72: TIKICLST100048545 | F72: 1079 | G72: 1079 | H72: 0 | I72: 2500 | J72: 1250 | K72: Inter-State | L72: 12 | M72: 115.61 | N72: 0 | O72: 0 | P72: 4.817 | Q72: 0.963 | R72: 25.96 | S72: 280.108 | T72: -280.108 | U72: -285.888 | V72: -53.1 | W72: 0 | X72: 45 | Y72: 0 | Z72: 8.1 | AA72: 1 | AB72: NATIONAL | AC72: 1250 | AD72: 740.012 | AE72: 740.012 | AF72: 0 | AG72: 0 | AI72: 0 | AJ72: -285.888 | AK72: -53.1 | AL72: 1079 | AP72: 0 | AQ72: 963.39 | AR72: 12 | AS72: 0 | AT72: 0 | AU72: 0.5 | AV72: 0 | AW72: 0 | AX72: 0.1 | AY72: Tiny Kingdom | AZ72: Kurta Sets | BC72: 0 | BD72: 0 | BE72: 0 | BF72: 0 | BG72: 0 | BJ72: 25.96 | BK72: 0 | BL72: 280.108 | BM72: -280.108 | BN72: 0 | BO72: 0 | BP72: 0 | BQ72: 1250 | BR72: 0.96339 | BS72: e056339c-e872-4fa1-9570-917888bb4b9a | BT72: 0 | BU72: 4.817 | BV72: 0 | BW72: 0.963 | BX72: 0 | BY72: 0 | BZ72: 0 | CA72: 0 | CB72: 0 | CC72: 0 | CD72: 740.012 | CE72: 0 | CF72: 0 | CG72: 0 | CH72: 0 | CI72: 0 | CJ72: 0 | CK72: 0 | CL72: 0 | CM72: 0 | CN72: 0 | CO72: 0 | CP72: 0 | CQ72: 0 | CR72: 0 | CS72: 0 | CT72: 0 | CU72: 0 | CV72: 0 | CW72: 0 | CX72: 0 | CY72: 0 | CZ72: 0 | DA72: 0 | DB72: 0 | DC72: =IFERROR(G72,0)+IFERROR(H72,0) -> 1079 | DD72: =ABS(IFERROR(T72,0)) -> 280.108 | DE72: =ABS(IFERROR(P72,0)+IFERROR(Q72,0)) -> 5.78 | DF72: =ABS(IFERROR(AH72,0))+ABS(IFERROR(AK72,0))+IFERROR(W72,0) -> 53.1 | DG72: =IFERROR(M72,0)+IFERROR(N72,0)+IFERROR(O72,0)+IFERROR(P72,0) -> 120.427 | DH72: 740.012
A73: 8729589626 | B73: 10729545839 | C73: 45933.481 | D73: 45937.449 | E73: TIKICLST116340919 | F73: 3743 | G73: 0 | H73: 3742.99 | I73: 4000 | J73: 51 | K73: Inter-State | L73: 18 | M73: 570.97 | N73: 0 | O73: 0 | P73: 15.86 | Q73: 3.172 | R73: 24.78 | S73: 927.513 | T73: -927.513 | U73: -946.545 | V73: -71.98 | W73: 0 | X73: 61 | Y73: 0 | Z73: 10.98 | AA73: 1 | AB73: NATIONAL | AC73: 3949 | AD73: 2724.465 | AE73: 2724.465 | AF73: 0 | AG73: -946.545 | AH73: -71.98 | AI73: 3742.99 | AJ73: 0 | AL73: 0 | AM73: 45953 | AN73: 45953 | AO73: 45953 | AP73: 0 | AQ73: 3172.03 | AR73: 18 | AS73: 0 | AT73: 0 | AU73: 0.5 | AV73: 0 | AW73: 0 | AX73: 0.1 | AY73: Tiny Kingdom | AZ73: Clothing Set | BA73: 24.78 | BB73: 0 | BC73: 927.513 | BD73: -927.513 | BE73: 0 | BF73: 0 | BG73: 0 | BH73: 51 | BI73: 3.17203 | BL73: 0 | BM73: 0 | BN73: 0 | BO73: 0 | BP73: 0 | BS73: fe5e2309-6ffb-413f-afb4-da079ec6d7da | BT73: 15.86 | BU73: 0 | BV73: 3.172 | BW73: 0 | BX73: 0 | BY73: 0 | BZ73: 0 | CA73: 0 | CB73: 0 | CC73: 0 | CD73: 0 | CE73: 0 | CF73: 0 | CG73: 0 | CH73: 2724.465 | CI73: 0 | CJ73: 0 | CK73: 0 | CL73: 0 | CM73: 0 | CN73: 0 | CO73: 0 | CP73: 0 | CQ73: 0 | CR73: 0 | CS73: 0 | CT73: 0 | CU73: 0 | CV73: 0 | CW73: 0 | CX73: 0 | CY73: 0 | CZ73: 0 | DA73: 0 | DB73: 0 | DC73: =IFERROR(G73,0)+IFERROR(H73,0) -> 3742.99 | DD73: =ABS(IFERROR(T73,0)) -> 927.513 | DE73: =ABS(IFERROR(P73,0)+IFERROR(Q73,0)) -> 19.032 | DF73: =ABS(IFERROR(AH73,0))+ABS(IFERROR(AK73,0))+IFERROR(W73,0) -> 71.98 | DG73: =IFERROR(M73,0)+IFERROR(N73,0)+IFERROR(O73,0)+IFERROR(P73,0) -> 586.83 | DH73: 2724.465
A74: 8733552059 | B74: 10733520727 | C74: 45934.836 | D74: 45939.627 | E74: BETYCLST55835622 | F74: 2150 | G74: 0 | H74: 2150 | I74: 4800 | J74: 2444 | K74: Intra-State | L74: 5 | M74: 0 | N74: 51.19 | O74: 51.19 | P74: 10.238 | Q74: 2.048 | R74: 30.68 | S74: 659.62 | T74: -659.62 | U74: -671.906 | V74: -71.98 | W74: 0 | X74: 61 | Y74: 0 | Z74: 10.98 | AA74: 1 | AB74: LOCAL | AC74: 2356 | AD74: 1406.114 | AE74: 1406.114 | AF74: 0 | AG74: -671.906 | AH74: -71.98 | AI74: 2150 | AJ74: 0 | AL74: 0 | AM74: 45953 | AN74: 45953 | AO74: 45953 | AP74: 0 | AQ74: 2047.62 | AR74: 0 | AS74: 2.5 | AT74: 2.5 | AU74: 0 | AV74: 0.25 | AW74: 0.25 | AX74: 0.1 | AY74: BETTY | AZ74: Kurta Sets | BA74: 30.68 | BB74: 0 | BC74: 659.62 | BD74: -659.62 | BE74: 0 | BF74: 0 | BG74: 0 | BH74: 2444 | BI74: 2.04762 | BL74: 0 | BM74: 0 | BN74: 0 | BO74: 0 | BP74: 0 | BS74: 504b83a4-3bfa-4cde-8d39-4a8360f07c05 | BT74: 10.238 | BU74: 0 | BV74: 2.048 | BW74: 0 | BX74: 0 | BY74: 0 | BZ74: 0 | CA74: 0 | CB74: 0 | CC74: 0 | CD74: 0 | CE74: 0 | CF74: 0 | CG74: 0 | CH74: 1406.114 | CI74: 0 | CJ74: 0 | CK74: 0 | CL74: 0 | CM74: 0 | CN74: 0 | CO74: 0 | CP74: 0 | CQ74: 0 | CR74: 0 | CS74: 0 | CT74: 0 | CU74: 0 | CV74: 0 | CW74: 0 | CX74: 0 | CY74: 0 | CZ74: 0 | DA74: 0 | DB74: 0 | DC74: =IFERROR(G74,0)+IFERROR(H74,0) -> 2150 | DD74: =ABS(IFERROR(T74,0)) -> 659.62 | DE74: =ABS(IFERROR(P74,0)+IFERROR(Q74,0)) -> 12.286 | DF74: =ABS(IFERROR(AH74,0))+ABS(IFERROR(AK74,0))+IFERROR(W74,0) -> 71.98 | DG74: =IFERROR(M74,0)+IFERROR(N74,0)+IFERROR(O74,0)+IFERROR(P74,0) -> 112.618 | DH74: 1406.114
A75: 8738500127 | B75: 10738481531 | C75: 45936.573 | D75: 45941.614 | E75: BETYDRSS101248982 | F75: 3839 | G75: 0 | H75: 3839 | I75: 5500 | J75: 1455 | K75: Inter-State | L75: 18 | M75: 585.61 | N75: 0 | O75: 0 | P75: 16.267 | Q75: 3.253 | R75: 31.86 | S75: 1223.105 | T75: -1223.105 | U75: -1242.625 | V75: -71.98 | W75: 0 | X75: 61 | Y75: 0 | Z75: 10.98 | AA75: 1 | AB75: NATIONAL | AC75: 4045 | AD75: 2524.395 | AE75: 2524.395 | AF75: 0 | AG75: -1242.625 | AH75: -71.98 | AI75: 3839 | AJ75: 0 | AL75: 0 | AM75: 45957 | AN75: 45957 | AO75: 45957 | AP75: 0 | AQ75: 3253.39 | AR75: 18 | AS75: 0 | AT75: 0 | AU75: 0.5 | AV75: 0 | AW75: 0 | AX75: 0.1 | AY75: BETTY | AZ75: Dresses | BA75: 31.86 | BB75: 0 | BC75: 1223.105 | BD75: -1223.105 | BE75: 0 | BF75: 0 | BG75: 0 | BH75: 1455 | BI75: 3.25339 | BL75: 0 | BM75: 0 | BN75: 0 | BO75: 0 | BP75: 0 | BS75: 400dbd19-1c66-4f08-9d61-b7ef417d2c0c | BT75: 16.267 | BU75: 0 | BV75: 3.253 | BW75: 0 | BX75: 0 | BY75: 0 | BZ75: 0 | CA75: 0 | CB75: 0 | CC75: 0 | CD75: 0 | CE75: 0 | CF75: 0 | CG75: 0 | CH75: 0 | CI75: 0 | CJ75: 2524.395 | CK75: 0 | CL75: 0 | CM75: 0 | CN75: 0 | CO75: 0 | CP75: 0 | CQ75: 0 | CR75: 0 | CS75: 0 | CT75: 0 | CU75: 0 | CV75: 0 | CW75: 0 | CX75: 0 | CY75: 0 | CZ75: 0 | DA75: 0 | DB75: 0 | DC75: =IFERROR(G75,0)+IFERROR(H75,0) -> 3839 | DD75: =ABS(IFERROR(T75,0)) -> 1223.105 | DE75: =ABS(IFERROR(P75,0)+IFERROR(Q75,0)) -> 19.52 | DF75: =ABS(IFERROR(AH75,0))+ABS(IFERROR(AK75,0))+IFERROR(W75,0) -> 71.98 | DG75: =IFERROR(M75,0)+IFERROR(N75,0)+IFERROR(O75,0)+IFERROR(P75,0) -> 601.877 | DH75: 2524.395
A76: 8664041077 | B76: 10663965137 | C76: 45913.451 | D76: 45916.46 | E76: BETYDRSS93852544 | F76: 3119 | G76: 0 | H76: 3119 | I76: 5000 | J76: 1500 | K76: Inter-State | L76: 12 | M76: 334.18 | N76: 0 | O76: 0 | P76: 13.924 | Q76: 2.785 | R76: 31.86 | S76: 993.713 | T76: -993.713 | U76: -1010.422 | V76: -71.98 | W76: 0 | X76: 61 | Y76: 0 | Z76: 10.98 | AA76: 1 | AB76: ZONAL | AC76: 3325 | AD76: 2036.598 | AE76: 2036.598 | AF76: 0 | AG76: -1010.422 | AH76: -71.98 | AI76: 3119 | AJ76: 0 | AL76: 0 | AM76: 45933 | AN76: 45933 | AO76: 45933 | AP76: 0 | AQ76: 2784.82 | AR76: 12 | AS76: 0 | AT76: 0 | AU76: 0.5 | AV76: 0 | AW76: 0 | AX76: 0.1 | AY76: BETTY | AZ76: Dresses | BA76: 31.86 | BB76: 0 | BC76: 993.713 | BD76: -993.713 | BE76: 0 | BF76: 0 | BG76: 0 | BH76: 1500 | BI76: 2.78482 | BL76: 0 | BM76: 0 | BN76: 0 | BO76: 0 | BP76: 0 | BS76: a275f0fe-38e3-4bb3-8496-95d1b7a731da | BT76: 13.924 | BU76: 0 | BV76: 2.785 | BW76: 0 | BX76: 2036.598 | BY76: 0 | BZ76: 0 | CA76: 0 | CB76: 0 | CC76: 0 | CD76: 0 | CE76: 0 | CF76: 0 | CG76: 0 | CH76: 0 | CI76: 0 | CJ76: 0 | CK76: 0 | CL76: 0 | CM76: 0 | CN76: 0 | CO76: 0 | CP76: 0 | CQ76: 0 | CR76: 0 | CS76: 0 | CT76: 0 | CU76: 0 | CV76: 0 | CW76: 0 | CX76: 0 | CY76: 0 | CZ76: 0 | DA76: 0 | DB76: 0 | DC76: =IFERROR(G76,0)+IFERROR(H76,0) -> 3119 | DD76: =ABS(IFERROR(T76,0)) -> 993.713 | DE76: =ABS(IFERROR(P76,0)+IFERROR(Q76,0)) -> 16.709 | DF76: =ABS(IFERROR(AH76,0))+ABS(IFERROR(AK76,0))+IFERROR(W76,0) -> 71.98 | DG76: =IFERROR(M76,0)+IFERROR(N76,0)+IFERROR(O76,0)+IFERROR(P76,0) -> 348.104 | DH76: 2036.598
A77: 8741667042 | B77: 10741662108 | C77: 45938.424 | D77: 45942.772 | E77: BETYDRSS67133044 | F77: 391 | G77: 0 | H77: 391 | I77: 2750 | J77: 2300 | K77: Inter-State | L77: 5 | M77: 18.62 | N77: 0 | O77: 0 | P77: 1.862 | Q77: 0.372 | R77: 2.36 | S77: 9.228 | T77: -9.228 | U77: -11.462 | V77: -31.86 | W77: 0 | X77: 27 | Y77: 0 | Z77: 4.86 | AA77: 1 | AB77: NATIONAL | AC77: 450 | AD77: 347.678 | AE77: 347.678 | AF77: 0 | AG77: -11.462 | AH77: -31.86 | AI77: 391 | AJ77: 0 | AL77: 0 | AM77: 45957 | AN77: 45957 | AO77: 45957 | AP77: 0 | AQ77: 372.38 | AR77: 5 | AS77: 0 | AT77: 0 | AU77: 0.5 | AV77: 0 | AW77: 0 | AX77: 0.1 | AY77: BETTY | AZ77: Dresses | BA77: 2.36 | BB77: 0 | BC77: 9.228 | BD77: -9.228 | BE77: 0 | BF77: 0 | BG77: 0 | BH77: 2300 | BI77: 0.37238 | BL77: 0 | BM77: 0 | BN77: 0 | BO77: 0 | BP77: 0 | BS77: 923f6247-aa6b-4950-ac93-d58a5d3f6b8d | BT77: 1.862 | BU77: 0 | BV77: 0.372 | BW77: 0 | BX77: 0 | BY77: 0 | BZ77: 0 | CA77: 0 | CB77: 0 | CC77: 0 | CD77: 0 | CE77: 0 | CF77: 0 | CG77: 0 | CH77: 0 | CI77: 0 | CJ77: 347.678 | CK77: 0 | CL77: 0 | CM77: 0 | CN77: 0 | CO77: 0 | CP77: 0 | CQ77: 0 | CR77: 0 | CS77: 0 | CT77: 0 | CU77: 0 | CV77: 0 | CW77: 0 | CX77: 0 | CY77: 0 | CZ77: 0 | DA77: 0 | DB77: 0 | DC77: =IFERROR(G77,0)+IFERROR(H77,0) -> 391 | DD77: =ABS(IFERROR(T77,0)) -> 9.228 | DE77: =ABS(IFERROR(P77,0)+IFERROR(Q77,0)) -> 2.234 | DF77: =ABS(IFERROR(AH77,0))+ABS(IFERROR(AK77,0))+IFERROR(W77,0) -> 31.86 | DG77: =IFERROR(M77,0)+IFERROR(N77,0)+IFERROR(O77,0)+IFERROR(P77,0) -> 20.482 | DH77: 347.678
A78: 8731459709 | B78: 10731421656 | C78: 45934.437 | D78: 45939.451 | E78: TNBYCLST101412242 | F78: 2396 | G78: 2396 | H78: 0 | I78: 3250 | J78: 648 | K78: Inter-State | L78: 5 | M78: 114.1 | N78: 0 | O78: 0 | P78: 11.41 | Q78: 2.282 | R78: 25.96 | S78: 622.002 | T78: -622.002 | U78: -635.694 | V78: -71.98 | W78: 0 | X78: 61 | Y78: 0 | Z78: 10.98 | AA78: 1 | AB78: NATIONAL | AC78: 2602 | AD78: 1688.326 | AE78: 1688.326 | AF78: 0 | AG78: 0 | AI78: 0 | AJ78: -635.694 | AK78: -71.98 | AL78: 2396 | AP78: 0 | AQ78: 2281.9 | AR78: 5 | AS78: 0 | AT78: 0 | AU78: 0.5 | AV78: 0 | AW78: 0 | AX78: 0.1 | AY78: Tiny Baby | AZ78: Clothing Set | BC78: 0 | BD78: 0 | BE78: 0 | BF78: 0 | BG78: 0 | BJ78: 25.96 | BK78: 0 | BL78: 622.002 | BM78: -622.002 | BN78: 0 | BO78: 0 | BP78: 0 | BQ78: 648 | BR78: 2.2819 | BS78: 7309452e-3b72-42b8-ba4a-416c4156eee6 | BT78: 0 | BU78: 11.41 | BV78: 0 | BW78: 2.282 | BX78: 0 | BY78: 0 | BZ78: 0 | CA78: 0 | CB78: 0 | CC78: 0 | CD78: 0 | CE78: 0 | CF78: 0 | CG78: 0 | CH78: 1688.326 | CI78: 0 | CJ78: 0 | CK78: 0 | CL78: 0 | CM78: 0 | CN78: 0 | CO78: 0 | CP78: 0 | CQ78: 0 | CR78: 0 | CS78: 0 | CT78: 0 | CU78: 0 | CV78: 0 | CW78: 0 | CX78: 0 | CY78: 0 | CZ78: 0 | DA78: 0 | DB78: 0 | DC78: =IFERROR(G78,0)+IFERROR(H78,0) -> 2396 | DD78: =ABS(IFERROR(T78,0)) -> 622.002 | DE78: =ABS(IFERROR(P78,0)+IFERROR(Q78,0)) -> 13.692 | DF78: =ABS(IFERROR(AH78,0))+ABS(IFERROR(AK78,0))+IFERROR(W78,0) -> 71.98 | DG78: =IFERROR(M78,0)+IFERROR(N78,0)+IFERROR(O78,0)+IFERROR(P78,0) -> 125.51 | DH78: 1688.326
A79: 8732429950 | B79: 10732395094 | C79: 45934.56 | D79: 45939.64 | E79: TIKICLST113026325 | F79: 3104 | G79: 0 | H79: 3104 | I79: 3500 | J79: 190 | K79: Intra-State | L79: 18 | M79: 0 | N79: 236.75 | O79: 236.75 | P79: 13.153 | Q79: 2.631 | R79: 24.78 | S79: 769.171 | T79: -769.171 | U79: -784.955 | V79: -71.98 | W79: 0 | X79: 61 | Y79: 0 | Z79: 10.98 | AA79: 1 | AB79: LOCAL | AC79: 3310 | AD79: 2247.065 | AE79: 2247.065 | AF79: 0 | AG79: -784.955 | AH79: -71.98 | AI79: 3104 | AJ79: 0 | AL79: 0 | AM79: 45953 | AN79: 45953 | AO79: 45953 | AP79: 0 | AQ79: 2630.5 | AR79: 0 | AS79: 9 | AT79: 9 | AU79: 0 | AV79: 0.25 | AW79: 0.25 | AX79: 0.1 | AY79: Tiny Kingdom | AZ79: Clothing Set | BA79: 24.78 | BB79: 0 | BC79: 769.171 | BD79: -769.171 | BE79: 0 | BF79: 0 | BG79: 0 | BH79: 190 | BI79: 2.6305 | BL79: 0 | BM79: 0 | BN79: 0 | BO79: 0 | BP79: 0 | BS79: 28a691f3-a3f0-46a9-aac3-58f4b67e647d | BT79: 13.153 | BU79: 0 | BV79: 2.631 | BW79: 0 | BX79: 0 | BY79: 0 | BZ79: 0 | CA79: 0 | CB79: 0 | CC79: 0 | CD79: 0 | CE79: 0 | CF79: 0 | CG79: 0 | CH79: 2247.065 | CI79: 0 | CJ79: 0 | CK79: 0 | CL79: 0 | CM79: 0 | CN79: 0 | CO79: 0 | CP79: 0 | CQ79: 0 | CR79: 0 | CS79: 0 | CT79: 0 | CU79: 0 | CV79: 0 | CW79: 0 | CX79: 0 | CY79: 0 | CZ79: 0 | DA79: 0 | DB79: 0 | DC79: =IFERROR(G79,0)+IFERROR(H79,0) -> 3104 | DD79: =ABS(IFERROR(T79,0)) -> 769.171 | DE79: =ABS(IFERROR(P79,0)+IFERROR(Q79,0)) -> 15.784 | DF79: =ABS(IFERROR(AH79,0))+ABS(IFERROR(AK79,0))+IFERROR(W79,0) -> 71.98 | DG79: =IFERROR(M79,0)+IFERROR(N79,0)+IFERROR(O79,0)+IFERROR(P79,0) -> 486.653 | DH79: 2247.065
A80: 8705332926 | B80: 10705265422 | C80: 45924.787 | D80: 45931.792 | E80: BETYLHNC115587694 | F80: 6340.98 | G80: 0 | H80: 6341 | I80: 6950 | J80: 403 | K80: Intra-State | L80: 18 | M80: 0 | N80: 483.63 | O80: 483.63 | P80: 26.869 | Q80: 5.374 | R80: 30.68 | S80: 1945.419 | T80: -1945.419 | U80: -1977.662 | V80: -71.98 | W80: 0 | X80: 61 | Y80: 0 | Z80: 10.98 | AA80: 1 | AB80: LOCAL | AC80: 6547 | AD80: 4291.358 | AE80: 4291.358 | AF80: 0 | AG80: -1977.662 | AH80: -71.98 | AI80: 6341 | AJ80: 0 | AL80: 0 | AM80: 45945 | AN80: 45945 | AO80: 45945 | AP80: 0 | AQ80: 5373.72 | AR80: 0 | AS80: 9 | AT80: 9 | AU80: 0 | AV80: 0.25 | AW80: 0.25 | AX80: 0.1 | AY80: BETTY | AZ80: Lehenga Choli | BA80: 30.68 | BB80: 0 | BC80: 1945.419 | BD80: -1945.419 | BE80: 0 | BF80: 0 | BG80: 0 | BH80: 403 | BI80: 5.37372 | BL80: 0 | BM80: 0 | BN80: 0 | BO80: 0 | BP80: 0 | BS80: 29755282-9eb2-4036-b763-f61b1f7c8fc3 | BT80: 26.869 | BU80: 0 | BV80: 5.374 | BW80: 0 | BX80: 0 | BY80: 0 | BZ80: 0 | CA80: 0 | CB80: 0 | CC80: 0 | CD80: 0 | CE80: 4291.358 | CF80: 0 | CG80: 0 | CH80: 0 | CI80: 0 | CJ80: 0 | CK80: 0 | CL80: 0 | CM80: 0 | CN80: 0 | CO80: 0 | CP80: 0 | CQ80: 0 | CR80: 0 | CS80: 0 | CT80: 0 | CU80: 0 | CV80: 0 | CW80: 0 | CX80: 0 | CY80: 0 | CZ80: 0 | DA80: 0 | DB80: 0 | DC80: =IFERROR(G80,0)+IFERROR(H80,0) -> 6341 | DD80: =ABS(IFERROR(T80,0)) -> 1945.419 | DE80: =ABS(IFERROR(P80,0)+IFERROR(Q80,0)) -> 32.243 | DF80: =ABS(IFERROR(AH80,0))+ABS(IFERROR(AK80,0))+IFERROR(W80,0) -> 71.98 | DG80: =IFERROR(M80,0)+IFERROR(N80,0)+IFERROR(O80,0)+IFERROR(P80,0) -> 994.129 | DH80: 4291.358
A81: 8686759194 | B81: 10686686593 | C81: 45920.539 | D81: 45924.662 | E81: TIKICLST103607741 | F81: 3544 | G81: 0 | H81: 3544 | I81: 5000 | J81: 1250 | K81: Inter-State | L81: 12 | M81: 379.71 | N81: 0 | O81: 0 | P81: 15.821 | Q81: 3.164 | R81: 25.96 | S81: 920.022 | T81: -920.022 | U81: -939.007 | V81: -71.98 | W81: 0 | X81: 61 | Y81: 0 | Z81: 10.98 | AA81: 1 | AB81: NATIONAL | AC81: 3750 | AD81: 2533.013 | AE81: 2533.013 | AF81: 0 | AG81: -939.007 | AH81: -71.98 | AI81: 3544 | AJ81: 0 | AL81: 0 | AM81: 45938 | AN81: 45938 | AO81: 45938 | AP81: 0 | AQ81: 3164.29 | AR81: 12 | AS81: 0 | AT81: 0 | AU81: 0.5 | AV81: 0 | AW81: 0 | AX81: 0.1 | AY81: Tiny Kingdom | AZ81: Kurta Sets | BA81: 25.96 | BB81: 0 | BC81: 920.022 | BD81: -920.022 | BE81: 0 | BF81: 0 | BG81: 0 | BH81: 1250 | BI81: 3.16429 | BL81: 0 | BM81: 0 | BN81: 0 | BO81: 0 | BP81: 0 | BS81: adf75b7a-d763-4f20-910d-f4d8a338f5b9 | BT81: 15.821 | BU81: 0 | BV81: 3.164 | BW81: 0 | BX81: 0 | BY81: 0 | BZ81: 2533.013 | CA81: 0 | CB81: 0 | CC81: 0 | CD81: 0 | CE81: 0 | CF81: 0 | CG81: 0 | CH81: 0 | CI81: 0 | CJ81: 0 | CK81: 0 | CL81: 0 | CM81: 0 | CN81: 0 | CO81: 0 | CP81: 0 | CQ81: 0 | CR81: 0 | CS81: 0 | CT81: 0 | CU81: 0 | CV81: 0 | CW81: 0 | CX81: 0 | CY81: 0 | CZ81: 0 | DA81: 0 | DB81: 0 | DC81: =IFERROR(G81,0)+IFERROR(H81,0) -> 3544 | DD81: =ABS(IFERROR(T81,0)) -> 920.022 | DE81: =ABS(IFERROR(P81,0)+IFERROR(Q81,0)) -> 18.985 | DF81: =ABS(IFERROR(AH81,0))+ABS(IFERROR(AK81,0))+IFERROR(W81,0) -> 71.98 | DG81: =IFERROR(M81,0)+IFERROR(N81,0)+IFERROR(O81,0)+IFERROR(P81,0) -> 395.531 | DH81: 2533.013
A82: 8680967376 | B82: 10680893112 | C82: 45918.801 | D82: 45924.518 | E82: TIKIDRSS113491283 | F82: 2794 | G82: 2794 | H82: 0 | I82: 3750 | J82: 750 | K82: Inter-State | L82: 12 | M82: 299.36 | N82: 0 | O82: 0 | P82: 12.473 | Q82: 2.495 | R82: 21.24 | S82: 593.446 | T82: -593.446 | U82: -608.414 | V82: -71.98 | W82: 0 | X82: 61 | Y82: 0 | Z82: 10.98 | AA82: 1 | AB82: NATIONAL | AC82: 3000 | AD82: 2113.606 | AE82: 2113.606 | AF82: 0 | AG82: 0 | AI82: 0 | AJ82: -608.414 | AK82: -71.98 | AL82: 2794 | AP82: 0 | AQ82: 2494.64 | AR82: 12 | AS82: 0 | AT82: 0 | AU82: 0.5 | AV82: 0 | AW82: 0 | AX82: 0.1 | AY82: Tiny Kingdom | AZ82: Dresses | BC82: 0 | BD82: 0 | BE82: 0 | BF82: 0 | BG82: 0 | BJ82: 21.24 | BK82: 0 | BL82: 593.446 | BM82: -593.446 | BN82: 0 | BO82: 0 | BP82: 0 | BQ82: 750 | BR82: 2.49464 | BS82: cf054e59-fb81-4fce-90c1-9745327d5d48 | BT82: 0 | BU82: 12.473 | BV82: 0 | BW82: 2.495 | BX82: 0 | BY82: 0 | BZ82: 2113.606 | CA82: 0 | CB82: 0 | CC82: 0 | CD82: 0 | CE82: 0 | CF82: 0 | CG82: 0 | CH82: 0 | CI82: 0 | CJ82: 0 | CK82: 0 | CL82: 0 | CM82: 0 | CN82: 0 | CO82: 0 | CP82: 0 | CQ82: 0 | CR82: 0 | CS82: 0 | CT82: 0 | CU82: 0 | CV82: 0 | CW82: 0 | CX82: 0 | CY82: 0 | CZ82: 0 | DA82: 0 | DB82: 0 | DC82: =IFERROR(G82,0)+IFERROR(H82,0) -> 2794 | DD82: =ABS(IFERROR(T82,0)) -> 593.446 | DE82: =ABS(IFERROR(P82,0)+IFERROR(Q82,0)) -> 14.968 | DF82: =ABS(IFERROR(AH82,0))+ABS(IFERROR(AK82,0))+IFERROR(W82,0) -> 71.98 | DG82: =IFERROR(M82,0)+IFERROR(N82,0)+IFERROR(O82,0)+IFERROR(P82,0) -> 311.833 | DH82: 2113.606
A83: 8738277768 | B83: 10738254885 | C83: 45936.455 | D83: 45942.816 | E83: BETYDRSS67133056 | F83: 391 | G83: 0 | H83: 391 | I83: 2750 | J83: 2300 | K83: Inter-State | L83: 5 | M83: 18.62 | N83: 0 | O83: 0 | P83: 1.862 | Q83: 0.372 | R83: 2.36 | S83: 9.228 | T83: -9.228 | U83: -11.462 | V83: -31.86 | W83: 0 | X83: 27 | Y83: 0 | Z83: 4.86 | AA83: 1 | AB83: NATIONAL | AC83: 450 | AD83: 347.678 | AE83: 347.678 | AF83: 0 | AG83: -11.462 | AH83: -31.86 | AI83: 391 | AJ83: 0 | AL83: 0 | AM83: 45957 | AN83: 45957 | AO83: 45957 | AP83: 0 | AQ83: 372.38 | AR83: 5 | AS83: 0 | AT83: 0 | AU83: 0.5 | AV83: 0 | AW83: 0 | AX83: 0.1 | AY83: BETTY | AZ83: Dresses | BA83: 2.36 | BB83: 0 | BC83: 9.228 | BD83: -9.228 | BE83: 0 | BF83: 0 | BG83: 0 | BH83: 2300 | BI83: 0.37238 | BL83: 0 | BM83: 0 | BN83: 0 | BO83: 0 | BP83: 0 | BS83: d23f1451-f604-43b8-a9e2-9e134f4a0186 | BT83: 1.862 | BU83: 0 | BV83: 0.372 | BW83: 0 | BX83: 0 | BY83: 0 | BZ83: 0 | CA83: 0 | CB83: 0 | CC83: 0 | CD83: 0 | CE83: 0 | CF83: 0 | CG83: 0 | CH83: 0 | CI83: 0 | CJ83: 347.678 | CK83: 0 | CL83: 0 | CM83: 0 | CN83: 0 | CO83: 0 | CP83: 0 | CQ83: 0 | CR83: 0 | CS83: 0 | CT83: 0 | CU83: 0 | CV83: 0 | CW83: 0 | CX83: 0 | CY83: 0 | CZ83: 0 | DA83: 0 | DB83: 0 | DC83: =IFERROR(G83,0)+IFERROR(H83,0) -> 391 | DD83: =ABS(IFERROR(T83,0)) -> 9.228 | DE83: =ABS(IFERROR(P83,0)+IFERROR(Q83,0)) -> 2.234 | DF83: =ABS(IFERROR(AH83,0))+ABS(IFERROR(AK83,0))+IFERROR(W83,0) -> 31.86 | DG83: =IFERROR(M83,0)+IFERROR(N83,0)+IFERROR(O83,0)+IFERROR(P83,0) -> 20.482 | DH83: 347.678
A84: 8714558795 | B84: 10714498549 | C84: 45929.449 | D84: 45936.767 | E84: TNBYTSHT49476507 | F84: 140 | G84: 0 | H84: 140 | I84: 699 | J84: 500 | K84: Inter-State | L84: 5 | M84: 6.67 | N84: 0 | O84: 0 | P84: 0.667 | Q84: 0.133 | R84: 11.8 | S84: 16.52 | T84: -16.52 | U84: -17.32 | V84: -31.86 | W84: 0 | X84: 27 | Y84: 0 | Z84: 4.86 | AA84: 1 | AB84: NATIONAL | AC84: 199 | AD84: 90.82 | AE84: 90.82 | AF84: 0 | AG84: -17.32 | AH84: -31.86 | AI84: 140 | AJ84: 0 | AL84: 0 | AM84: 45953 | AN84: 45953 | AO84: 45953 | AP84: 0 | AQ84: 133.33 | AR84: 5 | AS84: 0 | AT84: 0 | AU84: 0.5 | AV84: 0 | AW84: 0 | AX84: 0.1 | AY84: Tiny Baby | AZ84: Tshirts | BA84: 11.8 | BB84: 0 | BC84: 16.52 | BD84: -16.52 | BE84: 0 | BF84: 0 | BG84: 0 | BH84: 500 | BI84: 0.13333 | BL84: 0 | BM84: 0 | BN84: 0 | BO84: 0 | BP84: 0 | BS84: 0749e851-1fda-471b-991c-e94133e0f8f1 | BT84: 0.667 | BU84: 0 | BV84: 0.133 | BW84: 0 | BX84: 0 | BY84: 0 | BZ84: 0 | CA84: 0 | CB84: 0 | CC84: 0 | CD84: 0 | CE84: 0 | CF84: 0 | CG84: 0 | CH84: 90.82 | CI84: 0 | CJ84: 0 | CK84: 0 | CL84: 0 | CM84: 0 | CN84: 0 | CO84: 0 | CP84: 0 | CQ84: 0 | CR84: 0 | CS84: 0 | CT84: 0 | CU84: 0 | CV84: 0 | CW84: 0 | CX84: 0 | CY84: 0 | CZ84: 0 | DA84: 0 | DB84: 0 | DC84: =IFERROR(G84,0)+IFERROR(H84,0) -> 140 | DD84: =ABS(IFERROR(T84,0)) -> 16.52 | DE84: =ABS(IFERROR(P84,0)+IFERROR(Q84,0)) -> 0.8 | DF84: =ABS(IFERROR(AH84,0))+ABS(IFERROR(AK84,0))+IFERROR(W84,0) -> 31.86 | DG84: =IFERROR(M84,0)+IFERROR(N84,0)+IFERROR(O84,0)+IFERROR(P84,0) -> 7.337 | DH84: 90.82
A85: 8682570667 | B85: 10682497661 | C85: 45919.798 | D85: 45925.501 | E85: BETYDRSS93852556 | F85: 3629 | G85: 3629 | H85: 0 | I85: 5000 | J85: 1165 | K85: Inter-State | L85: 12 | M85: 388.82 | N85: 0 | O85: 0 | P85: 16.201 | Q85: 3.24 | R85: 31.86 | S85: 1156.199 | T85: -1156.199 | U85: -1175.64 | V85: -71.98 | W85: 0 | X85: 61 | Y85: 0 | Z85: 10.98 | AA85: 1 | AB85: NATIONAL | AC85: 3835 | AD85: 2381.38 | AE85: 2381.38 | AF85: 0 | AG85: 0 | AI85: 0 | AJ85: -1175.64 | AK85: -71.98 | AL85: 3629 | AP85: 0 | AQ85: 3240.18 | AR85: 12 | AS85: 0 | AT85: 0 | AU85: 0.5 | AV85: 0 | AW85: 0 | AX85: 0.1 | AY85: BETTY | AZ85: Dresses | BC85: 0 | BD85: 0 | BE85: 0 | BF85: 0 | BG85: 0 | BJ85: 31.86 | BK85: 0 | BL85: 1156.199 | BM85: -1156.199 | BN85: 0 | BO85: 0 | BP85: 0 | BQ85: 1165 | BR85: 3.24018 | BS85: a1a5995d-ff4f-4674-9a02-d98b5cd020ff | BT85: 0 | BU85: 16.201 | BV85: 0 | BW85: 3.24 | BX85: 0 | BY85: 0 | BZ85: 0 | CA85: 2381.38 | CB85: 0 | CC85: 0 | CD85: 0 | CE85: 0 | CF85: 0 | CG85: 0 | CH85: 0 | CI85: 0 | CJ85: 0 | CK85: 0 | CL85: 0 | CM85: 0 | CN85: 0 | CO85: 0 | CP85: 0 | CQ85: 0 | CR85: 0 | CS85: 0 | CT85: 0 | CU85: 0 | CV85: 0 | CW85: 0 | CX85: 0 | CY85: 0 | CZ85: 0 | DA85: 0 | DB85: 0 | DC85: =IFERROR(G85,0)+IFERROR(H85,0) -> 3629 | DD85: =ABS(IFERROR(T85,0)) -> 1156.199 | DE85: =ABS(IFERROR(P85,0)+IFERROR(Q85,0)) -> 19.441 | DF85: =ABS(IFERROR(AH85,0))+ABS(IFERROR(AK85,0))+IFERROR(W85,0) -> 71.98 | DG85: =IFERROR(M85,0)+IFERROR(N85,0)+IFERROR(O85,0)+IFERROR(P85,0) -> 405.021 | DH85: 2381.38
A86: 8662341758 | B86: 10662265807 | C86: 45912.476 | D86: 45917.516 | E86: BETYDRSS74936920 | F86: 1931 | G86: 126.162 | H86: 1804.838 | I86: 4750 | J86: 2613 | K86: Inter-State | L86: 12 | M86: 206.89 | N86: 0 | O86: 0 | P86: 8.62 | Q86: 1.724 | R86: 33.04 | S86: 638.003 | T86: -638.003 | U86: -648.347 | V86: -53.1 | W86: 0 | X86: 45 | Y86: 0 | Z86: 8.1 | AA86: 1 | AB86: NATIONAL | AC86: 2137 | AD86: 1229.553 | AE86: 1229.553 | AF86: 0 | AG86: -605.987 | AH86: -49.6308 | AI86: 1804.838 | AJ86: -42.36 | AK86: -3.4692 | AL86: 126.162 | AM86: 45933 | AN86: 45933 | AO86: 45933 | AP86: 114 | AQ86: 1724.11 | AR86: 12 | AS86: 0 | AT86: 0 | AU86: 0.5 | AV86: 0 | AW86: 0 | AX86: 0.1 | AY86: BETTY | AZ86: Dresses | BA86: 33.04 | BB86: 0 | BC86: 596.319 | BD86: -596.319 | BE86: 0 | BF86: 0 | BG86: 0 | BH86: 2613 | BI86: 1.72411 | BJ86: 33.04 | BK86: 0 | BL86: 41.684 | BM86: -41.684 | BN86: 0 | BO86: 0 | BP86: 0 | BQ86: 2613 | BR86: 1.72411 | BS86: e5af4908-85ad-40c8-9d56-ca223bc0df6e | BT86: 8.057 | BU86: 0.563 | BV86: 1.611 | BW86: 0.113 | BX86: 1229.553 | BY86: 0 | BZ86: 0 | CA86: 0 | CB86: 0 | CC86: 0 | CD86: 0 | CE86: 0 | CF86: 0 | CG86: 0 | CH86: 0 | CI86: 0 | CJ86: 0 | CK86: 0 | CL86: 0 | CM86: 0 | CN86: 0 | CO86: 0 | CP86: 0 | CQ86: 0 | CR86: 0 | CS86: 0 | CT86: 0 | CU86: 0 | CV86: 0 | CW86: 0 | CX86: 0 | CY86: 0 | CZ86: 0 | DA86: 0 | DB86: 0 | DC86: =IFERROR(G86,0)+IFERROR(H86,0) -> 1931 | DD86: =ABS(IFERROR(T86,0)) -> 638.003 | DE86: =ABS(IFERROR(P86,0)+IFERROR(Q86,0)) -> 10.344 | DF86: =ABS(IFERROR(AH86,0))+ABS(IFERROR(AK86,0))+IFERROR(W86,0) -> 53.1 | DG86: =IFERROR(M86,0)+IFERROR(N86,0)+IFERROR(O86,0)+IFERROR(P86,0) -> 215.51 | DH86: 1229.553
A87: 8724483694 | B87: 10724432180 | C87: 45931.463 | D87: 45935.506 | E87: TNBYCLST112440786 | F87: 2338 | G87: 2338 | H87: 0 | I87: 3000 | J87: 456 | K87: Inter-State | L87: 5 | M87: 111.33 | N87: 0 | O87: 0 | P87: 11.133 | Q87: 2.227 | R87: 25.96 | S87: 606.945 | T87: -606.945 | U87: -620.305 | V87: -71.98 | W87: 0 | X87: 61 | Y87: 0 | Z87: 10.98 | AA87: 1 | AB87: NATIONAL | AC87: 2544 | AD87: 1645.715 | AE87: 1645.715 | AF87: 0 | AG87: 0 | AI87: 0 | AJ87: -620.305 | AK87: -71.98 | AL87: 2338 | AP87: 0 | AQ87: 2226.67 | AR87: 5 | AS87: 0 | AT87: 0 | AU87: 0.5 | AV87: 0 | AW87: 0 | AX87: 0.1 | AY87: Tiny Baby | AZ87: Clothing Set | BC87: 0 | BD87: 0 | BE87: 0 | BF87: 0 | BG87: 0 | BJ87: 25.96 | BK87: 0 | BL87: 606.945 | BM87: -606.945 | BN87: 0 | BO87: 0 | BP87: 0 | BQ87: 456 | BR87: 2.22667 | BS87: ddebef14-1ae4-4319-ad0f-b9ebee1238b3 | BT87: 0 | BU87: 11.133 | BV87: 0 | BW87: 2.227 | BX87: 0 | BY87: 0 | BZ87: 0 | CA87: 0 | CB87: 0 | CC87: 0 | CD87: 0 | CE87: 0 | CF87: 0 | CG87: 0 | CH87: 1645.715 | CI87: 0 | CJ87: 0 | CK87: 0 | CL87: 0 | CM87: 0 | CN87: 0 | CO87: 0 | CP87: 0 | CQ87: 0 | CR87: 0 | CS87: 0 | CT87: 0 | CU87: 0 | CV87: 0 | CW87: 0 | CX87: 0 | CY87: 0 | CZ87: 0 | DA87: 0 | DB87: 0 | DC87: =IFERROR(G87,0)+IFERROR(H87,0) -> 2338 | DD87: =ABS(IFERROR(T87,0)) -> 606.945 | DE87: =ABS(IFERROR(P87,0)+IFERROR(Q87,0)) -> 13.36 | DF87: =ABS(IFERROR(AH87,0))+ABS(IFERROR(AK87,0))+IFERROR(W87,0) -> 71.98 | DG87: =IFERROR(M87,0)+IFERROR(N87,0)+IFERROR(O87,0)+IFERROR(P87,0) -> 122.463 | DH87: 1645.715
A88: 8740345353 | B88: 10740335813 | C88: 45937.797 | D88: 45945.451 | E88: TIKICLST112314130 | F88: 3594 | G88: 3594 | H88: 0 | I88: 4000 | J88: 200 | K88: Intra-State | L88: 18 | M88: 0 | N88: 274.12 | O88: 274.12 | P88: 15.229 | Q88: 3.046 | R88: 25.96 | S88: 933.002 | T88: -933.002 | U88: -951.277 | V88: -71.98 | W88: 0 | X88: 61 | Y88: 0 | Z88: 10.98 | AA88: 1 | AB88: ZONAL | AC88: 3800 | AD88: 2570.743 | AE88: 2570.743 | AF88: 0 | AG88: 0 | AI88: 0 | AJ88: -951.277 | AK88: -71.98 | AL88: 3594 | AP88: 0 | AQ88: 3045.76 | AR88: 0 | AS88: 9 | AT88: 9 | AU88: 0 | AV88: 0.25 | AW88: 0.25 | AX88: 0.1 | AY88: Tiny Kingdom | AZ88: Kurta Sets | BC88: 0 | BD88: 0 | BE88: 0 | BF88: 0 | BG88: 0 | BJ88: 25.96 | BK88: 0 | BL88: 933.002 | BM88: -933.002 | BN88: 0 | BO88: 0 | BP88: 0 | BQ88: 200 | BR88: 3.04576 | BS88: 86acdbc2-9183-42e6-93a9-a73ab4869a44 | BT88: 0 | BU88: 15.229 | BV88: 0 | BW88: 3.046 | BX88: 0 | BY88: 0 | BZ88: 0 | CA88: 0 | CB88: 0 | CC88: 0 | CD88: 0 | CE88: 0 | CF88: 0 | CG88: 0 | CH88: 0 | CI88: 0 | CJ88: 0 | CK88: 0 | CL88: 2570.743 | CM88: 0 | CN88: 0 | CO88: 0 | CP88: 0 | CQ88: 0 | CR88: 0 | CS88: 0 | CT88: 0 | CU88: 0 | CV88: 0 | CW88: 0 | CX88: 0 | CY88: 0 | CZ88: 0 | DA88: 0 | DB88: 0 | DC88: =IFERROR(G88,0)+IFERROR(H88,0) -> 3594 | DD88: =ABS(IFERROR(T88,0)) -> 933.002 | DE88: =ABS(IFERROR(P88,0)+IFERROR(Q88,0)) -> 18.275 | DF88: =ABS(IFERROR(AH88,0))+ABS(IFERROR(AK88,0))+IFERROR(W88,0) -> 71.98 | DG88: =IFERROR(M88,0)+IFERROR(N88,0)+IFERROR(O88,0)+IFERROR(P88,0) -> 563.469 | DH88: 2570.743
A89: 8706210922 | B89: 10706143517 | C89: 45925.451 | D89: 45929.394 | E89: BETYDRSS63786092 | F89: 391 | G89: 391 | H89: 0 | I89: 2500 | J89: 2050 | K89: Inter-State | L89: 5 | M89: 18.62 | N89: 0 | O89: 0 | P89: 1.862 | Q89: 0.372 | R89: 2.36 | S89: 9.228 | T89: -9.228 | U89: -11.462 | V89: -31.86 | W89: 0 | X89: 27 | Y89: 0 | Z89: 4.86 | AA89: 1 | AB89: NATIONAL | AC89: 450 | AD89: 347.678 | AE89: 347.678 | AF89: 0 | AG89: 0 | AI89: 0 | AJ89: -11.462 | AK89: -31.86 | AL89: 391 | AP89: 0 | AQ89: 372.38 | AR89: 5 | AS89: 0 | AT89: 0 | AU89: 0.5 | AV89: 0 | AW89: 0 | AX89: 0.1 | AY89: BETTY | AZ89: Dresses | BC89: 0 | BD89: 0 | BE89: 0 | BF89: 0 | BG89: 0 | BJ89: 2.36 | BK89: 0 | BL89: 9.228 | BM89: -9.228 | BN89: 0 | BO89: 0 | BP89: 0 | BQ89: 2050 | BR89: 0.37238 | BS89: 0275f1a2-7527-4aee-b1df-ce17e37e3741 | BT89: 0 | BU89: 1.862 | BV89: 0 | BW89: 0.372 | BX89: 0 | BY89: 0 | BZ89: 0 | CA89: 0 | CB89: 0 | CC89: 0 | CD89: 347.678 | CE89: 0 | CF89: 0 | CG89: 0 | CH89: 0 | CI89: 0 | CJ89: 0 | CK89: 0 | CL89: 0 | CM89: 0 | CN89: 0 | CO89: 0 | CP89: 0 | CQ89: 0 | CR89: 0 | CS89: 0 | CT89: 0 | CU89: 0 | CV89: 0 | CW89: 0 | CX89: 0 | CY89: 0 | CZ89: 0 | DA89: 0 | DB89: 0 | DC89: =IFERROR(G89,0)+IFERROR(H89,0) -> 391 | DD89: =ABS(IFERROR(T89,0)) -> 9.228 | DE89: =ABS(IFERROR(P89,0)+IFERROR(Q89,0)) -> 2.234 | DF89: =ABS(IFERROR(AH89,0))+ABS(IFERROR(AK89,0))+IFERROR(W89,0) -> 31.86 | DG89: =IFERROR(M89,0)+IFERROR(N89,0)+IFERROR(O89,0)+IFERROR(P89,0) -> 20.482 | DH89: 347.678
A90: 8738896129 | B90: 10738881856 | C90: 45936.808 | D90: 45942.45 | E90: TIKICLST106786475 | F90: 3954.99 | G90: 3955 | H90: 0 | I90: 4500 | J90: 339 | K90: Inter-State | L90: 18 | M90: 603.3 | N90: 0 | O90: 0 | P90: 16.758 | Q90: 3.352 | R90: 24.78 | S90: 980.049 | T90: -980.049 | U90: -1000.159 | V90: -71.98 | W90: 0 | X90: 61 | Y90: 0 | Z90: 10.98 | AA90: 1 | AB90: NATIONAL | AC90: 4161 | AD90: 2882.861 | AE90: 2882.861 | AF90: 0 | AG90: 0 | AI90: 0 | AJ90: -1000.159 | AK90: -71.98 | AL90: 3955 | AP90: 0 | AQ90: 3351.69 | AR90: 18 | AS90: 0 | AT90: 0 | AU90: 0.5 | AV90: 0 | AW90: 0 | AX90: 0.1 | AY90: Tiny Kingdom | AZ90: Clothing Set | BC90: 0 | BD90: 0 | BE90: 0 | BF90: 0 | BG90: 0 | BJ90: 24.78 | BK90: 0 | BL90: 980.049 | BM90: -980.049 | BN90: 0 | BO90: 0 | BP90: 0 | BQ90: 339 | BR90: 3.35169 | BS90: 55566ff2-131f-4eba-9a43-059bf997c088 | BT90: 0 | BU90: 16.758 | BV90: 0 | BW90: 3.352 | BX90: 0 | BY90: 0 | BZ90: 0 | CA90: 0 | CB90: 0 | CC90: 0 | CD90: 0 | CE90: 0 | CF90: 0 | CG90: 0 | CH90: 0 | CI90: 0 | CJ90: 2882.861 | CK90: 0 | CL90: 0 | CM90: 0 | CN90: 0 | CO90: 0 | CP90: 0 | CQ90: 0 | CR90: 0 | CS90: 0 | CT90: 0 | CU90: 0 | CV90: 0 | CW90: 0 | CX90: 0 | CY90: 0 | CZ90: 0 | DA90: 0 | DB90: 0 | DC90: =IFERROR(G90,0)+IFERROR(H90,0) -> 3955 | DD90: =ABS(IFERROR(T90,0)) -> 980.049 | DE90: =ABS(IFERROR(P90,0)+IFERROR(Q90,0)) -> 20.11 | DF90: =ABS(IFERROR(AH90,0))+ABS(IFERROR(AK90,0))+IFERROR(W90,0) -> 71.98 | DG90: =IFERROR(M90,0)+IFERROR(N90,0)+IFERROR(O90,0)+IFERROR(P90,0) -> 620.058 | DH90: 2882.861
A91: 8721028699 | B91: 10720973620 | C91: 45930.615 | D91: 45935.401 | E91: TIKILHNC101907528 | F91: 1012 | G91: 1012 | H91: 0 | I91: 2500 | J91: 1317 | K91: Inter-State | L91: 5 | M91: 48.19 | N91: 0 | O91: 0 | P91: 4.819 | Q91: 0.964 | R91: 24.78 | S91: 250.774 | T91: -250.774 | U91: -256.557 | V91: -53.1 | W91: 0 | X91: 45 | Y91: 0 | Z91: 8.1 | AA91: 1 | AB91: NATIONAL | AC91: 1183 | AD91: 702.343 | AE91: 702.343 | AF91: 0 | AG91: 0 | AI91: 0 | AJ91: -256.557 | AK91: -53.1 | AL91: 1012 | AP91: 0 | AQ91: 963.81 | AR91: 5 | AS91: 0 | AT91: 0 | AU91: 0.5 | AV91: 0 | AW91: 0 | AX91: 0.1 | AY91: Tiny Kingdom | AZ91: Lehenga Choli | BC91: 0 | BD91: 0 | BE91: 0 | BF91: 0 | BG91: 0 | BJ91: 24.78 | BK91: 0 | BL91: 250.774 | BM91: -250.774 | BN91: 0 | BO91: 0 | BP91: 0 | BQ91: 1317 | BR91: 0.96381 | BS91: 8f92733b-0eaf-4e8d-98a6-24b606397f7a | BT91: 0 | BU91: 4.819 | BV91: 0 | BW91: 0.964 | BX91: 0 | BY91: 0 | BZ91: 0 | CA91: 0 | CB91: 0 | CC91: 0 | CD91: 0 | CE91: 0 | CF91: 0 | CG91: 0 | CH91: 702.343 | CI91: 0 | CJ91: 0 | CK91: 0 | CL91: 0 | CM91: 0 | CN91: 0 | CO91: 0 | CP91: 0 | CQ91: 0 | CR91: 0 | CS91: 0 | CT91: 0 | CU91: 0 | CV91: 0 | CW91: 0 | CX91: 0 | CY91: 0 | CZ91: 0 | DA91: 0 | DB91: 0 | DC91: =IFERROR(G91,0)+IFERROR(H91,0) -> 1012 | DD91: =ABS(IFERROR(T91,0)) -> 250.774 | DE91: =ABS(IFERROR(P91,0)+IFERROR(Q91,0)) -> 5.783 | DF91: =ABS(IFERROR(AH91,0))+ABS(IFERROR(AK91,0))+IFERROR(W91,0) -> 53.1 | DG91: =IFERROR(M91,0)+IFERROR(N91,0)+IFERROR(O91,0)+IFERROR(P91,0) -> 53.009 | DH91: 702.343
A92: 8691260646 | B92: 10691188862 | C92: 45922.443 | D92: 45927.622 | E92: TIKIDRSS101406984 | F92: 3143 | G92: 0 | H92: 3143 | I92: 4000 | J92: 651 | K92: Inter-State | L92: 18 | M92: 479.44 | N92: 0 | O92: 0 | P92: 13.318 | Q92: 2.664 | R92: 21.24 | S92: 667.573 | T92: -667.573 | U92: -683.555 | V92: -71.98 | W92: 0 | X92: 61 | Y92: 0 | Z92: 10.98 | AA92: 1 | AB92: NATIONAL | AC92: 3349 | AD92: 2387.465 | AE92: 2387.465 | AF92: 0 | AG92: -683.555 | AH92: -71.98 | AI92: 3143 | AJ92: 0 | AL92: 0 | AM92: 45943 | AN92: 45943 | AO92: 45943 | AP92: 0 | AQ92: 2663.56 | AR92: 18 | AS92: 0 | AT92: 0 | AU92: 0.5 | AV92: 0 | AW92: 0 | AX92: 0.1 | AY92: Tiny Kingdom | AZ92: Dresses | BA92: 21.24 | BB92: 0 | BC92: 667.573 | BD92: -667.573 | BE92: 0 | BF92: 0 | BG92: 0 | BH92: 651 | BI92: 2.66356 | BL92: 0 | BM92: 0 | BN92: 0 | BO92: 0 | BP92: 0 | BS92: 33852e32-406d-4dbd-80e3-5af8f4fbacfd | BT92: 13.318 | BU92: 0 | BV92: 2.664 | BW92: 0 | BX92: 0 | BY92: 0 | BZ92: 0 | CA92: 0 | CB92: 0 | CC92: 2387.465 | CD92: 0 | CE92: 0 | CF92: 0 | CG92: 0 | CH92: 0 | CI92: 0 | CJ92: 0 | CK92: 0 | CL92: 0 | CM92: 0 | CN92: 0 | CO92: 0 | CP92: 0 | CQ92: 0 | CR92: 0 | CS92: 0 | CT92: 0 | CU92: 0 | CV92: 0 | CW92: 0 | CX92: 0 | CY92: 0 | CZ92: 0 | DA92: 0 | DB92: 0 | DC92: =IFERROR(G92,0)+IFERROR(H92,0) -> 3143 | DD92: =ABS(IFERROR(T92,0)) -> 667.573 | DE92: =ABS(IFERROR(P92,0)+IFERROR(Q92,0)) -> 15.982 | DF92: =ABS(IFERROR(AH92,0))+ABS(IFERROR(AK92,0))+IFERROR(W92,0) -> 71.98 | DG92: =IFERROR(M92,0)+IFERROR(N92,0)+IFERROR(O92,0)+IFERROR(P92,0) -> 492.758 | DH92: 2387.465
A93: 8722877791 | B93: 10722824633 | C93: 45930.787 | D93: 45935.581 | E93: TIKIDRSS113553908 | F93: 3119 | G93: 0 | H93: 3118.99 | I93: 3500 | J93: 175 | K93: Inter-State | L93: 18 | M93: 475.78 | N93: 0 | O93: 0 | P93: 13.216 | Q93: 2.643 | R93: 21.24 | S93: 662.473 | T93: -662.473 | U93: -678.332 | V93: -71.98 | W93: 0 | X93: 61 | Y93: 0 | Z93: 10.98 | AA93: 1 | AB93: NATIONAL | AC93: 3325 | AD93: 2368.678 | AE93: 2368.678 | AF93: 0 | AG93: -678.332 | AH93: -71.98 | AI93: 3118.99 | AJ93: 0 | AL93: 0 | AM93: 45953 | AN93: 45953 | AO93: 45953 | AP93: 0 | AQ93: 2643.22 | AR93: 18 | AS93: 0 | AT93: 0 | AU93: 0.5 | AV93: 0 | AW93: 0 | AX93: 0.1 | AY93: Tiny Kingdom | AZ93: Dresses | BA93: 21.24 | BB93: 0 | BC93: 662.473 | BD93: -662.473 | BE93: 0 | BF93: 0 | BG93: 0 | BH93: 175 | BI93: 2.64322 | BL93: 0 | BM93: 0 | BN93: 0 | BO93: 0 | BP93: 0 | BS93: f325081f-8190-46df-bd6d-c7c06fe3bd1d | BT93: 13.216 | BU93: 0 | BV93: 2.643 | BW93: 0 | BX93: 0 | BY93: 0 | BZ93: 0 | CA93: 0 | CB93: 0 | CC93: 0 | CD93: 0 | CE93: 0 | CF93: 0 | CG93: 0 | CH93: 2368.678 | CI93: 0 | CJ93: 0 | CK93: 0 | CL93: 0 | CM93: 0 | CN93: 0 | CO93: 0 | CP93: 0 | CQ93: 0 | CR93: 0 | CS93: 0 | CT93: 0 | CU93: 0 | CV93: 0 | CW93: 0 | CX93: 0 | CY93: 0 | CZ93: 0 | DA93: 0 | DB93: 0 | DC93: =IFERROR(G93,0)+IFERROR(H93,0) -> 3118.99 | DD93: =ABS(IFERROR(T93,0)) -> 662.473 | DE93: =ABS(IFERROR(P93,0)+IFERROR(Q93,0)) -> 15.859 | DF93: =ABS(IFERROR(AH93,0))+ABS(IFERROR(AK93,0))+IFERROR(W93,0) -> 71.98 | DG93: =IFERROR(M93,0)+IFERROR(N93,0)+IFERROR(O93,0)+IFERROR(P93,0) -> 488.996 | DH93: 2368.678
A94: 8663313597 | B94: 10663237650 | C94: 45912.803 | D94: 45917.524 | E94: TIKICLST116340916 | F94: 2994 | G94: 2994 | H94: 0 | I94: 4000 | J94: 800 | K94: Inter-State | L94: 12 | M94: 320.79 | N94: 0 | O94: 0 | P94: 13.366 | Q94: 2.673 | R94: 24.78 | S94: 741.913 | T94: -741.913 | U94: -757.952 | V94: -71.98 | W94: 0 | X94: 61 | Y94: 0 | Z94: 10.98 | AA94: 1 | AB94: NATIONAL | AC94: 3200 | AD94: 2164.068 | AE94: 2164.068 | AF94: 0 | AG94: 0 | AI94: 0 | AJ94: -757.952 | AK94: -71.98 | AL94: 2994 | AP94: 0 | AQ94: 2673.21 | AR94: 12 | AS94: 0 | AT94: 0 | AU94: 0.5 | AV94: 0 | AW94: 0 | AX94: 0.1 | AY94: Tiny Kingdom | AZ94: Clothing Set | BC94: 0 | BD94: 0 | BE94: 0 | BF94: 0 | BG94: 0 | BJ94: 24.78 | BK94: 0 | BL94: 741.913 | BM94: -741.913 | BN94: 0 | BO94: 0 | BP94: 0 | BQ94: 800 | BR94: 2.67321 | BS94: 64ddf8cd-38ff-4769-b158-ba30850889cf | BT94: 0 | BU94: 13.366 | BV94: 0 | BW94: 2.673 | BX94: 2164.068 | BY94: 0 | BZ94: 0 | CA94: 0 | CB94: 0 | CC94: 0 | CD94: 0 | CE94: 0 | CF94: 0 | CG94: 0 | CH94: 0 | CI94: 0 | CJ94: 0 | CK94: 0 | CL94: 0 | CM94: 0 | CN94: 0 | CO94: 0 | CP94: 0 | CQ94: 0 | CR94: 0 | CS94: 0 | CT94: 0 | CU94: 0 | CV94: 0 | CW94: 0 | CX94: 0 | CY94: 0 | CZ94: 0 | DA94: 0 | DB94: 0 | DC94: =IFERROR(G94,0)+IFERROR(H94,0) -> 2994 | DD94: =ABS(IFERROR(T94,0)) -> 741.913 | DE94: =ABS(IFERROR(P94,0)+IFERROR(Q94,0)) -> 16.039 | DF94: =ABS(IFERROR(AH94,0))+ABS(IFERROR(AK94,0))+IFERROR(W94,0) -> 71.98 | DG94: =IFERROR(M94,0)+IFERROR(N94,0)+IFERROR(O94,0)+IFERROR(P94,0) -> 334.156 | DH94: 2164.068
A95: 8705353325 | B95: 10705285821 | C95: 45924.787 | D95: 45933.679 | E95: TNBYCLST113088278 | F95: 2338 | G95: 0 | H95: 2338 | I95: 3000 | J95: 456 | K95: Inter-State | L95: 5 | M95: 111.33 | N95: 0 | O95: 0 | P95: 11.133 | Q95: 2.227 | R95: 24.78 | S95: 579.356 | T95: -579.356 | U95: -592.716 | V95: -71.98 | W95: 0 | X95: 61 | Y95: 0 | Z95: 10.98 | AA95: 1 | AB95: NATIONAL | AC95: 2544 | AD95: 1673.304 | AE95: 1673.304 | AF95: 0 | AG95: -592.716 | AH95: -71.98 | AI95: 2338 | AJ95: 0 | AL95: 0 | AM95: 45947 | AN95: 45947 | AO95: 45947 | AP95: 0 | AQ95: 2226.67 | AR95: 5 | AS95: 0 | AT95: 0 | AU95: 0.5 | AV95: 0 | AW95: 0 | AX95: 0.1 | AY95: Tiny Baby | AZ95: Jumpsuit | BA95: 24.78 | BB95: 0 | BC95: 579.356 | BD95: -579.356 | BE95: 0 | BF95: 0 | BG95: 0 | BH95: 456 | BI95: 2.22667 | BL95: 0 | BM95: 0 | BN95: 0 | BO95: 0 | BP95: 0 | BS95: 513fcb6a-783a-4289-bafb-94c1c645664c | BT95: 11.133 | BU95: 0 | BV95: 2.227 | BW95: 0 | BX95: 0 | BY95: 0 | BZ95: 0 | CA95: 0 | CB95: 0 | CC95: 0 | CD95: 0 | CE95: 0 | CF95: 0 | CG95: 1673.304 | CH95: 0 | CI95: 0 | CJ95: 0 | CK95: 0 | CL95: 0 | CM95: 0 | CN95: 0 | CO95: 0 | CP95: 0 | CQ95: 0 | CR95: 0 | CS95: 0 | CT95: 0 | CU95: 0 | CV95: 0 | CW95: 0 | CX95: 0 | CY95: 0 | CZ95: 0 | DA95: 0 | DB95: 0 | DC95: =IFERROR(G95,0)+IFERROR(H95,0) -> 2338 | DD95: =ABS(IFERROR(T95,0)) -> 579.356 | DE95: =ABS(IFERROR(P95,0)+IFERROR(Q95,0)) -> 13.36 | DF95: =ABS(IFERROR(AH95,0))+ABS(IFERROR(AK95,0))+IFERROR(W95,0) -> 71.98 | DG95: =IFERROR(M95,0)+IFERROR(N95,0)+IFERROR(O95,0)+IFERROR(P95,0) -> 122.463 | DH95: 1673.304
A96: 8730594942 | B96: 10730556871 | C96: 45933.806 | D96: 45940.672 | E96: TIKICLST113026321 | F96: 3104 | G96: 2778.712 | H96: 325.278 | I96: 3500 | J96: 190 | K96: Intra-State | L96: 18 | M96: 0 | N96: 236.75 | O96: 236.75 | P96: 13.152 | Q96: 2.631 | R96: 24.78 | S96: 769.169 | T96: -769.169 | U96: -784.952 | V96: -71.98 | W96: 0 | X96: 61 | Y96: 0 | Z96: 10.98 | AA96: 1 | AB96: LOCAL | AC96: 3310 | AD96: 2247.058 | AE96: 2247.058 | AF96: 0 | AG96: -82.258 | AH96: -7.54256 | AI96: 325.278 | AJ96: -702.694 | AK96: -64.43744 | AL96: 2778.712 | AM96: 45954 | AN96: 45954 | AO96: 45954 | AP96: 0 | AQ96: 2630.5 | AR96: 0 | AS96: 9 | AT96: 9 | AU96: 0 | AV96: 0.25 | AW96: 0.25 | AX96: 0.1 | AY96: Tiny Kingdom | AZ96: Clothing Set | BA96: 24.78 | BB96: 0 | BC96: 80.604 | BD96: -80.604 | BE96: 0 | BF96: 0 | BG96: 0 | BH96: 190 | BI96: 2.6305 | BJ96: 24.78 | BK96: 0 | BL96: 688.565 | BM96: -688.565 | BN96: 0 | BO96: 0 | BP96: 0 | BQ96: 190 | BR96: 2.6305 | BS96: 82aeee50-e1a2-420e-8d10-4d8891acd58f | BT96: 1.378 | BU96: 11.774 | BV96: 0.276 | BW96: 2.355 | BX96: 0 | BY96: 0 | BZ96: 0 | CA96: 0 | CB96: 0 | CC96: 0 | CD96: 0 | CE96: 0 | CF96: 0 | CG96: 0 | CH96: 0 | CI96: 2247.058 | CJ96: 0 | CK96: 0 | CL96: 0 | CM96: 0 | CN96: 0 | CO96: 0 | CP96: 0 | CQ96: 0 | CR96: 0 | CS96: 0 | CT96: 0 | CU96: 0 | CV96: 0 | CW96: 0 | CX96: 0 | CY96: 0 | CZ96: 0 | DA96: 0 | DB96: 0 | DC96: =IFERROR(G96,0)+IFERROR(H96,0) -> 3103.99 | DD96: =ABS(IFERROR(T96,0)) -> 769.169 | DE96: =ABS(IFERROR(P96,0)+IFERROR(Q96,0)) -> 15.783 | DF96: =ABS(IFERROR(AH96,0))+ABS(IFERROR(AK96,0))+IFERROR(W96,0) -> 71.98 | DG96: =IFERROR(M96,0)+IFERROR(N96,0)+IFERROR(O96,0)+IFERROR(P96,0) -> 486.652 | DH96: 2247.058
A97: 8729326570 | B97: 10729282779 | C97: 45933.481 | D97: 45938.611 | E97: BETYCLST59437934 | F97: 1963 | G97: 0 | H97: 1963.01 | I97: 4600 | J97: 2431 | K97: Inter-State | L97: 5 | M97: 93.48 | N97: 0 | O97: 0 | P97: 9.348 | Q97: 1.87 | R97: 31.86 | S97: 625.415 | T97: -625.415 | U97: -636.633 | V97: -53.1 | W97: 0 | X97: 45 | Y97: 0 | Z97: 8.1 | AA97: 1 | AB97: NATIONAL | AC97: 2169 | AD97: 1273.277 | AE97: 1273.277 | AF97: 0 | AG97: -636.633 | AH97: -53.1 | AI97: 1963.01 | AJ97: 0 | AL97: 0 | AM97: 45953 | AN97: 45953 | AO97: 45953 | AP97: 0 | AQ97: 1869.52 | AR97: 5 | AS97: 0 | AT97: 0 | AU97: 0.5 | AV97: 0 | AW97: 0 | AX97: 0.1 | AY97: BETTY | AZ97: Clothing Set | BA97: 31.86 | BB97: 0 | BC97: 625.415 | BD97: -625.415 | BE97: 0 | BF97: 0 | BG97: 0 | BH97: 2431 | BI97: 1.86952 | BL97: 0 | BM97: 0 | BN97: 0 | BO97: 0 | BP97: 0 | BS97: ede8f615-34b1-483c-ad2d-d609932b8e7a | BT97: 9.348 | BU97: 0 | BV97: 1.87 | BW97: 0 | BX97: 0 | BY97: 0 | BZ97: 0 | CA97: 0 | CB97: 0 | CC97: 0 | CD97: 0 | CE97: 0 | CF97: 0 | CG97: 0 | CH97: 1273.277 | CI97: 0 | CJ97: 0 | CK97: 0 | CL97: 0 | CM97: 0 | CN97: 0 | CO97: 0 | CP97: 0 | CQ97: 0 | CR97: 0 | CS97: 0 | CT97: 0 | CU97: 0 | CV97: 0 | CW97: 0 | CX97: 0 | CY97: 0 | CZ97: 0 | DA97: 0 | DB97: 0 | DC97: =IFERROR(G97,0)+IFERROR(H97,0) -> 1963.01 | DD97: =ABS(IFERROR(T97,0)) -> 625.415 | DE97: =ABS(IFERROR(P97,0)+IFERROR(Q97,0)) -> 11.218 | DF97: =ABS(IFERROR(AH97,0))+ABS(IFERROR(AK97,0))+IFERROR(W97,0) -> 53.1 | DG97: =IFERROR(M97,0)+IFERROR(N97,0)+IFERROR(O97,0)+IFERROR(P97,0) -> 102.828 | DH97: 1273.277
A98: 8682097274 | B98: 10682023979 | C98: 45919.525 | D98: 45923.627 | E98: TNBYCLST103346298 | F98: 2769 | G98: 0 | H98: 2769 | I98: 3500 | J98: 525 | K98: Inter-State | L98: 12 | M98: 296.68 | N98: 0 | O98: 0 | P98: 12.362 | Q98: 2.472 | R98: 25.96 | S98: 718.832 | T98: -718.832 | U98: -733.666 | V98: -71.98 | W98: 0 | X98: 61 | Y98: 0 | Z98: 10.98 | AA98: 1 | AB98: NATIONAL | AC98: 2975 | AD98: 1963.354 | AE98: 1963.354 | AF98: 0 | AG98: -733.666 | AH98: -71.98 | AI98: 2769 | AJ98: 0 | AL98: 0 | AM98: 45938 | AN98: 45938 | AO98: 45938 | AP98: 0 | AQ98: 2472.32 | AR98: 12 | AS98: 0 | AT98: 0 | AU98: 0.5 | AV98: 0 | AW98: 0 | AX98: 0.1 | AY98: Tiny Baby | AZ98: Clothing Set | BA98: 25.96 | BB98: 0 | BC98: 718.832 | BD98: -718.832 | BE98: 0 | BF98: 0 | BG98: 0 | BH98: 525 | BI98: 2.47232 | BL98: 0 | BM98: 0 | BN98: 0 | BO98: 0 | BP98: 0 | BS98: 7b039990-40e1-4b95-a4ef-5fbf311cf2d7 | BT98: 12.362 | BU98: 0 | BV98: 2.472 | BW98: 0 | BX98: 0 | BY98: 0 | BZ98: 1963.354 | CA98: 0 | CB98: 0 | CC98: 0 | CD98: 0 | CE98: 0 | CF98: 0 | CG98: 0 | CH98: 0 | CI98: 0 | CJ98: 0 | CK98: 0 | CL98: 0 | CM98: 0 | CN98: 0 | CO98: 0 | CP98: 0 | CQ98: 0 | CR98: 0 | CS98: 0 | CT98: 0 | CU98: 0 | CV98: 0 | CW98: 0 | CX98: 0 | CY98: 0 | CZ98: 0 | DA98: 0 | DB98: 0 | DC98: =IFERROR(G98,0)+IFERROR(H98,0) -> 2769 | DD98: =ABS(IFERROR(T98,0)) -> 718.832 | DE98: =ABS(IFERROR(P98,0)+IFERROR(Q98,0)) -> 14.834 | DF98: =ABS(IFERROR(AH98,0))+ABS(IFERROR(AK98,0))+IFERROR(W98,0) -> 71.98 | DG98: =IFERROR(M98,0)+IFERROR(N98,0)+IFERROR(O98,0)+IFERROR(P98,0) -> 309.042 | DH98: 1963.354
A99: 8745960959 | B99: 10745977542 | C99: 45940.445 | D99: 45945.816 | E99: TIKICLST113026323 | F99: 2410 | G99: 2410 | H99: 0 | I99: 3500 | J99: 884 | K99: Inter-State | L99: 5 | M99: 114.76 | N99: 0 | O99: 0 | P99: 11.476 | Q99: 2.295 | R99: 24.78 | S99: 597.198 | T99: -597.198 | U99: -610.969 | V99: -71.98 | W99: 0 | X99: 61 | Y99: 0 | Z99: 10.98 | AA99: 1 | AB99: NATIONAL | AC99: 2616 | AD99: 1727.051 | AE99: 1727.051 | AF99: 0 | AG99: 0 | AI99: 0 | AJ99: -610.969 | AK99: -71.98 | AL99: 2410 | AP99: 0 | AQ99: 2295.24 | AR99: 5 | AS99: 0 | AT99: 0 | AU99: 0.5 | AV99: 0 | AW99: 0 | AX99: 0.1 | AY99: Tiny Kingdom | AZ99: Clothing Set | BC99: 0 | BD99: 0 | BE99: 0 | BF99: 0 | BG99: 0 | BJ99: 24.78 | BK99: 0 | BL99: 597.198 | BM99: -597.198 | BN99: 0 | BO99: 0 | BP99: 0 | BQ99: 884 | BR99: 2.29524 | BS99: 1647244c-d6e5-430c-9b1c-66c10a1dede0 | BT99: 0 | BU99: 11.476 | BV99: 0 | BW99: 2.295 | BX99: 0 | BY99: 0 | BZ99: 0 | CA99: 0 | CB99: 0 | CC99: 0 | CD99: 0 | CE99: 0 | CF99: 0 | CG99: 0 | CH99: 0 | CI99: 0 | CJ99: 0 | CK99: 0 | CL99: 1727.051 | CM99: 0 | CN99: 0 | CO99: 0 | CP99: 0 | CQ99: 0 | CR99: 0 | CS99: 0 | CT99: 0 | CU99: 0 | CV99: 0 | CW99: 0 | CX99: 0 | CY99: 0 | CZ99: 0 | DA99: 0 | DB99: 0 | DC99: =IFERROR(G99,0)+IFERROR(H99,0) -> 2410 | DD99: =ABS(IFERROR(T99,0)) -> 597.198 | DE99: =ABS(IFERROR(P99,0)+IFERROR(Q99,0)) -> 13.771 | DF99: =ABS(IFERROR(AH99,0))+ABS(IFERROR(AK99,0))+IFERROR(W99,0) -> 71.98 | DG99: =IFERROR(M99,0)+IFERROR(N99,0)+IFERROR(O99,0)+IFERROR(P99,0) -> 126.236 | DH99: 1727.051
A100: 8680835728 | B100: 10680761485 | C100: 45918.801 | D100: 45924.713 | E100: TIKIDRSS113553896 | F100: 2594 | G100: 2594 | H100: 0 | I100: 3500 | J100: 700 | K100: Inter-State | L100: 12 | M100: 277.93 | N100: 0 | O100: 0 | P100: 11.58 | Q100: 2.316 | R100: 21.24 | S100: 550.966 | T100: -550.966 | U100: -564.862 | V100: -71.98 | W100: 0 | X100: 61 | Y100: 0 | Z100: 10.98 | AA100: 1 | AB100: NATIONAL | AC100: 2800 | AD100: 1957.158 | AE100: 1957.158 | AF100: 0 | AG100: -564.862 | AH100: -71.98 | AI100: 2594 | AJ100: 0 | AL100: 0 | AM100: 45938 | AN100: 45938 | AO100: 45938 | AP100: 0 | AQ100: 2316.07 | AR100: 12 | AS100: 0 | AT100: 0 | AU100: 0.5 | AV100: 0 | AW100: 0 | AX100: 0.1 | AY100: Tiny Kingdom | AZ100: Dresses | BC100: 0 | BD100: 0 | BE100: 0 | BF100: 0 | BG100: 0 | BJ100: 21.24 | BK100: 0 | BL100: 550.966 | BM100: -550.966 | BN100: 0 | BO100: 0 | BP100: 0 | BQ100: 700 | BR100: 2.31607 | BS100: 7beb17db-a498-4d01-ac50-c581b9ac6cc1 | BT100: 11.58 | BU100: 0 | BV100: 2.316 | BW100: 0 | BX100: 0 | BY100: 0 | BZ100: 1957.158 | CA100: 0 | CB100: 0 | CC100: 0 | CD100: 0 | CE100: 0 | CF100: 0 | CG100: 0 | CH100: 0 | CI100: 0 | CJ100: 0 | CK100: 0 | CL100: 0 | CM100: 0 | CN100: 0 | CO100: 0 | CP100: 0 | CQ100: 0 | CR100: 0 | CS100: 0 | CT100: 0 | CU100: 0 | CV100: 0 | CW100: 0 | CX100: 0 | CY100: 0 | CZ100: 0 | DA100: 0 | DB100: 0 | DC100: =IFERROR(G100,0)+IFERROR(H100,0) -> 2594 | DD100: =ABS(IFERROR(T100,0)) -> 550.966 | DE100: =ABS(IFERROR(P100,0)+IFERROR(Q100,0)) -> 13.896 | DF100: =ABS(IFERROR(AH100,0))+ABS(IFERROR(AK100,0))+IFERROR(W100,0) -> 71.98 | DG100: =IFERROR(M100,0)+IFERROR(N100,0)+IFERROR(O100,0)+IFERROR(P100,0) -> 289.51 | DH100: 1957.158
A101: 8730282759 | B101: 10730241591 | C101: 45933.806 | D101: 45944.583 | E101: TIKICLST113026339 | F101: 3594 | G101: 3594 | H101: 0 | I101: 4000 | J101: 200 | K101: Inter-State | L101: 18 | M101: 548.24 | N101: 0 | O101: 0 | P101: 15.229 | Q101: 3.046 | R101: 25.96 | S101: 933.002 | T101: -933.002 | U101: -951.277 | V101: -71.98 | W101: 0 | X101: 61 | Y101: 0 | Z101: 10.98 | AA101: 1 | AB101: NATIONAL | AC101: 3800 | AD101: 2570.743 | AE101: 2570.743 | AF101: 0 | AG101: 0 | AI101: 0 | AJ101: -951.277 | AK101: -71.98 | AL101: 3594 | AP101: 0 | AQ101: 3045.76 | AR101: 18 | AS101: 0 | AT101: 0 | AU101: 0.5 | AV101: 0 | AW101: 0 | AX101: 0.1 | AY101: Tiny Kingdom | AZ101: Kurta Sets | BC101: 0 | BD101: 0 | BE101: 0 | BF101: 0 | BG101: 0 | BJ101: 25.96 | BK101: 0 | BL101: 933.002 | BM101: -933.002 | BN101: 0 | BO101: 0 | BP101: 0 | BQ101: 200 | BR101: 3.04576 | BS101: 16aa3fd8-04ce-4e50-8393-15294aef397e | BT101: 0 | BU101: 15.229 | BV101: 0 | BW101: 3.046 | BX101: 0 | BY101: 0 | BZ101: 0 | CA101: 0 | CB101: 0 | CC101: 0 | CD101: 0 | CE101: 0 | CF101: 0 | CG101: 0 | CH101: 0 | CI101: 0 | CJ101: 0 | CK101: 2570.743 | CL101: 0 | CM101: 0 | CN101: 0 | CO101: 0 | CP101: 0 | CQ101: 0 | CR101: 0 | CS101: 0 | CT101: 0 | CU101: 0 | CV101: 0 | CW101: 0 | CX101: 0 | CY101: 0 | CZ101: 0 | DA101: 0 | DB101: 0 | DC101: =IFERROR(G101,0)+IFERROR(H101,0) -> 3594 | DD101: =ABS(IFERROR(T101,0)) -> 933.002 | DE101: =ABS(IFERROR(P101,0)+IFERROR(Q101,0)) -> 18.275 | DF101: =ABS(IFERROR(AH101,0))+ABS(IFERROR(AK101,0))+IFERROR(W101,0) -> 71.98 | DG101: =IFERROR(M101,0)+IFERROR(N101,0)+IFERROR(O101,0)+IFERROR(P101,0) -> 563.469 | DH101: 2570.743
...

Sheet Sheet9
A3: Row Labels | B3: Sum of Net Settlement
A4: Mar | B4: 2211.2008
A5: Aug | B5: 827.428
A6: Sep | B6: 288163.44
A7: Oct | B7: 509457.75
A8: Grand Total | B8: 800659.82

Sheet PGReconsile
A1: order_id | B1: Customer_Paid | C1: Commission | D1: Tax_On_Commission | E1: Logistics | F1: GST_taxes | G1: Myntra_Settlement | H1: Final_Settlement | I1: Difference (what Myntra kept per order) | J1: Charges while Return | K1: Reverse Settlement | L1: Net Settlement | M1: Order_status | N1: Return Reason | O1: Date
A2: 8743896489 | B2: =VLOOKUP(A2,PG_FORWARD_SETTLED__1[[order_id]:[Customer_Paid]],107,0) -> 2410 | C2: =VLOOKUP(A2,PG_FORWARD_SETTLED__1[[order_id]:[Commission]],108,0) -> 597.198 | D2: =VLOOKUP(A2,PG_FORWARD_SETTLED__1[[#All],[order_id]:[Tax_On_Commission]],109,0) -> 13.771 | E2: =VLOOKUP(A2,PG_FORWARD_SETTLED__1[#All],110,0) -> 71.98 | F2: =VLOOKUP(A2,PG_FORWARD_SETTLED__1[#All],111,0) -> 126.236 | G2: =VLOOKUP(A2,PG_FORWARD_SETTLED__1[#All],112,0) -> 1727.051 | H2: =G2-F2 -> 1600.815 | I2: =B2-G2 -> 682.949 | J2: 0 | K2: - | L2: 1727.051 | M2: Completed | O2: 45939.449
A3: 8746383853 | B3: =VLOOKUP(A3,PG_FORWARD_SETTLED__1[[order_id]:[Customer_Paid]],107,0) -> 2385 | C3: =VLOOKUP(A3,PG_FORWARD_SETTLED__1[[order_id]:[Commission]],108,0) -> 422.145 | D3: =VLOOKUP(A3,PG_FORWARD_SETTLED__1[[#All],[order_id]:[Tax_On_Commission]],109,0) -> 13.628 | E3: =VLOOKUP(A3,PG_FORWARD_SETTLED__1[#All],110,0) -> 71.98 | F3: =VLOOKUP(A3,PG_FORWARD_SETTLED__1[#All],111,0) -> 124.927 | G3: =VLOOKUP(A3,PG_FORWARD_SETTLED__1[#All],112,0) -> 1877.247 | H3: =G3-F3 -> 1752.32 | I3: =B3-G3 -> 507.753 | J3: 0 | K3: - | L3: 1877.247 | M3: Completed | O3: 45940.808
A4: 8725799225 | B4: =VLOOKUP(A4,PG_FORWARD_SETTLED__1[[order_id]:[Customer_Paid]],107,0) -> 2556 | C4: =VLOOKUP(A4,PG_FORWARD_SETTLED__1[[order_id]:[Commission]],108,0) -> 663.538 | D4: =VLOOKUP(A4,PG_FORWARD_SETTLED__1[[#All],[order_id]:[Tax_On_Commission]],109,0) -> 14.605 | E4: =VLOOKUP(A4,PG_FORWARD_SETTLED__1[#All],110,0) -> 71.98 | F4: =VLOOKUP(A4,PG_FORWARD_SETTLED__1[#All],111,0) -> 133.891 | G4: =VLOOKUP(A4,PG_FORWARD_SETTLED__1[#All],112,0) -> 1805.877 | H4: =G4-F4 -> 1671.986 | I4: =B4-G4 -> 750.123 | J4: 0 | K4: - | L4: 1805.877 | M4: Completed | O4: 45931.8
A5: 8718239977 | B5: =VLOOKUP(A5,PG_FORWARD_SETTLED__1[[order_id]:[Customer_Paid]],107,0) -> 3788.99 | C5: =VLOOKUP(A5,PG_FORWARD_SETTLED__1[[order_id]:[Commission]],108,0) -> 938.912 | D5: =VLOOKUP(A5,PG_FORWARD_SETTLED__1[[#All],[order_id]:[Tax_On_Commission]],109,0) -> 19.266 | E5: =VLOOKUP(A5,PG_FORWARD_SETTLED__1[#All],110,0) -> 71.98 | F5: =VLOOKUP(A5,PG_FORWARD_SETTLED__1[#All],111,0) -> 594.035 | G5: =VLOOKUP(A5,PG_FORWARD_SETTLED__1[#All],112,0) -> 2758.832 | H5: =G5-F5 -> 2164.797 | I5: =B5-G5 -> 1030.158 | J5: 0 | K5: - | L5: 2758.832 | M5: Completed | O5: 45930.615
A6: 8752499712 | B6: =VLOOKUP(A6,PG_FORWARD_SETTLED__1[[order_id]:[Customer_Paid]],107,0) -> 2150 | C6: =VLOOKUP(A6,PG_FORWARD_SETTLED__1[[order_id]:[Commission]],108,0) -> 684.99 | D6: =VLOOKUP(A6,PG_FORWARD_SETTLED__1[[#All],[order_id]:[Tax_On_Commission]],109,0) -> 12.286 | E6: =VLOOKUP(A6,PG_FORWARD_SETTLED__1[#All],110,0) -> 71.98 | F6: =VLOOKUP(A6,PG_FORWARD_SETTLED__1[#All],111,0) -> 112.618 | G6: =VLOOKUP(A6,PG_FORWARD_SETTLED__1[#All],112,0) -> 1380.744 | H6: =G6-F6 -> 1268.126 | I6: =B6-G6 -> 769.256 | J6: =VLOOKUP(A6,PG_Reverse_Settled__1[#All],103,0) -> 132.16 | K6: =G6+E6+J6 -> 1584.884 | L6: -204.14 | M6: Return | N6: =VLOOKUP(A6,Return!A:L,12,0) -> I did not like the fit | O6: 45943.449
A7: 8727502935 | B7: =VLOOKUP(A7,PG_FORWARD_SETTLED__1[[order_id]:[Customer_Paid]],107,0) -> 3119 | C7: =VLOOKUP(A7,PG_FORWARD_SETTLED__1[[order_id]:[Commission]],108,0) -> 662.476 | D7: =VLOOKUP(A7,PG_FORWARD_SETTLED__1[[#All],[order_id]:[Tax_On_Commission]],109,0) -> 15.859 | E7: =VLOOKUP(A7,PG_FORWARD_SETTLED__1[#All],110,0) -> 71.98 | F7: =VLOOKUP(A7,PG_FORWARD_SETTLED__1[#All],111,0) -> 488.996 | G7: =VLOOKUP(A7,PG_FORWARD_SETTLED__1[#All],112,0) -> 2368.685 | H7: =G7-F7 -> 1879.689 | I7: =B7-G7 -> 750.315 | J7: =VLOOKUP(A7,PG_Reverse_Settled__1[#All],103,0) -> 107.38 | K7: =G7+E7+J7 -> 2548.045 | L7: -179.36 | M7: Return | N7: =VLOOKUP(A7,Return!A:L,12,0) -> Size too small | O7: 45933.481
A8: 8663926203 | B8: =VLOOKUP(A8,PG_FORWARD_SETTLED__1[[order_id]:[Customer_Paid]],107,0) -> 1454 | C8: =VLOOKUP(A8,PG_FORWARD_SETTLED__1[[order_id]:[Commission]],108,0) -> 325.987 | D8: =VLOOKUP(A8,PG_FORWARD_SETTLED__1[[#All],[order_id]:[Tax_On_Commission]],109,0) -> 7.789 | E8: =VLOOKUP(A8,PG_FORWARD_SETTLED__1[#All],110,0) -> 53.1 | F8: =VLOOKUP(A8,PG_FORWARD_SETTLED__1[#All],111,0) -> 162.281 | G8: =VLOOKUP(A8,PG_FORWARD_SETTLED__1[#All],112,0) -> 1067.124 | H8: =G8-F8 -> 904.843 | I8: =B8-G8 -> 386.876 | J8: =VLOOKUP(A8,PG_Reverse_Settled__1[#All],103,0) -> 197.06 | K8: =G8+E8+J8 -> 1317.284 | L8: -250.16 | M8: Return | N8: =VLOOKUP(A8,Return!A:L,12,0) -> - | O8: 45912.803
A9: 8689247485 | B9: =VLOOKUP(A9,PG_FORWARD_SETTLED__1[[order_id]:[Customer_Paid]],107,0) -> 3564 | C9: =VLOOKUP(A9,PG_FORWARD_SETTLED__1[[order_id]:[Commission]],108,0) -> 883.159 | D9: =VLOOKUP(A9,PG_FORWARD_SETTLED__1[[#All],[order_id]:[Tax_On_Commission]],109,0) -> 18.122 | E9: =VLOOKUP(A9,PG_FORWARD_SETTLED__1[#All],110,0) -> 71.98 | F9: =VLOOKUP(A9,PG_FORWARD_SETTLED__1[#All],111,0) -> 558.762 | G9: =VLOOKUP(A9,PG_FORWARD_SETTLED__1[#All],112,0) -> 2590.739 | H9: =G9-F9 -> 2031.977 | I9: =B9-G9 -> 973.261 | J9: =VLOOKUP(A9,PG_Reverse_Settled__1[#All],103,0) -> 197.06 | K9: =G9+E9+J9 -> 2859.779 | L9: -269.04 | M9: Return | N9: =VLOOKUP(A9,Return!A:L,12,0) -> I did not like the fit | O9: 45922.443
A10: 8694687361 | B10: =VLOOKUP(A10,PG_FORWARD_SETTLED__1[[order_id]:[Customer_Paid]],107,0) -> 3142.99 | C10: =VLOOKUP(A10,PG_FORWARD_SETTLED__1[[order_id]:[Commission]],108,0) -> 667.571 | D10: =VLOOKUP(A10,PG_FORWARD_SETTLED__1[[#All],[order_id]:[Tax_On_Commission]],109,0) -> 15.982 | E10: =VLOOKUP(A10,PG_FORWARD_SETTLED__1[#All],110,0) -> 71.98 | F10: =VLOOKUP(A10,PG_FORWARD_SETTLED__1[#All],111,0) -> 492.758 | G10: =VLOOKUP(A10,PG_FORWARD_SETTLED__1[#All],112,0) -> 2387.457 | H10: =G10-F10 -> 1894.699 | I10: =B10-G10 -> 755.533 | J10: 0 | K10: - | L10: 2387.457 | M10: Completed | O10: 45922.443
A11: 8687587807 | B11: =VLOOKUP(A11,PG_FORWARD_SETTLED__1[[order_id]:[Customer_Paid]],107,0) -> 3104 | C11: =VLOOKUP(A11,PG_FORWARD_SETTLED__1[[order_id]:[Commission]],108,0) -> 769.171 | D11: =VLOOKUP(A11,PG_FORWARD_SETTLED__1[[#All],[order_id]:[Tax_On_Commission]],109,0) -> 15.784 | E11: =VLOOKUP(A11,PG_FORWARD_SETTLED__1[#All],110,0) -> 71.98 | F11: =VLOOKUP(A11,PG_FORWARD_SETTLED__1[#All],111,0) -> 486.643 | G11: =VLOOKUP(A11,PG_FORWARD_SETTLED__1[#All],112,0) -> 2247.065 | H11: =G11-F11 -> 1760.422 | I11: =B11-G11 -> 856.935 | J11: 0 | K11: - | L11: 2247.065 | M11: Completed | O11: 45922.443
A12: 8688316765 | B12: =VLOOKUP(A12,PG_FORWARD_SETTLED__1[[order_id]:[Customer_Paid]],107,0) -> 2594 | C12: =VLOOKUP(A12,PG_FORWARD_SETTLED__1[[order_id]:[Commission]],108,0) -> 550.966 | D12: =VLOOKUP(A12,PG_FORWARD_SETTLED__1[[#All],[order_id]:[Tax_On_Commission]],109,0) -> 14.822 | E12: =VLOOKUP(A12,PG_FORWARD_SETTLED__1[#All],110,0) -> 71.98 | F12: =VLOOKUP(A12,PG_FORWARD_SETTLED__1[#All],111,0) -> 135.872 | G12: =VLOOKUP(A12,PG_FORWARD_SETTLED__1[#All],112,0) -> 1956.232 | H12: =G12-F12 -> 1820.36 | I12: =B12-G12 -> 637.768 | J12: =VLOOKUP(A12,PG_Reverse_Settled__1[#All],103,0) -> 197.06 | K12: =G12+E12+J12 -> 2225.272 | L12: -269.04 | M12: Return | N12: =VLOOKUP(A12,Return!A:L,12,0) -> I did not like the fit | O12: 45922.443
A13: 8717002058 | B13: =VLOOKUP(A13,PG_FORWARD_SETTLED__1[[order_id]:[Customer_Paid]],107,0) -> 3118.99 | C13: =VLOOKUP(A13,PG_FORWARD_SETTLED__1[[order_id]:[Commission]],108,0) -> 662.473 | D13: =VLOOKUP(A13,PG_FORWARD_SETTLED__1[[#All],[order_id]:[Tax_On_Commission]],109,0) -> 15.859 | E13: =VLOOKUP(A13,PG_FORWARD_SETTLED__1[#All],110,0) -> 71.98 | F13: =VLOOKUP(A13,PG_FORWARD_SETTLED__1[#All],111,0) -> 488.996 | G13: =VLOOKUP(A13,PG_FORWARD_SETTLED__1[#All],112,0) -> 2368.678 | H13: =G13-F13 -> 1879.682 | I13: =B13-G13 -> 750.312 | J13: =VLOOKUP(A13,PG_Reverse_Settled__1[#All],103,0) -> 132.16 | K13: =G13+E13+J13 -> 2572.818 | L13: -204.14 | M13: Return | N13: =VLOOKUP(A13,Return!A:L,12,0) -> - | O13: 45930.615
A14: 8670163180 | B14: =VLOOKUP(A14,PG_FORWARD_SETTLED__1[[order_id]:[Customer_Paid]],107,0) -> 1610 | C14: =VLOOKUP(A14,PG_FORWARD_SETTLED__1[[order_id]:[Commission]],108,0) -> 360.962 | D14: =VLOOKUP(A14,PG_FORWARD_SETTLED__1[[#All],[order_id]:[Tax_On_Commission]],109,0) -> 8.626 | E14: =VLOOKUP(A14,PG_FORWARD_SETTLED__1[#All],110,0) -> 53.1 | F14: =VLOOKUP(A14,PG_FORWARD_SETTLED__1[#All],111,0) -> 179.688 | G14: =VLOOKUP(A14,PG_FORWARD_SETTLED__1[#All],112,0) -> 1187.312 | H14: =G14-F14 -> 1007.624 | I14: =B14-G14 -> 422.688 | J14: 0 | K14: - | L14: 1187.312 | M14: Completed | O14: 45915.472
A15: 8741339872 | B15: =VLOOKUP(A15,PG_FORWARD_SETTLED__1[[order_id]:[Customer_Paid]],107,0) -> 1421 | C15: =VLOOKUP(A15,PG_FORWARD_SETTLED__1[[order_id]:[Commission]],108,0) -> 385.659 | D15: =VLOOKUP(A15,PG_FORWARD_SETTLED__1[[#All],[order_id]:[Tax_On_Commission]],109,0) -> 8.12 | E15: =VLOOKUP(A15,PG_FORWARD_SETTLED__1[#All],110,0) -> 53.1 | F15: =VLOOKUP(A15,PG_FORWARD_SETTLED__1[#All],111,0) -> 74.437 | G15: =VLOOKUP(A15,PG_FORWARD_SETTLED__1[#All],112,0) -> 974.121 | H15: =G15-F15 -> 899.684 | I15: =B15-G15 -> 446.879 | J15: =VLOOKUP(A15,PG_Reverse_Settled__1[#All],103,0) -> 197.06 | K15: =G15+E15+J15 -> 1224.281 | L15: -250.16 | M15: Return | N15: =VLOOKUP(A15,Return!A:L,12,0) -> - | O15: 45938.423
A16: 8720752290 | B16: =VLOOKUP(A16,PG_FORWARD_SETTLED__1[[order_id]:[Customer_Paid]],107,0) -> 2944 | C16: =VLOOKUP(A16,PG_FORWARD_SETTLED__1[[order_id]:[Commission]],108,0) -> 729.523 | D16: =VLOOKUP(A16,PG_FORWARD_SETTLED__1[[#All],[order_id]:[Tax_On_Commission]],109,0) -> 14.97 | E16: =VLOOKUP(A16,PG_FORWARD_SETTLED__1[#All],110,0) -> 71.98 | F16: =VLOOKUP(A16,PG_FORWARD_SETTLED__1[#All],111,0) -> 461.565 | G16: =VLOOKUP(A16,PG_FORWARD_SETTLED__1[#All],112,0) -> 2127.527 | H16: =G16-F16 -> 1665.962 | I16: =B16-G16 -> 816.473 | J16: 0 | K16: - | L16: 2127.527 | M16: Completed | O16: 45930.615
A17: 8657021789 | B17: =VLOOKUP(A17,PG_FORWARD_SETTLED__1[[order_id]:[Customer_Paid]],107,0) -> 706 | C17: =VLOOKUP(A17,PG_FORWARD_SETTLED__1[[order_id]:[Commission]],108,0) -> 208.27 | D17: =VLOOKUP(A17,PG_FORWARD_SETTLED__1[[#All],[order_id]:[Tax_On_Commission]],109,0) -> 4.034 | E17: =VLOOKUP(A17,PG_FORWARD_SETTLED__1[#All],110,0) -> 31.86 | F17: =VLOOKUP(A17,PG_FORWARD_SETTLED__1[#All],111,0) -> 36.982 | G17: =VLOOKUP(A17,PG_FORWARD_SETTLED__1[#All],112,0) -> 461.836 | H17: =G17-F17 -> 424.854 | I17: =B17-G17 -> 244.164 | J17: 0 | K17: - | L17: 461.836 | M17: Completed | O17: 45909.456
A18: 8737192003 | B18: =VLOOKUP(A18,PG_FORWARD_SETTLED__1[[order_id]:[Customer_Paid]],107,0) -> 391 | C18: =VLOOKUP(A18,PG_FORWARD_SETTLED__1[[order_id]:[Commission]],108,0) -> 9.228 | D18: =VLOOKUP(A18,PG_FORWARD_SETTLED__1[[#All],[order_id]:[Tax_On_Commission]],109,0) -> 2.234 | E18: =VLOOKUP(A18,PG_FORWARD_SETTLED__1[#All],110,0) -> 31.86 | F18: =VLOOKUP(A18,PG_FORWARD_SETTLED__1[#All],111,0) -> 20.482 | G18: =VLOOKUP(A18,PG_FORWARD_SETTLED__1[#All],112,0) -> 347.678 | H18: =G18-F18 -> 327.196 | I18: =B18-G18 -> 43.322 | J18: =VLOOKUP(A18,PG_Reverse_Settled__1[#All],103,0) -> 197.06 | K18: =G18+E18+J18 -> 576.598 | L18: -228.92 | M18: Return | N18: =VLOOKUP(A18,Return!A:L,12,0) -> I did not like the fit | O18: 45936.455
A19: 8715339734 | B19: =VLOOKUP(A19,PG_FORWARD_SETTLED__1[[order_id]:[Customer_Paid]],107,0) -> 3470 | C19: =VLOOKUP(A19,PG_FORWARD_SETTLED__1[[order_id]:[Commission]],108,0) -> 1105.542 | D19: =VLOOKUP(A19,PG_FORWARD_SETTLED__1[[#All],[order_id]:[Tax_On_Commission]],109,0) -> 17.644 | E19: =VLOOKUP(A19,PG_FORWARD_SETTLED__1[#All],110,0) -> 71.98 | F19: =VLOOKUP(A19,PG_FORWARD_SETTLED__1[#All],111,0) -> 544.023 | G19: =VLOOKUP(A19,PG_FORWARD_SETTLED__1[#All],112,0) -> 2274.834 | H19: =G19-F19 -> 1730.811 | I19: =B19-G19 -> 1195.166 | J19: 0 | K19: - | L19: 2274.834 | M19: Completed | O19: 45929.449
A20: 8697412249 | B20: =VLOOKUP(A20,PG_FORWARD_SETTLED__1[[order_id]:[Customer_Paid]],107,0) -> 3109 | C20: =VLOOKUP(A20,PG_FORWARD_SETTLED__1[[order_id]:[Commission]],108,0) -> 660.352 | D20: =VLOOKUP(A20,PG_FORWARD_SETTLED__1[[#All],[order_id]:[Tax_On_Commission]],109,0) -> 15.809 | E20: =VLOOKUP(A20,PG_FORWARD_SETTLED__1[#All],110,0) -> 71.98 | F20: =VLOOKUP(A20,PG_FORWARD_SETTLED__1[#All],111,0) -> 487.434 | G20: =VLOOKUP(A20,PG_FORWARD_SETTLED__1[#All],112,0) -> 2360.859 | H20: =G20-F20 -> 1873.425 | I20: =B20-G20 -> 748.141 | J20: 0 | K20: - | L20: 2360.859 | M20: Completed | O20: 45922.78
A21: 8723563426 | B21: =VLOOKUP(A21,PG_FORWARD_SETTLED__1[[order_id]:[Customer_Paid]],107,0) -> 3734 | C21: =VLOOKUP(A21,PG_FORWARD_SETTLED__1[[order_id]:[Commission]],108,0) -> 969.346 | D21: =VLOOKUP(A21,PG_FORWARD_SETTLED__1[[#All],[order_id]:[Tax_On_Commission]],109,0) -> 18.986 | E21: =VLOOKUP(A21,PG_FORWARD_SETTLED__1[#All],110,0) -> 71.98 | F21: =VLOOKUP(A21,PG_FORWARD_SETTLED__1[#All],111,0) -> 585.412 | G21: =VLOOKUP(A21,PG_FORWARD_SETTLED__1[#All],112,0) -> 2673.688 | H21: =G21-F21 -> 2088.276 | I21: =B21-G21 -> 1060.312 | J21: 0 | K21: - | L21: 2673.688 | M21: Completed | O21: 45931.463
A22: 8715259067 | B22: =VLOOKUP(A22,PG_FORWARD_SETTLED__1[[order_id]:[Customer_Paid]],107,0) -> 2150 | C22: =VLOOKUP(A22,PG_FORWARD_SETTLED__1[[order_id]:[Commission]],108,0) -> 684.99 | D22: =VLOOKUP(A22,PG_FORWARD_SETTLED__1[[#All],[order_id]:[Tax_On_Commission]],109,0) -> 12.286 | E22: =VLOOKUP(A22,PG_FORWARD_SETTLED__1[#All],110,0) -> 71.98 | F22: =VLOOKUP(A22,PG_FORWARD_SETTLED__1[#All],111,0) -> 112.618 | G22: =VLOOKUP(A22,PG_FORWARD_SETTLED__1[#All],112,0) -> 1380.744 | H22: =G22-F22 -> 1268.126 | I22: =B22-G22 -> 769.256 | J22: =VLOOKUP(A22,PG_Reverse_Settled__1[#All],103,0) -> 197.06 | K22: =G22+E22+J22 -> 1649.784 | L22: -269.04 | M22: Return | N22: =VLOOKUP(A22,Return!A:L,12,0) -> Size too small | O22: 45929.449
A23: 8742176123 | B23: =VLOOKUP(A23,PG_FORWARD_SETTLED__1[[order_id]:[Customer_Paid]],107,0) -> 2198 | C23: =VLOOKUP(A23,PG_FORWARD_SETTLED__1[[order_id]:[Commission]],108,0) -> 570.601 | D23: =VLOOKUP(A23,PG_FORWARD_SETTLED__1[[#All],[order_id]:[Tax_On_Commission]],109,0) -> 12.56 | E23: =VLOOKUP(A23,PG_FORWARD_SETTLED__1[#All],110,0) -> 71.98 | F23: =VLOOKUP(A23,PG_FORWARD_SETTLED__1[#All],111,0) -> 115.137 | G23: =VLOOKUP(A23,PG_FORWARD_SETTLED__1[#All],112,0) -> 1542.859 | H23: =G23-F23 -> 1427.722 | I23: =B23-G23 -> 655.141 | J23: 0 | K23: - | L23: 1542.859 | M23: Completed | O23: 45938.519
A24: 8682082418 | B24: =VLOOKUP(A24,PG_FORWARD_SETTLED__1[[order_id]:[Customer_Paid]],107,0) -> 1694 | C24: =VLOOKUP(A24,PG_FORWARD_SETTLED__1[[order_id]:[Commission]],108,0) -> 499.73 | D24: =VLOOKUP(A24,PG_FORWARD_SETTLED__1[[#All],[order_id]:[Tax_On_Commission]],109,0) -> 9.074 | E24: =VLOOKUP(A24,PG_FORWARD_SETTLED__1[#All],110,0) -> 53.1 | F24: =VLOOKUP(A24,PG_FORWARD_SETTLED__1[#All],111,0) -> 189.062 | G24: =VLOOKUP(A24,PG_FORWARD_SETTLED__1[#All],112,0) -> 1132.096 | H24: =G24-F24 -> 943.034 | I24: =B24-G24 -> 561.904 | J24: 0 | K24: - | L24: 1132.096 | M24: Completed | O24: 45919.525
A25: 8747034027 | B25: =VLOOKUP(A25,PG_FORWARD_SETTLED__1[[order_id]:[Customer_Paid]],107,0) -> 3564 | C25: =VLOOKUP(A25,PG_FORWARD_SETTLED__1[[order_id]:[Commission]],108,0) -> 883.159 | D25: =VLOOKUP(A25,PG_FORWARD_SETTLED__1[[#All],[order_id]:[Tax_On_Commission]],109,0) -> 18.122 | E25: =VLOOKUP(A25,PG_FORWARD_SETTLED__1[#All],110,0) -> 71.98 | F25: =VLOOKUP(A25,PG_FORWARD_SETTLED__1[#All],111,0) -> 558.762 | G25: =VLOOKUP(A25,PG_FORWARD_SETTLED__1[#All],112,0) -> 2590.739 | H25: =G25-F25 -> 2031.977 | I25: =B25-G25 -> 973.261 | J25: 0 | K25: - | L25: 2590.739 | M25: Completed | O25: 45941.44
A26: 8737583490 | B26: =VLOOKUP(A26,PG_FORWARD_SETTLED__1[[order_id]:[Customer_Paid]],107,0) -> 1644 | C26: =VLOOKUP(A26,PG_FORWARD_SETTLED__1[[order_id]:[Commission]],108,0) -> 543.178 | D26: =VLOOKUP(A26,PG_FORWARD_SETTLED__1[[#All],[order_id]:[Tax_On_Commission]],109,0) -> 9.395 | E26: =VLOOKUP(A26,PG_FORWARD_SETTLED__1[#All],110,0) -> 53.1 | F26: =VLOOKUP(A26,PG_FORWARD_SETTLED__1[#All],111,0) -> 86.119 | G26: =VLOOKUP(A26,PG_FORWARD_SETTLED__1[#All],112,0) -> 1038.327 | H26: =G26-F26 -> 952.208 | I26: =B26-G26 -> 605.673 | J26: =VLOOKUP(A26,PG_Reverse_Settled__1[#All],103,0) -> 197.06 | K26: =G26+E26+J26 -> 1288.487 | L26: -250.16 | M26: Return | N26: =VLOOKUP(A26,Return!A:L,12,0) -> - | O26: 45936.455
A27: 8739466534 | B27: =VLOOKUP(A27,PG_FORWARD_SETTLED__1[[order_id]:[Customer_Paid]],107,0) -> 4445 | C27: =VLOOKUP(A27,PG_FORWARD_SETTLED__1[[order_id]:[Commission]],108,0) -> 1101.471 | D27: =VLOOKUP(A27,PG_FORWARD_SETTLED__1[[#All],[order_id]:[Tax_On_Commission]],109,0) -> 22.602 | E27: =VLOOKUP(A27,PG_FORWARD_SETTLED__1[#All],110,0) -> 71.98 | F27: =VLOOKUP(A27,PG_FORWARD_SETTLED__1[#All],111,0) -> 696.885 | G27: =VLOOKUP(A27,PG_FORWARD_SETTLED__1[#All],112,0) -> 3248.947 | H27: =G27-F27 -> 2552.062 | I27: =B27-G27 -> 1196.053 | J27: =VLOOKUP(A27,PG_Reverse_Settled__1[#All],103,0) -> 197.06 | K27: =G27+E27+J27 -> 3517.987 | L27: -269.04 | M27: Return | N27: =VLOOKUP(A27,Return!A:L,12,0) -> Size too small | O27: 45937.468
A28: 8735054496 | B28: =VLOOKUP(A28,PG_FORWARD_SETTLED__1[[order_id]:[Customer_Paid]],107,0) -> 3169 | C28: =VLOOKUP(A28,PG_FORWARD_SETTLED__1[[order_id]:[Commission]],108,0) -> 785.278 | D28: =VLOOKUP(A28,PG_FORWARD_SETTLED__1[[#All],[order_id]:[Tax_On_Commission]],109,0) -> 16.114 | E28: =VLOOKUP(A28,PG_FORWARD_SETTLED__1[#All],110,0) -> 71.98 | F28: =VLOOKUP(A28,PG_FORWARD_SETTLED__1[#All],111,0) -> 496.838 | G28: =VLOOKUP(A28,PG_FORWARD_SETTLED__1[#All],112,0) -> 2295.628 | H28: =G28-F28 -> 1798.79 | I28: =B28-G28 -> 873.372 | J28: 0 | K28: - | L28: 2295.628 | M28: Completed | O28: 45935.461
A29: 8675097215 | B29: =VLOOKUP(A29,PG_FORWARD_SETTLED__1[[order_id]:[Customer_Paid]],107,0) -> 2794 | C29: =VLOOKUP(A29,PG_FORWARD_SETTLED__1[[order_id]:[Commission]],108,0) -> 692.353 | D29: =VLOOKUP(A29,PG_FORWARD_SETTLED__1[[#All],[order_id]:[Tax_On_Commission]],109,0) -> 14.968 | E29: =VLOOKUP(A29,PG_FORWARD_SETTLED__1[#All],110,0) -> 71.98 | F29: =VLOOKUP(A29,PG_FORWARD_SETTLED__1[#All],111,0) -> 311.833 | G29: =VLOOKUP(A29,PG_FORWARD_SETTLED__1[#All],112,0) -> 2014.699 | H29: =G29-F29 -> 1702.866 | I29: =B29-G29 -> 779.301 | J29: 0 | K29: - | L29: 2014.699 | M29: Completed | O29: 45916.56
A30: 8599978899 | B30: =VLOOKUP(A30,PG_FORWARD_SETTLED__1[[order_id]:[Customer_Paid]],107,0) -> 1179 | C30: =VLOOKUP(A30,PG_FORWARD_SETTLED__1[[order_id]:[Commission]],108,0) -> 292.156 | D30: =VLOOKUP(A30,PG_FORWARD_SETTLED__1[[#All],[order_id]:[Tax_On_Commission]],109,0) -> 6.316 | E30: =VLOOKUP(A30,PG_FORWARD_SETTLED__1[#All],110,0) -> 53.1 | F30: =VLOOKUP(A30,PG_FORWARD_SETTLED__1[#All],111,0) -> 131.583 | G30: =VLOOKUP(A30,PG_FORWARD_SETTLED__1[#All],112,0) -> 827.428 | H30: =G30-F30 -> 695.845 | I30: =B30-G30 -> 351.572 | J30: 0 | K30: - | L30: 827.428 | M30: Completed | O30: 45873.626
A31: 8744260042 | B31: =VLOOKUP(A31,PG_FORWARD_SETTLED__1[[order_id]:[Customer_Paid]],107,0) -> 3102 | C31: =VLOOKUP(A31,PG_FORWARD_SETTLED__1[[order_id]:[Commission]],108,0) -> 805.279 | D31: =VLOOKUP(A31,PG_FORWARD_SETTLED__1[[#All],[order_id]:[Tax_On_Commission]],109,0) -> 15.773 | E31: =VLOOKUP(A31,PG_FORWARD_SETTLED__1[#All],110,0) -> 71.98 | F31: =VLOOKUP(A31,PG_FORWARD_SETTLED__1[#All],111,0) -> 486.334 | G31: =VLOOKUP(A31,PG_FORWARD_SETTLED__1[#All],112,0) -> 2208.968 | H31: =G31-F31 -> 1722.634 | I31: =B31-G31 -> 893.032 | J31: =VLOOKUP(A31,PG_Reverse_Settled__1[#All],103,0) -> 197.06 | K31: =G31+E31+J31 -> 2478.008 | L31: -269.04 | M31: Return | N31: =VLOOKUP(A31,Return!A:L,12,0) -> - | O31: 45939.576
A32: 8691422928 | B32: =VLOOKUP(A32,PG_FORWARD_SETTLED__1[[order_id]:[Customer_Paid]],107,0) -> 3564 | C32: =VLOOKUP(A32,PG_FORWARD_SETTLED__1[[order_id]:[Commission]],108,0) -> 883.159 | D32: =VLOOKUP(A32,PG_FORWARD_SETTLED__1[[#All],[order_id]:[Tax_On_Commission]],109,0) -> 18.122 | E32: =VLOOKUP(A32,PG_FORWARD_SETTLED__1[#All],110,0) -> 71.98 | F32: =VLOOKUP(A32,PG_FORWARD_SETTLED__1[#All],111,0) -> 558.762 | G32: =VLOOKUP(A32,PG_FORWARD_SETTLED__1[#All],112,0) -> 2590.739 | H32: =G32-F32 -> 2031.977 | I32: =B32-G32 -> 973.261 | J32: =VLOOKUP(A32,PG_Reverse_Settled__1[#All],103,0) -> 132.16 | K32: =G32+E32+J32 -> 2794.879 | L32: -204.14 | M32: Return | N32: =VLOOKUP(A32,Return!A:L,12,0) -> I did not like the fit | O32: 45922.443
A33: 8694664241 | B33: =VLOOKUP(A33,PG_FORWARD_SETTLED__1[[order_id]:[Customer_Paid]],107,0) -> 2293 | C33: =VLOOKUP(A33,PG_FORWARD_SETTLED__1[[order_id]:[Commission]],108,0) -> 730.55 | D33: =VLOOKUP(A33,PG_FORWARD_SETTLED__1[[#All],[order_id]:[Tax_On_Commission]],109,0) -> 13.103 | E33: =VLOOKUP(A33,PG_FORWARD_SETTLED__1[#All],110,0) -> 71.98 | F33: =VLOOKUP(A33,PG_FORWARD_SETTLED__1[#All],111,0) -> 120.119 | G33: =VLOOKUP(A33,PG_FORWARD_SETTLED__1[#All],112,0) -> 1477.367 | H33: =G33-F33 -> 1357.248 | I33: =B33-G33 -> 815.633 | J33: =VLOOKUP(A33,PG_Reverse_Settled__1[#All],103,0) -> 107.38 | K33: =G33+E33+J33 -> 1656.727 | L33: -179.36 | M33: Return | N33: =VLOOKUP(A33,Return!A:L,12,0) -> Received a poor quality product | O33: 45922.443
A34: 8686235629 | B34: =VLOOKUP(A34,PG_FORWARD_SETTLED__1[[order_id]:[Customer_Paid]],107,0) -> 4219 | C34: =VLOOKUP(A34,PG_FORWARD_SETTLED__1[[order_id]:[Commission]],108,0) -> 1045.468 | D34: =VLOOKUP(A34,PG_FORWARD_SETTLED__1[[#All],[order_id]:[Tax_On_Commission]],109,0) -> 22.602 | E34: =VLOOKUP(A34,PG_FORWARD_SETTLED__1[#All],110,0) -> 71.98 | F34: =VLOOKUP(A34,PG_FORWARD_SETTLED__1[#All],111,0) -> 470.875 | G34: =VLOOKUP(A34,PG_FORWARD_SETTLED__1[#All],112,0) -> 3078.95 | H34: =G34-F34 -> 2608.075 | I34: =B34-G34 -> 1140.05 | J34: =VLOOKUP(A34,PG_Reverse_Settled__1[#All],103,0) -> 197.06 | K34: =G34+E34+J34 -> 3347.99 | L34: -269.04 | M34: Return | N34: =VLOOKUP(A34,Return!A:L,12,0) -> Received a poor quality product | O34: 45920.474
A35: 8743152600 | B35: =VLOOKUP(A35,PG_FORWARD_SETTLED__1[[order_id]:[Customer_Paid]],107,0) -> 2409.99 | C35: =VLOOKUP(A35,PG_FORWARD_SETTLED__1[[order_id]:[Commission]],108,0) -> 597.196 | D35: =VLOOKUP(A35,PG_FORWARD_SETTLED__1[[#All],[order_id]:[Tax_On_Commission]],109,0) -> 13.771 | E35: =VLOOKUP(A35,PG_FORWARD_SETTLED__1[#All],110,0) -> 71.98 | F35: =VLOOKUP(A35,PG_FORWARD_SETTLED__1[#All],111,0) -> 126.236 | G35: =VLOOKUP(A35,PG_FORWARD_SETTLED__1[#All],112,0) -> 1727.043 | H35: =G35-F35 -> 1600.807 | I35: =B35-G35 -> 682.947 | J35: =VLOOKUP(A35,PG_Reverse_Settled__1[#All],103,0) -> 132.16 | K35: =G35+E35+J35 -> 1931.183 | L35: -204.14 | M35: Return | N35: =VLOOKUP(A35,Return!A:L,12,0) -> Product image was better than the actual product | O35: 45939.449
A36: 8745416575 | B36: =VLOOKUP(A36,PG_FORWARD_SETTLED__1[[order_id]:[Customer_Paid]],107,0) -> 416 | C36: =VLOOKUP(A36,PG_FORWARD_SETTLED__1[[order_id]:[Commission]],108,0) -> 34.362 | D36: =VLOOKUP(A36,PG_FORWARD_SETTLED__1[[#All],[order_id]:[Tax_On_Commission]],109,0) -> 2.377 | E36: =VLOOKUP(A36,PG_FORWARD_SETTLED__1[#All],110,0) -> 31.86 | F36: =VLOOKUP(A36,PG_FORWARD_SETTLED__1[#All],111,0) -> 21.791 | G36: =VLOOKUP(A36,PG_FORWARD_SETTLED__1[#All],112,0) -> 347.401 | H36: =G36-F36 -> 325.61 | I36: =B36-G36 -> 68.599 | J36: 0 | K36: - | L36: 347.401 | M36: Completed | O36: 45940.445
A37: 8717347916 | B37: =VLOOKUP(A37,PG_FORWARD_SETTLED__1[[order_id]:[Customer_Paid]],107,0) -> 3119 | C37: =VLOOKUP(A37,PG_FORWARD_SETTLED__1[[order_id]:[Commission]],108,0) -> 662.476 | D37: =VLOOKUP(A37,PG_FORWARD_SETTLED__1[[#All],[order_id]:[Tax_On_Commission]],109,0) -> 15.859 | E37: =VLOOKUP(A37,PG_FORWARD_SETTLED__1[#All],110,0) -> 71.98 | F37: =VLOOKUP(A37,PG_FORWARD_SETTLED__1[#All],111,0) -> 488.996 | G37: =VLOOKUP(A37,PG_FORWARD_SETTLED__1[#All],112,0) -> 2368.685 | H37: =G37-F37 -> 1879.689 | I37: =B37-G37 -> 750.315 | J37: 0 | K37: - | L37: 2368.685 | M37: Completed | O37: 45930.615
A38: 8681243759 | B38: =VLOOKUP(A38,PG_FORWARD_SETTLED__1[[order_id]:[Customer_Paid]],107,0) -> 2275 | C38: =VLOOKUP(A38,PG_FORWARD_SETTLED__1[[order_id]:[Commission]],108,0) -> 563.745 | D38: =VLOOKUP(A38,PG_FORWARD_SETTLED__1[[#All],[order_id]:[Tax_On_Commission]],109,0) -> 12.187 | E38: =VLOOKUP(A38,PG_FORWARD_SETTLED__1[#All],110,0) -> 71.98 | F38: =VLOOKUP(A38,PG_FORWARD_SETTLED__1[#All],111,0) -> 253.906 | G38: =VLOOKUP(A38,PG_FORWARD_SETTLED__1[#All],112,0) -> 1627.088 | H38: =G38-F38 -> 1373.182 | I38: =B38-G38 -> 647.912 | J38: 0 | K38: - | L38: 1627.088 | M38: Completed | O38: 45919.434
A39: 8707877371 | B39: =VLOOKUP(A39,PG_FORWARD_SETTLED__1[[order_id]:[Customer_Paid]],107,0) -> 3104 | C39: =VLOOKUP(A39,PG_FORWARD_SETTLED__1[[order_id]:[Commission]],108,0) -> 769.171 | D39: =VLOOKUP(A39,PG_FORWARD_SETTLED__1[[#All],[order_id]:[Tax_On_Commission]],109,0) -> 15.783 | E39: =VLOOKUP(A39,PG_FORWARD_SETTLED__1[#All],110,0) -> 71.98 | F39: =VLOOKUP(A39,PG_FORWARD_SETTLED__1[#All],111,0) -> 486.643 | G39: =VLOOKUP(A39,PG_FORWARD_SETTLED__1[#All],112,0) -> 2247.066 | H39: =G39-F39 -> 1760.423 | I39: =B39-G39 -> 856.934 | J39: 0 | K39: - | L39: 2247.066 | M39: Completed | O39: 45925.776
A40: 8748140593 | B40: =VLOOKUP(A40,PG_FORWARD_SETTLED__1[[order_id]:[Customer_Paid]],107,0) -> 3743 | C40: =VLOOKUP(A40,PG_FORWARD_SETTLED__1[[order_id]:[Commission]],108,0) -> 927.515 | D40: =VLOOKUP(A40,PG_FORWARD_SETTLED__1[[#All],[order_id]:[Tax_On_Commission]],109,0) -> 19.032 | E40: =VLOOKUP(A40,PG_FORWARD_SETTLED__1[#All],110,0) -> 71.98 | F40: =VLOOKUP(A40,PG_FORWARD_SETTLED__1[#All],111,0) -> 586.83 | G40: =VLOOKUP(A40,PG_FORWARD_SETTLED__1[#All],112,0) -> 2724.473 | H40: =G40-F40 -> 2137.643 | I40: =B40-G40 -> 1018.527 | J40: =VLOOKUP(A40,PG_Reverse_Settled__1[#All],103,0) -> 132.16 | K40: =G40+E40+J40 -> 2928.613 | L40: -204.14 | M40: Return | N40: =VLOOKUP(A40,Return!A:L,12,0) -> - | O40: 45941.551
A41: 8742706323 | B41: =VLOOKUP(A41,PG_FORWARD_SETTLED__1[[order_id]:[Customer_Paid]],107,0) -> 368 | C41: =VLOOKUP(A41,PG_FORWARD_SETTLED__1[[order_id]:[Commission]],108,0) -> 8.685 | D41: =VLOOKUP(A41,PG_FORWARD_SETTLED__1[[#All],[order_id]:[Tax_On_Commission]],109,0) -> 2.102 | E41: =VLOOKUP(A41,PG_FORWARD_SETTLED__1[#All],110,0) -> 31.86 | F41: =VLOOKUP(A41,PG_FORWARD_SETTLED__1[#All],111,0) -> 19.272 | G41: =VLOOKUP(A41,PG_FORWARD_SETTLED__1[#All],112,0) -> 325.353 | H41: =G41-F41 -> 306.081 | I41: =B41-G41 -> 42.647 | J41: 0 | K41: - | L41: 325.353 | M41: Completed | O41: 45938.797
A42: 8725349158 | B42: =VLOOKUP(A42,PG_FORWARD_SETTLED__1[[order_id]:[Customer_Paid]],107,0) -> 2198 | C42: =VLOOKUP(A42,PG_FORWARD_SETTLED__1[[order_id]:[Commission]],108,0) -> 570.601 | D42: =VLOOKUP(A42,PG_FORWARD_SETTLED__1[[#All],[order_id]:[Tax_On_Commission]],109,0) -> 12.56 | E42: =VLOOKUP(A42,PG_FORWARD_SETTLED__1[#All],110,0) -> 71.98 | F42: =VLOOKUP(A42,PG_FORWARD_SETTLED__1[#All],111,0) -> 115.137 | G42: =VLOOKUP(A42,PG_FORWARD_SETTLED__1[#All],112,0) -> 1542.859 | H42: =G42-F42 -> 1427.722 | I42: =B42-G42 -> 655.141 | J42: =VLOOKUP(A42,PG_Reverse_Settled__1[#All],103,0) -> 197.06 | K42: =G42+E42+J42 -> 1811.899 | L42: -269.04 | M42: Return | N42: =VLOOKUP(A42,Return!A:L,12,0) -> I did not like the fit | O42: 45931.8
A43: 8664301435 | B43: =VLOOKUP(A43,PG_FORWARD_SETTLED__1[[order_id]:[Customer_Paid]],107,0) -> 1108.99 | C43: =VLOOKUP(A43,PG_FORWARD_SETTLED__1[[order_id]:[Commission]],108,0) -> 248.636 | D43: =VLOOKUP(A43,PG_FORWARD_SETTLED__1[[#All],[order_id]:[Tax_On_Commission]],109,0) -> 5.941 | E43: =VLOOKUP(A43,PG_FORWARD_SETTLED__1[#All],110,0) -> 53.1 | F43: =VLOOKUP(A43,PG_FORWARD_SETTLED__1[#All],111,0) -> 123.771 | G43: =VLOOKUP(A43,PG_FORWARD_SETTLED__1[#All],112,0) -> 801.313 | H43: =G43-F43 -> 677.542 | I43: =B43-G43 -> 307.677 | J43: 0 | K43: - | L43: 801.313 | M43: Completed | O43: 45913.451
A44: 8740468522 | B44: =VLOOKUP(A44,PG_FORWARD_SETTLED__1[[order_id]:[Customer_Paid]],107,0) -> 391 | C44: =VLOOKUP(A44,PG_FORWARD_SETTLED__1[[order_id]:[Commission]],108,0) -> 9.228 | D44: =VLOOKUP(A44,PG_FORWARD_SETTLED__1[[#All],[order_id]:[Tax_On_Commission]],109,0) -> 2.234 | E44: =VLOOKUP(A44,PG_FORWARD_SETTLED__1[#All],110,0) -> 31.86 | F44: =VLOOKUP(A44,PG_FORWARD_SETTLED__1[#All],111,0) -> 20.482 | G44: =VLOOKUP(A44,PG_FORWARD_SETTLED__1[#All],112,0) -> 347.678 | H44: =G44-F44 -> 327.196 | I44: =B44-G44 -> 43.322 | J44: =VLOOKUP(A44,PG_Reverse_Settled__1[#All],103,0) -> 197.06 | K44: =G44+E44+J44 -> 576.598 | L44: -228.92 | M44: Return | N44: =VLOOKUP(A44,Return!A:L,12,0) -> I did not like the fit | O44: 45937.797
A45: 8700420125 | B45: =VLOOKUP(A45,PG_FORWARD_SETTLED__1[[order_id]:[Customer_Paid]],107,0) -> 3119 | C45: =VLOOKUP(A45,PG_FORWARD_SETTLED__1[[order_id]:[Commission]],108,0) -> 662.476 | D45: =VLOOKUP(A45,PG_FORWARD_SETTLED__1[[#All],[order_id]:[Tax_On_Commission]],109,0) -> 15.859 | E45: =VLOOKUP(A45,PG_FORWARD_SETTLED__1[#All],110,0) -> 71.98 | F45: =VLOOKUP(A45,PG_FORWARD_SETTLED__1[#All],111,0) -> 488.996 | G45: =VLOOKUP(A45,PG_FORWARD_SETTLED__1[#All],112,0) -> 2368.685 | H45: =G45-F45 -> 1879.689 | I45: =B45-G45 -> 750.315 | J45: =VLOOKUP(A45,PG_Reverse_Settled__1[#All],103,0) -> 132.16 | K45: =G45+E45+J45 -> 2572.825 | L45: -204.14 | M45: Return | N45: =VLOOKUP(A45,Return!A:L,12,0) -> I did not like the fit | O45: 45923.447
A46: 8717347910 | B46: =VLOOKUP(A46,PG_FORWARD_SETTLED__1[[order_id]:[Customer_Paid]],107,0) -> 3119 | C46: =VLOOKUP(A46,PG_FORWARD_SETTLED__1[[order_id]:[Commission]],108,0) -> 662.476 | D46: =VLOOKUP(A46,PG_FORWARD_SETTLED__1[[#All],[order_id]:[Tax_On_Commission]],109,0) -> 15.859 | E46: =VLOOKUP(A46,PG_FORWARD_SETTLED__1[#All],110,0) -> 71.98 | F46: =VLOOKUP(A46,PG_FORWARD_SETTLED__1[#All],111,0) -> 488.996 | G46: =VLOOKUP(A46,PG_FORWARD_SETTLED__1[#All],112,0) -> 2368.685 | H46: =G46-F46 -> 1879.689 | I46: =B46-G46 -> 750.315 | J46: =VLOOKUP(A46,PG_Reverse_Settled__1[#All],103,0) -> 197.06 | K46: =G46+E46+J46 -> 2637.725 | L46: -269.04 | M46: Return | N46: =VLOOKUP(A46,Return!A:L,12,0) -> I did not like the fit | O46: 45930.615
A47: 8695924416 | B47: =VLOOKUP(A47,PG_FORWARD_SETTLED__1[[order_id]:[Customer_Paid]],107,0) -> 2244 | C47: =VLOOKUP(A47,PG_FORWARD_SETTLED__1[[order_id]:[Commission]],108,0) -> 582.542 | D47: =VLOOKUP(A47,PG_FORWARD_SETTLED__1[[#All],[order_id]:[Tax_On_Commission]],109,0) -> 12.823 | E47: =VLOOKUP(A47,PG_FORWARD_SETTLED__1[#All],110,0) -> 71.98 | F47: =VLOOKUP(A47,PG_FORWARD_SETTLED__1[#All],111,0) -> 117.546 | G47: =VLOOKUP(A47,PG_FORWARD_SETTLED__1[#All],112,0) -> 1576.655 | H47: =G47-F47 -> 1459.109 | I47: =B47-G47 -> 667.345 | J47: =VLOOKUP(A47,PG_Reverse_Settled__1[#All],103,0) -> 197.06 | K47: =G47+E47+J47 -> 1845.695 | L47: -269.04 | M47: Return | N47: =VLOOKUP(A47,Return!A:L,12,0) -> Received a poor quality product | O47: 45922.443
A48: 8672940065 | B48: =VLOOKUP(A48,PG_FORWARD_SETTLED__1[[order_id]:[Customer_Paid]],107,0) -> 3544 | C48: =VLOOKUP(A48,PG_FORWARD_SETTLED__1[[order_id]:[Commission]],108,0) -> 920.022 | D48: =VLOOKUP(A48,PG_FORWARD_SETTLED__1[[#All],[order_id]:[Tax_On_Commission]],109,0) -> 18.985 | E48: =VLOOKUP(A48,PG_FORWARD_SETTLED__1[#All],110,0) -> 71.98 | F48: =VLOOKUP(A48,PG_FORWARD_SETTLED__1[#All],111,0) -> 395.531 | G48: =VLOOKUP(A48,PG_FORWARD_SETTLED__1[#All],112,0) -> 2533.013 | H48: =G48-F48 -> 2137.482 | I48: =B48-G48 -> 1010.987 | J48: 0 | K48: - | L48: 2533.013 | M48: Completed | O48: 45916.46
A49: 8690064005 | B49: =VLOOKUP(A49,PG_FORWARD_SETTLED__1[[order_id]:[Customer_Paid]],107,0) -> 2719 | C49: =VLOOKUP(A49,PG_FORWARD_SETTLED__1[[order_id]:[Commission]],108,0) -> 705.852 | D49: =VLOOKUP(A49,PG_FORWARD_SETTLED__1[[#All],[order_id]:[Tax_On_Commission]],109,0) -> 13.825 | E49: =VLOOKUP(A49,PG_FORWARD_SETTLED__1[#All],110,0) -> 71.98 | F49: =VLOOKUP(A49,PG_FORWARD_SETTLED__1[#All],111,0) -> 426.281 | G49: =VLOOKUP(A49,PG_FORWARD_SETTLED__1[#All],112,0) -> 1927.343 | H49: =G49-F49 -> 1501.062 | I49: =B49-G49 -> 791.657 | J49: 0 | K49: - | L49: 1927.343 | M49: Completed | O49: 45922.443
A50: 8681830415 | B50: =VLOOKUP(A50,PG_FORWARD_SETTLED__1[[order_id]:[Customer_Paid]],107,0) -> 3544 | C50: =VLOOKUP(A50,PG_FORWARD_SETTLED__1[[order_id]:[Commission]],108,0) -> 920.022 | D50: =VLOOKUP(A50,PG_FORWARD_SETTLED__1[[#All],[order_id]:[Tax_On_Commission]],109,0) -> 18.985 | E50: =VLOOKUP(A50,PG_FORWARD_SETTLED__1[#All],110,0) -> 71.98 | F50: =VLOOKUP(A50,PG_FORWARD_SETTLED__1[#All],111,0) -> 395.531 | G50: =VLOOKUP(A50,PG_FORWARD_SETTLED__1[#All],112,0) -> 2533.013 | H50: =G50-F50 -> 2137.482 | I50: =B50-G50 -> 1010.987 | J50: =VLOOKUP(A50,PG_Reverse_Settled__1[#All],103,0) -> 197.06 | K50: =G50+E50+J50 -> 2802.053 | L50: -269.04 | M50: Return | N50: =VLOOKUP(A50,Return!A:L,12,0) -> - | O50: 45919.434
A51: 8663980354 | B51: =VLOOKUP(A51,PG_FORWARD_SETTLED__1[[order_id]:[Customer_Paid]],107,0) -> 4193.99 | C51: =VLOOKUP(A51,PG_FORWARD_SETTLED__1[[order_id]:[Commission]],108,0) -> 1336.205 | D51: =VLOOKUP(A51,PG_FORWARD_SETTLED__1[[#All],[order_id]:[Tax_On_Commission]],109,0) -> 22.468 | E51: =VLOOKUP(A51,PG_FORWARD_SETTLED__1[#All],110,0) -> 71.98 | F51: =VLOOKUP(A51,PG_FORWARD_SETTLED__1[#All],111,0) -> 468.083 | G51: =VLOOKUP(A51,PG_FORWARD_SETTLED__1[#All],112,0) -> 2763.337 | H51: =G51-F51 -> 2295.254 | I51: =B51-G51 -> 1430.653 | J51: =VLOOKUP(A51,PG_Reverse_Settled__1[#All],103,0) -> 197.06 | K51: =G51+E51+J51 -> 3032.377 | L51: -269.04 | M51: Return | N51: =VLOOKUP(A51,Return!A:L,12,0) -> - | O51: 45912.803
A52: 8737492325 | B52: =VLOOKUP(A52,PG_FORWARD_SETTLED__1[[order_id]:[Customer_Paid]],107,0) -> 3013 | C52: =VLOOKUP(A52,PG_FORWARD_SETTLED__1[[order_id]:[Commission]],108,0) -> 639.961 | D52: =VLOOKUP(A52,PG_FORWARD_SETTLED__1[[#All],[order_id]:[Tax_On_Commission]],109,0) -> 15.32 | E52: =VLOOKUP(A52,PG_FORWARD_SETTLED__1[#All],110,0) -> 71.98 | F52: =VLOOKUP(A52,PG_FORWARD_SETTLED__1[#All],111,0) -> 472.377 | G52: =VLOOKUP(A52,PG_FORWARD_SETTLED__1[#All],112,0) -> 2285.739 | H52: =G52-F52 -> 1813.362 | I52: =B52-G52 -> 727.261 | J52: 0 | K52: - | L52: 2285.739 | M52: Completed | O52: 45936.455
A53: 8683798730 | B53: =VLOOKUP(A53,PG_FORWARD_SETTLED__1[[order_id]:[Customer_Paid]],107,0) -> 2293 | C53: =VLOOKUP(A53,PG_FORWARD_SETTLED__1[[order_id]:[Commission]],108,0) -> 730.55 | D53: =VLOOKUP(A53,PG_FORWARD_SETTLED__1[[#All],[order_id]:[Tax_On_Commission]],109,0) -> 12.283 | E53: =VLOOKUP(A53,PG_FORWARD_SETTLED__1[#All],110,0) -> 71.98 | F53: =VLOOKUP(A53,PG_FORWARD_SETTLED__1[#All],111,0) -> 255.916 | G53: =VLOOKUP(A53,PG_FORWARD_SETTLED__1[#All],112,0) -> 1478.187 | H53: =G53-F53 -> 1222.271 | I53: =B53-G53 -> 814.813 | J53: =VLOOKUP(A53,PG_Reverse_Settled__1[#All],103,0) -> 197.06 | K53: =G53+E53+J53 -> 1747.227 | L53: -269.04 | M53: Return | N53: =VLOOKUP(A53,Return!A:L,12,0) -> - | O53: 45920.474
A54: 8741406110 | B54: =VLOOKUP(A54,PG_FORWARD_SETTLED__1[[order_id]:[Customer_Paid]],107,0) -> 3593.99 | C54: =VLOOKUP(A54,PG_FORWARD_SETTLED__1[[order_id]:[Commission]],108,0) -> 933 | D54: =VLOOKUP(A54,PG_FORWARD_SETTLED__1[[#All],[order_id]:[Tax_On_Commission]],109,0) -> 18.275 | E54: =VLOOKUP(A54,PG_FORWARD_SETTLED__1[#All],110,0) -> 71.98 | F54: =VLOOKUP(A54,PG_FORWARD_SETTLED__1[#All],111,0) -> 563.469 | G54: =VLOOKUP(A54,PG_FORWARD_SETTLED__1[#All],112,0) -> 2570.735 | H54: =G54-F54 -> 2007.266 | I54: =B54-G54 -> 1023.255 | J54: =VLOOKUP(A54,PG_Reverse_Settled__1[#All],103,0) -> 197.06 | K54: =G54+E54+J54 -> 2839.775 | L54: -269.04 | M54: Return | N54: =VLOOKUP(A54,Return!A:L,12,0) -> - | O54: 45938.424
A55: 8714990694 | B55: =VLOOKUP(A55,PG_FORWARD_SETTLED__1[[order_id]:[Customer_Paid]],107,0) -> 2150 | C55: =VLOOKUP(A55,PG_FORWARD_SETTLED__1[[order_id]:[Commission]],108,0) -> 532.77 | D55: =VLOOKUP(A55,PG_FORWARD_SETTLED__1[[#All],[order_id]:[Tax_On_Commission]],109,0) -> 12.286 | E55: =VLOOKUP(A55,PG_FORWARD_SETTLED__1[#All],110,0) -> 71.98 | F55: =VLOOKUP(A55,PG_FORWARD_SETTLED__1[#All],111,0) -> 112.618 | G55: =VLOOKUP(A55,PG_FORWARD_SETTLED__1[#All],112,0) -> 1532.964 | H55: =G55-F55 -> 1420.346 | I55: =B55-G55 -> 617.036 | J55: 0 | K55: - | L55: 1532.964 | M55: Completed | O55: 45929.449
A56: 8670260084 | B56: =VLOOKUP(A56,PG_FORWARD_SETTLED__1[[order_id]:[Customer_Paid]],107,0) -> 3544 | C56: =VLOOKUP(A56,PG_FORWARD_SETTLED__1[[order_id]:[Commission]],108,0) -> 920.022 | D56: =VLOOKUP(A56,PG_FORWARD_SETTLED__1[[#All],[order_id]:[Tax_On_Commission]],109,0) -> 18.985 | E56: =VLOOKUP(A56,PG_FORWARD_SETTLED__1[#All],110,0) -> 71.98 | F56: =VLOOKUP(A56,PG_FORWARD_SETTLED__1[#All],111,0) -> 395.531 | G56: =VLOOKUP(A56,PG_FORWARD_SETTLED__1[#All],112,0) -> 2533.013 | H56: =G56-F56 -> 2137.482 | I56: =B56-G56 -> 1010.987 | J56: =VLOOKUP(A56,PG_Reverse_Settled__1[#All],103,0) -> 197.06 | K56: =G56+E56+J56 -> 2802.053 | L56: -269.04 | M56: Return | N56: =VLOOKUP(A56,Return!A:L,12,0) -> - | O56: 45915.472
A57: 8695941287 | B57: =VLOOKUP(A57,PG_FORWARD_SETTLED__1[[order_id]:[Customer_Paid]],107,0) -> 3564 | C57: =VLOOKUP(A57,PG_FORWARD_SETTLED__1[[order_id]:[Commission]],108,0) -> 883.159 | D57: =VLOOKUP(A57,PG_FORWARD_SETTLED__1[[#All],[order_id]:[Tax_On_Commission]],109,0) -> 18.122 | E57: =VLOOKUP(A57,PG_FORWARD_SETTLED__1[#All],110,0) -> 71.98 | F57: =VLOOKUP(A57,PG_FORWARD_SETTLED__1[#All],111,0) -> 558.762 | G57: =VLOOKUP(A57,PG_FORWARD_SETTLED__1[#All],112,0) -> 2590.739 | H57: =G57-F57 -> 2031.977 | I57: =B57-G57 -> 973.261 | J57: =VLOOKUP(A57,PG_Reverse_Settled__1[#All],103,0) -> 132.16 | K57: =G57+E57+J57 -> 2794.879 | L57: -204.14 | M57: Return | N57: =VLOOKUP(A57,Return!A:L,12,0) -> - | O57: 45922.443
A58: 8739963006 | B58: =VLOOKUP(A58,PG_FORWARD_SETTLED__1[[order_id]:[Customer_Paid]],107,0) -> 2410 | C58: =VLOOKUP(A58,PG_FORWARD_SETTLED__1[[order_id]:[Commission]],108,0) -> 597.198 | D58: =VLOOKUP(A58,PG_FORWARD_SETTLED__1[[#All],[order_id]:[Tax_On_Commission]],109,0) -> 13.771 | E58: =VLOOKUP(A58,PG_FORWARD_SETTLED__1[#All],110,0) -> 71.98 | F58: =VLOOKUP(A58,PG_FORWARD_SETTLED__1[#All],111,0) -> 126.236 | G58: =VLOOKUP(A58,PG_FORWARD_SETTLED__1[#All],112,0) -> 1727.051 | H58: =G58-F58 -> 1600.815 | I58: =B58-G58 -> 682.949 | J58: 0 | K58: - | L58: 1727.051 | M58: Completed | O58: 45937.468
A59: 8728913393 | B59: =VLOOKUP(A59,PG_FORWARD_SETTLED__1[[order_id]:[Customer_Paid]],107,0) -> 1644 | C59: =VLOOKUP(A59,PG_FORWARD_SETTLED__1[[order_id]:[Commission]],108,0) -> 543.178 | D59: =VLOOKUP(A59,PG_FORWARD_SETTLED__1[[#All],[order_id]:[Tax_On_Commission]],109,0) -> 9.395 | E59: =VLOOKUP(A59,PG_FORWARD_SETTLED__1[#All],110,0) -> 53.1 | F59: =VLOOKUP(A59,PG_FORWARD_SETTLED__1[#All],111,0) -> 86.109 | G59: =VLOOKUP(A59,PG_FORWARD_SETTLED__1[#All],112,0) -> 1038.327 | H59: =G59-F59 -> 952.218 | I59: =B59-G59 -> 605.673 | J59: 0 | K59: - | L59: 1038.327 | M59: Completed | O59: 45933.481
A60: 8746617713 | B60: =VLOOKUP(A60,PG_FORWARD_SETTLED__1[[order_id]:[Customer_Paid]],107,0) -> 391 | C60: =VLOOKUP(A60,PG_FORWARD_SETTLED__1[[order_id]:[Commission]],108,0) -> 9.228 | D60: =VLOOKUP(A60,PG_FORWARD_SETTLED__1[[#All],[order_id]:[Tax_On_Commission]],109,0) -> 2.234 | E60: =VLOOKUP(A60,PG_FORWARD_SETTLED__1[#All],110,0) -> 31.86 | F60: =VLOOKUP(A60,PG_FORWARD_SETTLED__1[#All],111,0) -> 20.482 | G60: =VLOOKUP(A60,PG_FORWARD_SETTLED__1[#All],112,0) -> 347.678 | H60: =G60-F60 -> 327.196 | I60: =B60-G60 -> 43.322 | J60: 0 | K60: - | L60: 347.678 | M60: Completed | O60: 45940.808
A61: 8749897675 | B61: =VLOOKUP(A61,PG_FORWARD_SETTLED__1[[order_id]:[Customer_Paid]],107,0) -> 2610 | C61: =VLOOKUP(A61,PG_FORWARD_SETTLED__1[[order_id]:[Commission]],108,0) -> 554.364 | D61: =VLOOKUP(A61,PG_FORWARD_SETTLED__1[[#All],[order_id]:[Tax_On_Commission]],109,0) -> 14.915 | E61: =VLOOKUP(A61,PG_FORWARD_SETTLED__1[#All],110,0) -> 71.98 | F61: =VLOOKUP(A61,PG_FORWARD_SETTLED__1[#All],111,0) -> 136.709 | G61: =VLOOKUP(A61,PG_FORWARD_SETTLED__1[#All],112,0) -> 1968.741 | H61: =G61-F61 -> 1832.032 | I61: =B61-G61 -> 641.259 | J61: 0 | K61: - | L61: 1968.741 | M61: Completed | O61: 45942.467
A62: 8730440748 | B62: =VLOOKUP(A62,PG_FORWARD_SETTLED__1[[order_id]:[Customer_Paid]],107,0) -> 3594 | C62: =VLOOKUP(A62,PG_FORWARD_SETTLED__1[[order_id]:[Commission]],108,0) -> 933.002 | D62: =VLOOKUP(A62,PG_FORWARD_SETTLED__1[[#All],[order_id]:[Tax_On_Commission]],109,0) -> 18.275 | E62: =VLOOKUP(A62,PG_FORWARD_SETTLED__1[#All],110,0) -> 71.98 | F62: =VLOOKUP(A62,PG_FORWARD_SETTLED__1[#All],111,0) -> 563.469 | G62: =VLOOKUP(A62,PG_FORWARD_SETTLED__1[#All],112,0) -> 2570.743 | H62: =G62-F62 -> 2007.274 | I62: =B62-G62 -> 1023.257 | J62: 0 | K62: - | L62: 2570.743 | M62: Completed | O62: 45933.806
A63: 8735756275 | B63: =VLOOKUP(A63,PG_FORWARD_SETTLED__1[[order_id]:[Customer_Paid]],107,0) -> 1064 | C63: =VLOOKUP(A63,PG_FORWARD_SETTLED__1[[order_id]:[Commission]],108,0) -> 288.77 | D63: =VLOOKUP(A63,PG_FORWARD_SETTLED__1[[#All],[order_id]:[Tax_On_Commission]],109,0) -> 6.08 | E63: =VLOOKUP(A63,PG_FORWARD_SETTLED__1[#All],110,0) -> 53.1 | F63: =VLOOKUP(A63,PG_FORWARD_SETTLED__1[#All],111,0) -> 55.737 | G63: =VLOOKUP(A63,PG_FORWARD_SETTLED__1[#All],112,0) -> 716.05 | H63: =G63-F63 -> 660.313 | I63: =B63-G63 -> 347.95 | J63: 0 | K63: - | L63: 716.05 | M63: Completed | O63: 45935.731
A64: 8727960588 | B64: =VLOOKUP(A64,PG_FORWARD_SETTLED__1[[order_id]:[Customer_Paid]],107,0) -> 2432 | C64: =VLOOKUP(A64,PG_FORWARD_SETTLED__1[[order_id]:[Commission]],108,0) -> 516.557 | D64: =VLOOKUP(A64,PG_FORWARD_SETTLED__1[[#All],[order_id]:[Tax_On_Commission]],109,0) -> 13.897 | E64: =VLOOKUP(A64,PG_FORWARD_SETTLED__1[#All],110,0) -> 71.98 | F64: =VLOOKUP(A64,PG_FORWARD_SETTLED__1[#All],111,0) -> 127.391 | G64: =VLOOKUP(A64,PG_FORWARD_SETTLED__1[#All],112,0) -> 1829.566 | H64: =G64-F64 -> 1702.175 | I64: =B64-G64 -> 602.434 | J64: 0 | K64: - | L64: 1829.566 | M64: Completed | O64: 45933.481
A65: 8670314920 | B65: =VLOOKUP(A65,PG_FORWARD_SETTLED__1[[order_id]:[Customer_Paid]],107,0) -> 499 | C65: =VLOOKUP(A65,PG_FORWARD_SETTLED__1[[order_id]:[Commission]],108,0) -> 47.106 | D65: =VLOOKUP(A65,PG_FORWARD_SETTLED__1[[#All],[order_id]:[Tax_On_Commission]],109,0) -> 2.851 | E65: =VLOOKUP(A65,PG_FORWARD_SETTLED__1[#All],110,0) -> 31.86 | F65: =VLOOKUP(A65,PG_FORWARD_SETTLED__1[#All],111,0) -> 26.136 | G65: =VLOOKUP(A65,PG_FORWARD_SETTLED__1[#All],112,0) -> 417.183 | H65: =G65-F65 -> 391.047 | I65: =B65-G65 -> 81.817 | J65: 0 | K65: - | L65: 417.183 | M65: Completed | O65: 45915.472
