Workbook

Sheet PGReconsile
A1: order_id | B1: Customer_Paid | C1: Commission | D1: Logistics | E1: GST_taxes | F1: Myntra_Settlement | G1: Final_Settlement | H1: Difference (what Myntra kept per order) | I1: Charges while Return | J1: Reverse Settlement | K1: Net Settlement | L1: Order_status | M1: PG_status | N1: Date
A2: 8657309311 | B2: 4193.99 | C2: 1336.205 | D2: 71.98 | E2: 468.084 | F2: 2763.337 | G2: =F2-E2 -> 2295.253 | H2: 1430.653 | I2: 0 | J2: - | K2: 2763.337 | L2: Completed | M2: Settled | N2: =VLOOKUP(A2,[1]PGReconsile!$A$1:$E$642,5,0) -> 45909.542
A3: 8622766805 | B3: 2419 | C3: 513.795 | D3: 71.98 | E3: 269.979 | F3: 1820.266 | G3: =F3-E3 -> 1550.287 | H3: 598.734 | I3: 0 | J3: - | K3: 1820.266 | L3: Completed | M3: Settled | N3: =VLOOKUP(A3,[1]PGReconsile!$A$1:$E$642,5,0) -> 45888.476
A4: 8625934871 | B4: 2944 | C4: 764.262 | D4: 71.98 | E4: 328.573 | F4: 2091.986 | G4: =F4-E4 -> 1763.413 | H4: 852.014 | I4: 0 | J4: - | K4: 2091.986 | L4: Completed | M4: Settled | N4: =VLOOKUP(A4,[1]PGReconsile!$A$1:$E$642,5,0) -> 45890.458
A5: 8648874948 | B5: 364 | C5: 34.362 | D5: 31.86 | E5: 19.063 | F5: 295.698 | G5: =F5-E5 -> 276.635 | H5: 68.302 | I5: =VLOOKUP(A5,[1]PGReverse_all!$A$1:$FK$281,167,0) -> 197.06 | J5: =F5+D5+I5 -> 524.618 | K5: -228.92 | L5: Return | M5: Settled | N5: =VLOOKUP(A5,[1]PGReconsile!$A$1:$E$642,5,0) -> 45905.451
A6: 8644779341 | B6: 2794 | C6: 692.353 | D6: 71.98 | E6: 311.833 | F6: 2014.699 | G6: =F6-E6 -> 1702.866 | H6: 779.301 | I6: 0 | J6: - | K6: 2014.699 | L6: Completed | M6: Settled | N6: =VLOOKUP(A6,[1]PGReconsile!$A$1:$E$642,5,0) -> 45902.775
A7: 8592986686 | B7: 2406 | C7: 596.207 | D7: 71.98 | E7: 268.531 | F7: 1724.924 | G7: =F7-E7 -> 1456.393 | H7: 681.076 | I7: 0 | J7: - | K7: 1724.924 | L7: Completed | M7: Settled | N7: =VLOOKUP(A7,[1]PGReconsile!$A$1:$E$642,5,0) -> 45870.45
A8: 8634879839 | B8: 2719 | C8: 673.768 | D8: 71.98 | E8: 303.458 | F8: 1958.686 | G8: =F8-E8 -> 1655.228 | H8: 760.314 | I8: =VLOOKUP(A8,[1]PGReverse_all!$A$1:$FK$281,167,0) -> 197.06 | J8: =F8+D8+I8 -> 2227.726 | K8: -269.04 | L8: Return | M8: Settled | N8: =VLOOKUP(A8,[1]PGReconsile!$A$1:$E$642,5,0) -> 45897.441
A9: 8622910273 | B9: 3994 | C9: 1272.488 | D9: 71.98 | E9: 445.76 | F9: 2628.136 | G9: =F9-E9 -> 2182.376 | H9: 1365.864 | I9: =VLOOKUP(A9,[1]PGReverse_all!$A$1:$FK$281,167,0) -> 197.06 | J9: =F9+D9+I9 -> 2897.176 | K9: -269.04 | L9: Return | M9: Settled | N9: =VLOOKUP(A9,[1]PGReconsile!$A$1:$E$642,5,0) -> 45888.476
A10: 8638525832 | B10: 2643.99 | C10: 561.584 | D10: 71.98 | E10: 295.094 | F10: 1996.262 | G10: =F10-E10 -> 1701.168 | H10: 647.728 | I10: =VLOOKUP(A10,[1]PGReverse_all!$A$1:$FK$281,167,0) -> 197.06 | J10: =F10+D10+I10 -> 2265.302 | K10: -269.04 | L10: Return | M10: Settled | N10: =VLOOKUP(A10,[1]PGReconsile!$A$1:$E$642,5,0) -> 45899.442
A11: 8637560672 | B11: 1794 | C11: 444.553 | D11: 53.1 | E11: 200.219 | F11: 1286.736 | G11: =F11-E11 -> 1086.517 | H11: 507.264 | I11: =VLOOKUP(A11,[1]PGReverse_all!$A$1:$FK$281,167,0) -> 132.16 | J11: =F11+D11+I11 -> 1471.996 | K11: -185.26 | L11: Return | M11: Settled | N11: =VLOOKUP(A11,[1]PGReconsile!$A$1:$E$642,5,0) -> 45898.775
A12: 8631845358 | B12: 3169 | C12: 822.672 | D12: 71.98 | E12: 353.687 | F12: 2257.372 | G12: =F12-E12 -> 1903.685 | H12: 911.628 | I12: 0 | J12: - | K12: 2257.372 | L12: Completed | M12: Settled | N12: =VLOOKUP(A12,[1]PGReconsile!$A$1:$E$642,5,0) -> 45894.453
A13: 8614350224 | B13: 2994 | C13: 635.926 | D13: 71.98 | E13: 334.156 | F13: 2270.055 | G13: =F13-E13 -> 1935.899 | H13: 723.945 | I13: 0 | J13: - | K13: 2270.055 | L13: Completed | M13: Settled | N13: =VLOOKUP(A13,[1]PGReconsile!$A$1:$E$642,5,0) -> 45882.453
A14: 8623704786 | B14: 3294 | C14: 816.253 | D14: 71.98 | E14: 367.635 | F14: 2388.121 | G14: =F14-E14 -> 2020.486 | H14: 905.879 | I14: =VLOOKUP(A14,[1]PGReverse_all!$A$1:$FK$281,167,0) -> 132.16 | J14: =F14+D14+I14 -> 2592.261 | K14: -204.14 | L14: Return | M14: Settled | N14: =VLOOKUP(A14,[1]PGReconsile!$A$1:$E$642,5,0) -> 45888.776
A15: 8616454045 | B15: 3294 | C15: 816.253 | D15: 71.98 | E15: 367.635 | F15: 2388.121 | G15: =F15-E15 -> 2020.486 | H15: 905.879 | I15: =VLOOKUP(A15,[1]PGReverse_all!$A$1:$FK$281,167,0) -> 197.06 | J15: =F15+D15+I15 -> 2657.161 | K15: -269.04 | L15: Return | M15: Settled | N15: =VLOOKUP(A15,[1]PGReconsile!$A$1:$E$642,5,0) -> 45883.528
A16: 8598134488 | B16: 1204 | C16: 298.351 | D16: 53.1 | E16: 134.375 | F16: 846.099 | G16: =F16-E16 -> 711.724 | H16: 357.901 | I16: 0 | J16: - | K16: 846.099 | L16: Completed | M16: Settled | N16: =VLOOKUP(A16,[1]PGReconsile!$A$1:$E$642,5,0) -> 45873.456
A17: 8641487358 | B17: 1704 | C17: 442.358 | D17: 53.1 | E17: 190.177 | F17: 1199.414 | G17: =F17-E17 -> 1009.237 | H17: 504.586 | I17: =VLOOKUP(A17,[1]PGReverse_all!$A$1:$FK$281,167,0) -> 197.06 | J17: =F17+D17+I17 -> 1449.574 | K17: -250.16 | L17: Return | M17: Settled | N17: =VLOOKUP(A17,[1]PGReconsile!$A$1:$E$642,5,0) -> 45901.459
A18: 8623738388 | B18: 3169 | C18: 972.249 | D18: 71.98 | E18: 353.687 | F18: 2107.795 | G18: =F18-E18 -> 1754.108 | H18: 1061.205 | I18: =VLOOKUP(A18,[1]PGReverse_all!$A$1:$FK$281,167,0) -> 197.06 | J18: =F18+D18+I18 -> 2376.835 | K18: -269.04 | L18: Return | M18: Settled | N18: =VLOOKUP(A18,[1]PGReconsile!$A$1:$E$642,5,0) -> 45888.776
A19: 8594147199 | B19: 2343.99 | C19: 608.5 | D19: 71.98 | E19: 261.604 | F19: 1650.953 | G19: =F19-E19 -> 1389.349 | H19: 693.037 | I19: 0 | J19: - | K19: 1650.953 | L19: Completed | M19: Settled | N19: =VLOOKUP(A19,[1]PGReconsile!$A$1:$E$642,5,0) -> 45871.441
A20: 8631135329 | B20: 3294 | C20: 816.253 | D20: 71.98 | E20: 367.635 | F20: 2388.121 | G20: =F20-E20 -> 2020.486 | H20: 905.879 | I20: 0 | J20: - | K20: 2388.121 | L20: Completed | M20: Settled | N20: =VLOOKUP(A20,[1]PGReconsile!$A$1:$E$642,5,0) -> 45894.453
A21: 8614451899 | B21: 2044.01 | C21: 506.506 | D21: 71.98 | E21: 228.125 | F21: 1454.574 | G21: =F21-E21 -> 1226.449 | H21: 589.436 | I21: =VLOOKUP(A21,[1]PGReverse_all!$A$1:$FK$281,167,0) -> 197.06 | J21: =F21+D21+I21 -> 1723.614 | K21: -269.04 | L21: Return | M21: Settled | N21: =VLOOKUP(A21,[1]PGReconsile!$A$1:$E$642,5,0) -> 45882.453
A22: 8631283767 | B22: 3674 | C22: 1127.183 | D22: 71.98 | E22: 410.042 | F22: 2455.155 | G22: =F22-E22 -> 2045.113 | H22: 1218.845 | I22: 0 | J22: - | K22: 2455.155 | L22: Completed | M22: Settled | N22: =VLOOKUP(A22,[1]PGReconsile!$A$1:$E$642,5,0) -> 45894.453
A23: 8619882203 | B23: 2156 | C23: 457.934 | D23: 71.98 | E23: 240.625 | F23: 1614.536 | G23: =F23-E23 -> 1373.911 | H23: 541.464 | I23: 0 | J23: - | K23: 1614.536 | L23: Completed | M23: Settled | N23: =VLOOKUP(A23,[1]PGReconsile!$A$1:$E$642,5,0) -> 45888.476
A24: 8657350152 | B24: 1994 | C24: 541.172 | D24: 53.1 | E24: 222.542 | F24: 1389.046 | G24: =F24-E24 -> 1166.504 | H24: 604.954 | I24: =VLOOKUP(A24,[1]PGReverse_all!$A$1:$FK$281,167,0) -> 107.38 | J24: =F24+D24+I24 -> 1549.526 | K24: -160.48 | L24: Return | M24: Settled | N24: =VLOOKUP(A24,[1]PGReconsile!$A$1:$E$642,5,0) -> 45909.542
A25: 8655198144 | B25: 3594 | C25: 890.593 | D25: 71.98 | E25: 401.115 | F25: 2612.173 | G25: =F25-E25 -> 2211.058 | H25: 981.827 | I25: =VLOOKUP(A25,[1]PGReverse_all!$A$1:$FK$281,167,0) -> 132.16 | J25: =F25+D25+I25 -> 2816.313 | K25: -204.14 | L25: Return | M25: Settled | N25: =VLOOKUP(A25,[1]PGReconsile!$A$1:$E$642,5,0) -> 45908.483
A26: 8647972516 | B26: 3194 | C26: 791.473 | D26: 71.98 | E26: 356.469 | F26: 2313.436 | G26: =F26-E26 -> 1956.967 | H26: 880.564 | I26: =VLOOKUP(A26,[1]PGReverse_all!$A$1:$FK$281,167,0) -> 197.06 | J26: =F26+D26+I26 -> 2582.476 | K26: -269.04 | L26: Return | M26: Settled | N26: =VLOOKUP(A26,[1]PGReconsile!$A$1:$E$642,5,0) -> 45904.487
A27: 8643095523 | B27: 3544 | C27: 920.022 | D27: 71.98 | E27: 395.531 | F27: 2533.013 | G27: =F27-E27 -> 2137.482 | H27: 1010.987 | I27: 0 | J27: - | K27: 2533.013 | L27: Completed | M27: Settled | N27: =VLOOKUP(A27,[1]PGReconsile!$A$1:$E$642,5,0) -> 45902.449
A28: 8643991542 | B28: 2644.01 | C28: 561.588 | D28: 71.98 | E28: 295.094 | F28: 1996.277 | G28: =F28-E28 -> 1701.183 | H28: 647.733 | I28: =VLOOKUP(A28,[1]PGReverse_all!$A$1:$FK$281,167,0) -> 132.16 | J28: =F28+D28+I28 -> 2200.417 | K28: -204.14 | L28: Return | M28: Settled | N28: =VLOOKUP(A28,[1]PGReconsile!$A$1:$E$642,5,0) -> 45902.449
A29: 8647294613 | B29: 1079 | C29: 267.376 | D29: 53.1 | E29: 120.417 | F29: 752.744 | G29: =F29-E29 -> 632.327 | H29: 326.256 | I29: 0 | J29: - | K29: 752.744 | L29: Completed | M29: Settled | N29: =VLOOKUP(A29,[1]PGReconsile!$A$1:$E$642,5,0) -> 45904.487
A30: 8642965420 | B30: 2556 | C30: 633.377 | D30: 71.98 | E30: 285.271 | F30: 1836.95 | G30: =F30-E30 -> 1551.679 | H30: 719.05 | I30: 0 | J30: - | K30: 1836.95 | L30: Completed | M30: Settled | N30: =VLOOKUP(A30,[1]PGReconsile!$A$1:$E$642,5,0) -> 45902.449
A31: 8640366432 | B31: 2981 | C31: 738.692 | D31: 71.98 | E31: 332.698 | F31: 2154.358 | G31: =F31-E31 -> 1821.66 | H31: 826.642 | I31: =VLOOKUP(A31,[1]PGReverse_all!$A$1:$FK$281,167,0) -> 197.06 | J31: =F31+D31+I31 -> 2423.398 | K31: -269.04 | L31: Return | M31: Settled | N31: =VLOOKUP(A31,[1]PGReconsile!$A$1:$E$642,5,0) -> 45900.694
A32: 8633233419 | B32: 2981 | C32: 738.692 | D32: 71.98 | E32: 332.698 | F32: 2154.358 | G32: =F32-E32 -> 1821.66 | H32: 826.642 | I32: 0 | J32: - | K32: 2154.358 | L32: Completed | M32: Settled | N32: =VLOOKUP(A32,[1]PGReconsile!$A$1:$E$642,5,0) -> 45895.447
A33: 8634212307 | B33: 1516 | C33: 339.887 | D33: 53.1 | E33: 169.198 | F33: 1114.891 | G33: =F33-E33 -> 945.693 | H33: 401.109 | I33: 0 | J33: - | K33: 1114.891 | L33: Completed | M33: Settled | N33: =VLOOKUP(A33,[1]PGReconsile!$A$1:$E$642,5,0) -> 45895.787
A34: 8620217140 | B34: 5006 | C34: 1535.841 | D34: 71.98 | E34: 558.708 | F34: 3371.361 | G34: =F34-E34 -> 2812.653 | H34: 1634.639 | I34: =VLOOKUP(A34,[1]PGReverse_all!$A$1:$FK$281,167,0) -> 197.06 | J34: =F34+D34+I34 -> 3640.401 | K34: -269.04 | L34: Return | M34: Settled | N34: =VLOOKUP(A34,[1]PGReconsile!$A$1:$E$642,5,0) -> 45887.453
A35: 8626237350 | B35: 3294 | C35: 816.253 | D35: 71.98 | E35: 367.635 | F35: 2388.121 | G35: =F35-E35 -> 2020.486 | H35: 905.879 | I35: 0 | J35: - | K35: 2388.121 | L35: Completed | M35: Settled | N35: =VLOOKUP(A35,[1]PGReconsile!$A$1:$E$642,5,0) -> 45890.656
A36: 8615334100 | B36: 954 | C36: 258.916 | D36: 31.86 | E36: 49.973 | F36: 657.772 | G36: =F36-E36 -> 607.799 | H36: 296.228 | I36: 0 | J36: - | K36: 657.772 | L36: Completed | M36: Settled | N36: =VLOOKUP(A36,[1]PGReconsile!$A$1:$E$642,5,0) -> 45882.769
A37: 8608720011 | B37: 2944 | C37: 729.523 | D37: 71.98 | E37: 328.573 | F37: 2126.725 | G37: =F37-E37 -> 1798.152 | H37: 817.275 | I37: 0 | J37: - | K37: 2126.725 | L37: Completed | M37: Settled | N37: =VLOOKUP(A37,[1]PGReconsile!$A$1:$E$642,5,0) -> 45878.695
A38: 8616771946 | B38: 4293.99 | C38: 1317.396 | D38: 71.98 | E38: 479.239 | F38: 2881.611 | G38: =F38-E38 -> 2402.372 | H38: 1412.379 | I38: =VLOOKUP(A38,[1]PGReverse_all!$A$1:$FK$281,167,0) -> 197.06 | J38: =F38+D38+I38 -> 3150.651 | K38: -269.04 | L38: Return | M38: Settled | N38: =VLOOKUP(A38,[1]PGReconsile!$A$1:$E$642,5,0) -> 45883.797
A39: 8640582446 | B39: 2831 | C39: 734.928 | D39: 71.98 | E39: 315.958 | F39: 2008.926 | G39: =F39-E39 -> 1692.968 | H39: 822.074 | I39: =VLOOKUP(A39,[1]PGReverse_all!$A$1:$FK$281,167,0) -> 197.06 | J39: =F39+D39+I39 -> 2277.966 | K39: -269.04 | L39: Return | M39: Settled | N39: =VLOOKUP(A39,[1]PGReconsile!$A$1:$E$642,5,0) -> 45900.694
A40: 8617707567 | B40: 2786 | C40: 591.746 | D40: 71.98 | E40: 310.938 | F40: 2107.348 | G40: =F40-E40 -> 1796.41 | H40: 678.652 | I40: 0 | J40: - | K40: 2107.348 | L40: Completed | M40: Settled | N40: =VLOOKUP(A40,[1]PGReconsile!$A$1:$E$642,5,0) -> 45885.463
A41: 8601398846 | B41: 2131 | C41: 553.208 | D41: 71.98 | E41: 237.833 | F41: 1494.396 | G41: =F41-E41 -> 1256.563 | H41: 636.604 | I41: 0 | J41: - | K41: 1494.396 | L41: Completed | M41: Settled | N41: =VLOOKUP(A41,[1]PGReconsile!$A$1:$E$642,5,0) -> 45874.465
A42: 8655513263 | B42: 3294 | C42: 1049.468 | D42: 71.98 | E42: 367.636 | F42: 2154.905 | G42: =F42-E42 -> 1787.269 | H42: 1139.095 | I42: =VLOOKUP(A42,[1]PGReverse_all!$A$1:$FK$281,167,0) -> 197.06 | J42: =F42+D42+I42 -> 2423.945 | K42: -269.04 | L42: Return | M42: Settled | N42: =VLOOKUP(A42,[1]PGReconsile!$A$1:$E$642,5,0) -> 45908.483
A43: 8618679840 | B43: 3169 | C43: 822.672 | D43: 71.98 | E43: 353.687 | F43: 2257.372 | G43: =F43-E43 -> 1903.685 | H43: 911.628 | I43: =VLOOKUP(A43,[1]PGReverse_all!$A$1:$FK$281,167,0) -> 107.38 | J43: =F43+D43+I43 -> 2436.732 | K43: -179.36 | L43: Return | M43: Settled | N43: =VLOOKUP(A43,[1]PGReconsile!$A$1:$E$642,5,0) -> 45885.463
A44: 8618164100 | B44: 2994 | C44: 635.926 | D44: 71.98 | E44: 334.146 | F44: 2270.055 | G44: =F44-E44 -> 1935.909 | H44: 723.945 | I44: 0 | J44: - | K44: 2270.055 | L44: Completed | M44: Settled | N44: =VLOOKUP(A44,[1]PGReconsile!$A$1:$E$642,5,0) -> 45885.463
A45: 8611927891 | B45: 2131 | C45: 553.208 | D45: 71.98 | E45: 237.833 | F45: 1494.396 | G45: =F45-E45 -> 1256.563 | H45: 636.604 | I45: 0 | J45: - | K45: 1494.396 | L45: Completed | M45: Settled | N45: =VLOOKUP(A45,[1]PGReconsile!$A$1:$E$642,5,0) -> 45880.557
A46: 8633660254 | B46: 2981 | C46: 738.692 | D46: 71.98 | E46: 332.698 | F46: 2154.358 | G46: =F46-E46 -> 1821.66 | H46: 826.642 | I46: 0 | J46: - | K46: 2154.358 | L46: Completed | M46: Settled | N46: =VLOOKUP(A46,[1]PGReconsile!$A$1:$E$642,5,0) -> 45895.447
A47: 8620040747 | B47: 2606 | C47: 553.514 | D47: 71.98 | E47: 290.844 | F47: 1966.545 | G47: =F47-E47 -> 1675.701 | H47: 639.455 | I47: =VLOOKUP(A47,[1]PGReverse_all!$A$1:$FK$281,167,0) -> 132.16 | J47: =F47+D47+I47 -> 2170.685 | K47: -204.14 | L47: Return | M47: Settled | N47: =VLOOKUP(A47,[1]PGReconsile!$A$1:$E$642,5,0) -> 45887.453
A48: 8631868697 | B48: 2244 | C48: 476.626 | D48: 71.98 | E48: 250.448 | F48: 1683.372 | G48: =F48-E48 -> 1432.924 | H48: 560.628 | I48: 0 | J48: - | K48: 1683.372 | L48: Completed | M48: Settled | N48: =VLOOKUP(A48,[1]PGReconsile!$A$1:$E$642,5,0) -> 45894.453
A49: 8636986750 | B49: 2769 | C49: 588.136 | D49: 71.98 | E49: 309.042 | F49: 2094.05 | G49: =F49-E49 -> 1785.008 | H49: 674.95 | I49: =VLOOKUP(A49,[1]PGReverse_all!$A$1:$FK$281,167,0) -> 197.06 | J49: =F49+D49+I49 -> 2363.09 | K49: -269.04 | L49: Return | M49: Settled | N49: =VLOOKUP(A49,[1]PGReconsile!$A$1:$E$642,5,0) -> 45898.445
A50: 8634176784 | B50: 966 | C50: 227.976 | D50: 31.86 | E50: 50.6 | F50: 700.644 | G50: =F50-E50 -> 650.044 | H50: 265.356 | I50: =VLOOKUP(A50,[1]PGReverse_all!$A$1:$FK$281,167,0) -> 132.16 | J50: =F50+D50+I50 -> 864.664 | K50: -164.02 | L50: Return | M50: Settled | N50: =VLOOKUP(A50,[1]PGReconsile!$A$1:$E$642,5,0) -> 45895.787
A51: 8611806865 | B51: 4593.99 | C51: 1301.018 | D51: 71.98 | E51: 512.719 | F51: 3196.381 | G51: =F51-E51 -> 2683.662 | H51: 1397.609 | I51: =VLOOKUP(A51,[1]PGReverse_all!$A$1:$FK$281,167,0) -> 197.06 | J51: =F51+D51+I51 -> 3465.421 | K51: -269.04 | L51: Return | M51: Settled | N51: =VLOOKUP(A51,[1]PGReconsile!$A$1:$E$642,5,0) -> 45880.465
A52: 8657935085 | B52: 2943.99 | C52: 729.52 | D52: 71.98 | E52: 328.573 | F52: 2126.718 | G52: =F52-E52 -> 1798.145 | H52: 817.272 | I52: =VLOOKUP(A52,[1]PGReverse_all!$A$1:$FK$281,167,0) -> 132.16 | J52: =F52+D52+I52 -> 2330.858 | K52: -204.14 | L52: Return | M52: Settled | N52: =VLOOKUP(A52,[1]PGReconsile!$A$1:$E$642,5,0) -> 45910.46
A53: 8656288035 | B53: 2994 | C53: 777.242 | D53: 71.98 | E53: 334.156 | F53: 2128.739 | G53: =F53-E53 -> 1794.583 | H53: 865.261 | I53: =VLOOKUP(A53,[1]PGReverse_all!$A$1:$FK$281,167,0) -> 132.16 | J53: =F53+D53+I53 -> 2332.879 | K53: -204.14 | L53: Return | M53: Settled | N53: =VLOOKUP(A53,[1]PGReconsile!$A$1:$E$642,5,0) -> 45908.788
A54: 8629466445 | B54: 3544 | C54: 920.022 | D54: 71.98 | E54: 395.531 | F54: 2533.013 | G54: =F54-E54 -> 2137.482 | H54: 1010.987 | I54: =VLOOKUP(A54,[1]PGReverse_all!$A$1:$FK$281,167,0) -> 197.06 | J54: =F54+D54+I54 -> 2802.053 | K54: -269.04 | L54: Return | M54: Settled | N54: =VLOOKUP(A54,[1]PGReconsile!$A$1:$E$642,5,0) -> 45892.433
A55: 8620719877 | B55: 3394 | C55: 841.033 | D55: 71.98 | E55: 378.792 | F55: 2462.804 | G55: =F55-E55 -> 2084.012 | H55: 931.196 | I55: 0 | J55: - | K55: 2462.804 | L55: Completed | M55: Settled | N55: =VLOOKUP(A55,[1]PGReconsile!$A$1:$E$642,5,0) -> 45887.453
A56: 8612040958 | B56: 3544 | C56: 920.022 | D56: 71.98 | E56: 395.531 | F56: 2533.013 | G56: =F56-E56 -> 2137.482 | H56: 1010.987 | I56: =VLOOKUP(A56,[1]PGReverse_all!$A$1:$FK$281,167,0) -> 197.06 | J56: =F56+D56+I56 -> 2802.053 | K56: -269.04 | L56: Return | M56: Settled | N56: =VLOOKUP(A56,[1]PGReconsile!$A$1:$E$642,5,0) -> 45880.773
A57: 8623066496 | B57: 2594 | C57: 550.966 | D57: 71.98 | E57: 289.5 | F57: 1957.158 | G57: =F57-E57 -> 1667.658 | H57: 636.842 | I57: 0 | J57: - | K57: 1957.158 | L57: Completed | M57: Settled | N57: =VLOOKUP(A57,[1]PGReconsile!$A$1:$E$642,5,0) -> 45888.476
A58: 8655144624 | B58: 2794 | C58: 593.446 | D58: 71.98 | E58: 311.833 | F58: 2113.606 | G58: =F58-E58 -> 1801.773 | H58: 680.394 | I58: 0 | J58: - | K58: 2113.606 | L58: Completed | M58: Settled | N58: =VLOOKUP(A58,[1]PGReconsile!$A$1:$E$642,5,0) -> 45908.483
A59: 8639002063 | B59: 2194 | C59: 466.006 | D59: 71.98 | E59: 244.865 | F59: 1644.26 | G59: =F59-E59 -> 1399.395 | H59: 549.74 | I59: =VLOOKUP(A59,[1]PGReverse_all!$A$1:$FK$281,167,0) -> 197.06 | J59: =F59+D59+I59 -> 1913.3 | K59: -269.04 | L59: Return | M59: Settled | N59: =VLOOKUP(A59,[1]PGReconsile!$A$1:$E$642,5,0) -> 45899.764
A60: 8649996593 | B60: 2594 | C60: 550.966 | D60: 71.98 | E60: 289.5 | F60: 1957.158 | G60: =F60-E60 -> 1667.658 | H60: 636.842 | I60: 0 | J60: - | K60: 1957.158 | L60: Completed | M60: Settled | N60: =VLOOKUP(A60,[1]PGReconsile!$A$1:$E$642,5,0) -> 45905.806
A61: 8634757737 | B61: 3194 | C61: 791.473 | D61: 71.98 | E61: 356.479 | F61: 2313.436 | G61: =F61-E61 -> 1956.957 | H61: 880.564 | I61: =VLOOKUP(A61,[1]PGReverse_all!$A$1:$FK$281,167,0) -> 107.38 | J61: =F61+D61+I61 -> 2492.796 | K61: -179.36 | L61: Return | M61: Settled | N61: =VLOOKUP(A61,[1]PGReconsile!$A$1:$E$642,5,0) -> 45897.441
A62: 8644200717 | B62: 4594 | C62: 1409.439 | D62: 71.98 | E62: 512.719 | F62: 3087.97 | G62: =F62-E62 -> 2575.251 | H62: 1506.03 | I62: =VLOOKUP(A62,[1]PGReverse_all!$A$1:$FK$281,167,0) -> 197.06 | J62: =F62+D62+I62 -> 3357.01 | K62: -269.04 | L62: Return | M62: Settled | N62: =VLOOKUP(A62,[1]PGReconsile!$A$1:$E$642,5,0) -> 45902.56
A63: 8637941448 | B63: 3544 | C63: 920.022 | D63: 71.98 | E63: 395.531 | F63: 2533.013 | G63: =F63-E63 -> 2137.482 | H63: 1010.987 | I63: 0 | J63: - | K63: 2533.013 | L63: Completed | M63: Settled | N63: =VLOOKUP(A63,[1]PGReconsile!$A$1:$E$642,5,0) -> 45898.803
A64: 8615512711 | B64: 2419 | C64: 513.796 | D64: 71.98 | E64: 269.979 | F64: 1820.265 | G64: =F64-E64 -> 1550.286 | H64: 598.735 | I64: 0 | J64: - | K64: 1820.265 | L64: Completed | M64: Settled | N64: =VLOOKUP(A64,[1]PGReconsile!$A$1:$E$642,5,0) -> 45888.476
A65: 8654231853 | B65: 2194 | C65: 466.006 | D65: 71.98 | E65: 244.865 | F65: 1644.26 | G65: =F65-E65 -> 1399.395 | H65: 549.74 | I65: 0 | J65: - | K65: 1644.26 | L65: Completed | M65: Settled | N65: =VLOOKUP(A65,[1]PGReconsile!$A$1:$E$642,5,0) -> 45908.483
A66: 8629059218 | B66: 3169 | C66: 822.672 | D66: 71.98 | E66: 353.687 | F66: 2257.372 | G66: =F66-E66 -> 1903.685 | H66: 911.628 | I66: =VLOOKUP(A66,[1]PGReverse_all!$A$1:$FK$281,167,0) -> 197.06 | J66: =F66+D66+I66 -> 2526.412 | K66: -269.04 | L66: Return | M66: Settled | N66: =VLOOKUP(A66,[1]PGReconsile!$A$1:$E$642,5,0) -> 45892.433
A67: 8642596173 | B67: 3644 | C67: 1117.979 | D67: 71.98 | E67: 406.688 | F67: 2434.519 | G67: =F67-E67 -> 2027.831 | H67: 1209.481 | I67: =VLOOKUP(A67,[1]PGReverse_all!$A$1:$FK$281,167,0) -> 107.38 | J67: =F67+D67+I67 -> 2613.879 | K67: -179.36 | L67: Return | M67: Settled | N67: =VLOOKUP(A67,[1]PGReconsile!$A$1:$E$642,5,0) -> 45901.785
A68: 8641095253 | B68: 3994 | C68: 1272.488 | D68: 71.98 | E68: 445.76 | F68: 2628.136 | G68: =F68-E68 -> 2182.376 | H68: 1365.864 | I68: =VLOOKUP(A68,[1]PGReverse_all!$A$1:$FK$281,167,0) -> 197.06 | J68: =F68+D68+I68 -> 2897.176 | K68: -269.04 | L68: Return | M68: Settled | N68: =VLOOKUP(A68,[1]PGReconsile!$A$1:$E$642,5,0) -> 45901.459
A69: 8664266778 | B69: 2994 | C69: 741.913 | D69: 71.98 | E69: 334.156 | F69: 2164.068 | G69: =F69-E69 -> 1829.912 | H69: 829.932 | I69: 0 | J69: - | K69: 2164.068 | L69: Completed | M69: Settled | N69: =VLOOKUP(A69,[1]PGReconsile!$A$1:$E$642,5,0) -> 45913.451
A70: 8661941772 | B70: 2993.99 | C70: 741.911 | D70: 71.98 | E70: 334.156 | F70: 2164.06 | G70: =F70-E70 -> 1829.904 | H70: 829.93 | I70: 0 | J70: - | K70: 2164.06 | L70: Completed | M70: Settled | N70: =VLOOKUP(A70,[1]PGReconsile!$A$1:$E$642,5,0) -> 45912.476
A71: 8622529723 | B71: 3294 | C71: 816.253 | D71: 71.98 | E71: 367.635 | F71: 2388.121 | G71: =F71-E71 -> 2020.486 | H71: 905.879 | I71: =VLOOKUP(A71,[1]PGReverse_all!$A$1:$FK$281,167,0) -> 132.16 | J71: =F71+D71+I71 -> 2592.261 | K71: -204.14 | L71: Return | M71: Settled | N71: =VLOOKUP(A71,[1]PGReconsile!$A$1:$E$642,5,0) -> 45888.476
A72: 8614858318 | B72: 3844 | C72: 952.543 | D72: 71.98 | E72: 429.021 | F72: 2798.884 | G72: =F72-E72 -> 2369.863 | H72: 1045.116 | I72: 0 | J72: - | K72: 2798.884 | L72: Completed | M72: Settled | N72: =VLOOKUP(A72,[1]PGReconsile!$A$1:$E$642,5,0) -> 45882.456
A73: 8655672020 | B73: 2169 | C73: 537.478 | D73: 71.98 | E73: 242.073 | F73: 1547.922 | G73: =F73-E73 -> 1305.849 | H73: 621.078 | I73: =VLOOKUP(A73,[1]PGReverse_all!$A$1:$FK$281,167,0) -> 132.16 | J73: =F73+D73+I73 -> 1752.062 | K73: -204.14 | L73: Return | M73: Settled | N73: =VLOOKUP(A73,[1]PGReconsile!$A$1:$E$642,5,0) -> 45908.483
A74: 8630979515 | B74: 2821 | C74: 599.18 | D74: 71.98 | E74: 314.844 | F74: 2134.727 | G74: =F74-E74 -> 1819.883 | H74: 686.273 | I74: 0 | J74: - | K74: 2134.727 | L74: Completed | M74: Settled | N74: =VLOOKUP(A74,[1]PGReconsile!$A$1:$E$642,5,0) -> 45894.453
A75: 8653894535 | B75: 2994 | C75: 741.913 | D75: 71.98 | E75: 334.156 | F75: 2164.068 | G75: =F75-E75 -> 1829.912 | H75: 829.932 | I75: 0 | J75: - | K75: 2164.068 | L75: Completed | M75: Settled | N75: =VLOOKUP(A75,[1]PGReconsile!$A$1:$E$642,5,0) -> 45908.483
A76: 8662493509 | B76: 2794 | C76: 593.446 | D76: 71.98 | E76: 311.833 | F76: 2113.606 | G76: =F76-E76 -> 1801.773 | H76: 680.394 | I76: 0 | J76: - | K76: 2113.606 | L76: Completed | M76: Settled | N76: =VLOOKUP(A76,[1]PGReconsile!$A$1:$E$642,5,0) -> 45912.476
A77: 8631067091 | B77: 1794 | C77: 529.23 | D77: 53.1 | E77: 200.219 | F77: 1202.059 | G77: =F77-E77 -> 1001.84 | H77: 591.941 | I77: 0 | J77: - | K77: 1202.059 | L77: Completed | M77: Settled | N77: =VLOOKUP(A77,[1]PGReconsile!$A$1:$E$642,5,0) -> 45894.453
A78: 8619859831 | B78: 2044 | C78: 651.218 | D78: 71.98 | E78: 228.125 | F78: 1309.852 | G78: =F78-E78 -> 1081.727 | H78: 734.148 | I78: 0 | J78: - | K78: 1309.852 | L78: Completed | M78: Settled | N78: =VLOOKUP(A78,[1]PGReconsile!$A$1:$E$642,5,0) -> 45888.476
A79: 8611998481 | B79: 2944 | C79: 729.523 | D79: 71.98 | E79: 328.573 | F79: 2126.725 | G79: =F79-E79 -> 1798.152 | H79: 817.275 | I79: 0 | J79: - | K79: 2126.725 | L79: Completed | M79: Settled | N79: =VLOOKUP(A79,[1]PGReconsile!$A$1:$E$642,5,0) -> 45880.557
A80: 8639804045 | B80: 3543.98 | C80: 920.017 | D80: 71.98 | E80: 395.531 | F80: 2532.998 | G80: =F80-E80 -> 2137.467 | H80: 1010.982 | I80: =VLOOKUP(A80,[1]PGReverse_all!$A$1:$FK$281,167,0) -> 197.06 | J80: =F80+D80+I80 -> 2802.038 | K80: -269.04 | L80: Return | M80: Settled | N80: =VLOOKUP(A80,[1]PGReconsile!$A$1:$E$642,5,0) -> 45900.458
A81: 8612636944 | B81: 1793.99 | C81: 444.551 | D81: 53.1 | E81: 200.219 | F81: 1286.728 | G81: =F81-E81 -> 1086.509 | H81: 507.262 | I81: =VLOOKUP(A81,[1]PGReverse_all!$A$1:$FK$281,167,0) -> 132.16 | J81: =F81+D81+I81 -> 1471.988 | K81: -185.26 | L81: Return | M81: Settled | N81: =VLOOKUP(A81,[1]PGReconsile!$A$1:$E$642,5,0) -> 45881.472
A82: 8613217978 | B82: 2344 | C82: 580.843 | D82: 71.98 | E82: 261.604 | F82: 1678.62 | G82: =F82-E82 -> 1417.016 | H82: 665.38 | I82: 0 | J82: - | K82: 1678.62 | L82: Completed | M82: Settled | N82: =VLOOKUP(A82,[1]PGReconsile!$A$1:$E$642,5,0) -> 45881.472
A83: 8649618848 | B83: 3643.98 | C83: 1160.972 | D83: 71.98 | E83: 406.698 | F83: 2391.506 | G83: =F83-E83 -> 1984.808 | H83: 1252.474 | I83: 0 | J83: - | K83: 2391.506 | L83: Completed | M83: Settled | N83: =VLOOKUP(A83,[1]PGReconsile!$A$1:$E$642,5,0) -> 45905.451
A84: 8625454150 | B84: 3294 | C84: 1049.468 | D84: 71.98 | E84: 367.625 | F84: 2154.906 | G84: =F84-E84 -> 1787.281 | H84: 1139.094 | I84: =VLOOKUP(A84,[1]PGReverse_all!$A$1:$FK$281,167,0) -> 197.06 | J84: =F84+D84+I84 -> 2423.946 | K84: -269.04 | L84: Return | M84: Settled | N84: =VLOOKUP(A84,[1]PGReconsile!$A$1:$E$642,5,0) -> 45890.458
A85: 8648759873 | B85: 2556 | C85: 633.377 | D85: 71.98 | E85: 285.271 | F85: 1836.95 | G85: =F85-E85 -> 1551.679 | H85: 719.05 | I85: 0 | J85: - | K85: 1836.95 | L85: Completed | M85: Settled | N85: =VLOOKUP(A85,[1]PGReconsile!$A$1:$E$642,5,0) -> 45905.451
A86: 8612316631 | B86: 2069 | C86: 659.183 | D86: 71.98 | E86: 230.917 | F86: 1326.753 | G86: =F86-E86 -> 1095.836 | H86: 742.247 | I86: =VLOOKUP(A86,[1]PGReverse_all!$A$1:$FK$281,167,0) -> 197.06 | J86: =F86+D86+I86 -> 1595.793 | K86: -269.04 | L86: Return | M86: Settled | N86: =VLOOKUP(A86,[1]PGReconsile!$A$1:$E$642,5,0) -> 45880.773
A87: 8595142933 | B87: 2156.01 | C87: 457.936 | D87: 71.98 | E87: 240.625 | F87: 1614.544 | G87: =F87-E87 -> 1373.919 | H87: 541.466 | I87: 0 | J87: - | K87: 1614.544 | L87: Completed | M87: Settled | N87: =VLOOKUP(A87,[1]PGReconsile!$A$1:$E$642,5,0) -> 45871.441
A88: 8634561172 | B88: 1999 | C88: 448.176 | D88: 53.1 | E88: 223.104 | F88: 1487.015 | G88: =F88-E88 -> 1263.911 | H88: 511.985 | I88: =VLOOKUP(A88,[1]PGReverse_all!$A$1:$FK$281,167,0) -> 197.06 | J88: =F88+D88+I88 -> 1737.175 | K88: -250.16 | L88: Return | M88: Settled | N88: =VLOOKUP(A88,[1]PGReconsile!$A$1:$E$642,5,0) -> 45897.441
A89: 8634169145 | B89: 2769 | C89: 686.158 | D89: 71.98 | E89: 309.042 | F89: 1996.028 | G89: =F89-E89 -> 1686.986 | H89: 772.972 | I89: =VLOOKUP(A89,[1]PGReverse_all!$A$1:$FK$281,167,0) -> 197.06 | J89: =F89+D89+I89 -> 2265.068 | K89: -269.04 | L89: Return | M89: Settled | N89: =VLOOKUP(A89,[1]PGReconsile!$A$1:$E$642,5,0) -> 45895.787
A90: 8612775582 | B90: 4294 | C90: 1317.399 | D90: 71.98 | E90: 479.24 | F90: 2881.617 | G90: =F90-E90 -> 2402.377 | H90: 1412.383 | I90: =VLOOKUP(A90,[1]PGReverse_all!$A$1:$FK$281,167,0) -> 197.06 | J90: =F90+D90+I90 -> 3150.657 | K90: -269.04 | L90: Return | M90: Settled | N90: =VLOOKUP(A90,[1]PGReconsile!$A$1:$E$642,5,0) -> 45881.472
A91: 8624894778 | B91: 3194 | C91: 791.473 | D91: 71.98 | E91: 356.479 | F91: 2313.436 | G91: =F91-E91 -> 1956.957 | H91: 880.564 | I91: 0 | J91: - | K91: 2313.436 | L91: Completed | M91: Settled | N91: =VLOOKUP(A91,[1]PGReconsile!$A$1:$E$642,5,0) -> 45889.781
A92: 8615334101 | B92: 954 | C92: 258.916 | D92: 31.86 | E92: 49.973 | F92: 657.772 | G92: =F92-E92 -> 607.799 | H92: 296.228 | I92: =VLOOKUP(A92,[1]PGReverse_all!$A$1:$FK$281,167,0) -> 197.06 | J92: =F92+D92+I92 -> 886.692 | K92: -228.92 | L92: Return | M92: Settled | N92: =VLOOKUP(A92,[1]PGReconsile!$A$1:$E$642,5,0) -> 45882.769
A93: 8632189753 | B93: 2089 | C93: 542.304 | D93: 71.98 | E93: 233.146 | F93: 1463.525 | G93: =F93-E93 -> 1230.379 | H93: 625.475 | I93: 0 | J93: - | K93: 1463.525 | L93: Completed | M93: Settled | N93: =VLOOKUP(A93,[1]PGReconsile!$A$1:$E$642,5,0) -> 45894.453
A94: 8637715863 | B94: 3644 | C94: 1117.979 | D94: 71.98 | E94: 406.698 | F94: 2434.519 | G94: =F94-E94 -> 2027.821 | H94: 1209.481 | I94: =VLOOKUP(A94,[1]PGReverse_all!$A$1:$FK$281,167,0) -> 197.06 | J94: =F94+D94+I94 -> 2703.559 | K94: -269.04 | L94: Return | M94: Settled | N94: =VLOOKUP(A94,[1]PGReconsile!$A$1:$E$642,5,0) -> 45898.775
A95: 8655940273 | B95: 2994 | C95: 741.913 | D95: 71.98 | E95: 334.156 | F95: 2164.068 | G95: =F95-E95 -> 1829.912 | H95: 829.932 | I95: 0 | J95: - | K95: 2164.068 | L95: Completed | M95: Settled | N95: =VLOOKUP(A95,[1]PGReconsile!$A$1:$E$642,5,0) -> 45908.558
A96: 8633269027 | B96: 3644 | C96: 1117.979 | D96: 71.98 | E96: 406.698 | F96: 2434.519 | G96: =F96-E96 -> 2027.821 | H96: 1209.481 | I96: 0 | J96: - | K96: 2434.519 | L96: Completed | M96: Settled | N96: =VLOOKUP(A96,[1]PGReconsile!$A$1:$E$642,5,0) -> 45895.447
A97: 8659789290 | B97: 2194 | C97: 466.006 | D97: 71.98 | E97: 244.865 | F97: 1644.26 | G97: =F97-E97 -> 1399.395 | H97: 549.74 | I97: =VLOOKUP(A97,[1]PGReverse_all!$A$1:$FK$281,167,0) -> 197.06 | J97: =F97+D97+I97 -> 1913.3 | K97: -269.04 | L97: Return | M97: Settled | N97: =VLOOKUP(A97,[1]PGReconsile!$A$1:$E$642,5,0) -> 45911.459
A98: 8605655495 | B98: 1516 | C98: 500.886 | D98: 53.1 | E98: 169.198 | F98: 953.892 | G98: =F98-E98 -> 784.694 | H98: 562.108 | I98: 0 | J98: - | K98: 953.892 | L98: Completed | M98: Settled | N98: =VLOOKUP(A98,[1]PGReconsile!$A$1:$E$642,5,0) -> 45876.792
A99: 8635882443 | B99: 2981 | C99: 738.692 | D99: 71.98 | E99: 332.698 | F99: 2154.358 | G99: =F99-E99 -> 1821.66 | H99: 826.642 | I99: 0 | J99: - | K99: 2154.358 | L99: Completed | M99: Settled | N99: =VLOOKUP(A99,[1]PGReconsile!$A$1:$E$642,5,0) -> 45897.441
A100: 8646141428 | B100: 1994 | C100: 541.172 | D100: 53.1 | E100: 222.542 | F100: 1389.046 | G100: =F100-E100 -> 1166.504 | H100: 604.954 | I100: 0 | J100: - | K100: 1389.046 | L100: Completed | M100: Settled | N100: =VLOOKUP(A100,[1]PGReconsile!$A$1:$E$642,5,0) -> 45903.563
...

Sheet Insights
A1: BUSINESS INSIGHTS
A3: Summary | E3: Explaination:
A4: KPI | B4: Value | C4: Description | E4: Reverse Settlement = The amount Myntra takes back from your account when an order is returned.
A5: 💰 Total Sales (Overall) | B5: =B6+B7 -> 1691254.5 | C5: Total value customers paid | E5: This includes:
A6: Total Sales (Completed Orders) | B6: =SUMIF(PGReconsile!L1:L642,"Completed",PGReconsile!B1:B642) -> 948289.7 | C6: Total value customers paid for completed orders | E6: Refund to customer
A7: 📦Total Returns (Returned Orders) | B7: =SUMIF(PGReconsile!L1:L642,"Return",PGReconsile!B1:B642) -> 742964.83 | C7: Value of returned orders | E7: Forward logistics
A8: 🧾Total Commission | B8: =SUMIF(PGReconsile!L1:L642,"Completed",PGReconsile!C1:C642) -> 239885.22 | C8: Total Myntra commission on completed orders | E8: Return logistics
A9: 🚚Total Logistics | B9: =B10+B11 -> 89164.033 | C9: Total Shipping cost
A10: Total Logistics (Forward) | B10: =SUM(PGReconsile!D2:D642) -> 43008.333 | C10: Delivery cost
A11: Total Logistics (Return) | B11: =SUM(PGReconsile!I2:I642) -> 46155.7 | C11: Reverse shipping cost
A12: Total GST Taxes | B12: =SUMIF(PGReconsile!L1:L642,"Completed",PGReconsile!E1:E642) -> 108367.17 | C12: Tax deduction amount
A13: Total Settlement (Completed Orders) | B13: =SUMIF(PGReconsile!L1:L642,"Completed",PGReconsile!G1:G642) -> 570113.7 | C13: What Myntra paid you for completed orders
A14: 📉Reverse Settlement (Returned Orders) | B14: =SUMIF(PGReconsile!L1:L642,"Return",PGReconsile!J1:J642) -> 591962.39 | C14: Amount Myntra took back (includes return & forward logistics)
A15: 📈Net Settlement (All Orders) | B15: =SUM(PGReconsile!K2:K642) -> 614175.59 | C15: Actual amount credited or debited overall
A16: Return Rate (%) | B16: =B7/B5 -> 0.43929806 | C16: How much of your sale value got returned
A17: Profit % (Approx.) | B17: =B15/B5 -> 0.36314794 | C17: Overall business efficiency (real take-home %)
A19: Cost Breakdown Table
A20: Metric | B20: Completed | C20: Return | D20: Total | E20: Net Effect
A21: Customer Paid | B21: =SUMIF(PGReconsile!L1:L642,"Completed",PGReconsile!B1:B642) -> 948289.7 | C21: =SUMIF(PGReconsile!L1:L642,"Return",PGReconsile!B1:B642) -> 742964.83 | D21: =B21+C21 -> 1691254.5 | E21: =B21-C21 -> 205324.87
A22: Commission | B22: =SUMIF(PGReconsile!L1:L642,"Completed",PGReconsile!C1:C642) -> 239885.22 | C22: =SUMIF(PGReconsile!L1:L642,"Return",PGReconsile!C1:C642) -> 193181 | D22: =B22+C22 -> 433066.22 | E22: =B22-C22 -> 46704.218
A23: Logistics | B23: =SUMIF(PGReconsile!L1:L642,"Completed",PGReconsile!D1:D642) -> 24858.753 | C23: 64305.28 | D23: =B23+C23 -> 89164.033 | E23: =B23-C23 -> -39446.527
A24: GST | B24: =SUMIF(PGReconsile!L1:L642,"Completed",PGReconsile!E1:E642) -> 108367.17 | C24: =SUMIF(PGReconsile!L1:L642,"Return",PGReconsile!E1:E642) -> 84292.63 | D24: =B24+C24 -> 192659.8 | E24: =B24-C24 -> 24074.54
A25: Myntra Settlement | B25: =SUMIF(PGReconsile!L1:L642,"Completed",PGReconsile!G1:G642) -> 570113.7 | C25: =SUMIF(PGReconsile!L1:L642,"Return",PGReconsile!G1:G642) -> 443364.48 | D25: =B25+C25 -> 1013478.2 | E25: =B25-C25 -> 126749.22
A26: Reverse Settlement | B26: =SUMIF(PGReconsile!L1:L642,"Completed",PGReconsile!J1:J642) -> 0 | C26: =SUMIF(PGReconsile!L1:L642,"Return",PGReconsile!J1:J642) -> 591962.39 | D26: =B26+C26 -> 591962.39 | E26: =B26-C26 -> -591962.39
A27: Net Business Impact | B27: =SUMIF(PGReconsile!L1:L642,"Completed",PGReconsile!K1:K642) -> 678480.87 | C27: =SUMIF(PGReconsile!L1:L642,"Return",PGReconsile!K1:K642) -> -64305.28 | D27: =B27+C27 -> 614175.59 | E27: =B27-C27 -> 742786.15
A30: 🧾 Business Summary
A31: Total Sales = ₹16.91 Lakh
A32: Return Value = ₹7.42 Lakh
A33: Reverse Settlement = ₹5.91 Lakh
A34: Final Net Settlement = ₹6.14 Lakh
A35: ⚠️ Since reverse settlement already includes both forward and return logistics, returns directly reduce your profit.
A36: In simple words: Every return means you lose the order’s earnings plus you pay both-way logistics.
A1048560: Item | B1048560: Amount | D1048560: Row Labels | E1048560: Sum of Net Settlement
A1048561: Customer Paid | B1048561: =VLOOKUP(A1048561,A20:D27,4,0) -> 1691254.5 | D1048561: Mar | E1048561: 2290.2008
A1048562: Commission | B1048562: =VLOOKUP(A1048562,A21:D28,4,0) -> 433066.22 | D1048562: Aug | E1048562: 237712.05
A1048563: Logistics | B1048563: =VLOOKUP(A1048563,A22:D28,4,0) -> 89164.033 | D1048563: Sep | E1048563: 374173.34
A1048564: GST | B1048564: =VLOOKUP(A1048564,A23:D29,4,0) -> 192659.8 | D1048564: Grand Total | E1048564: 614175.59
A1048565: Reverse Settlement | B1048565: =VLOOKUP(A1048565,A24:D30,4,0) -> 591962.39
A1048566: Net Business Impact | B1048566: =VLOOKUP(A1048566,A25:D31,4,0) -> 614175.59

Sheet Outcome & Recommendations
A1: SUGGESTIONS
A2: 📊 BUSINESS OUTCOME & RECOMMENDATIONS (Based on Insights Data)
A4: Section | B4: Detail | C4: Explanation (Simple Terms)
A5: 💰 Total Customer Payments (Overall Sales) | B5: 1691254.5 | C5: Total amount paid by all customers.
A6: 📦 Returned Orders (Refunded) | B6: 742964.83 | C6: Value of products returned and refunded to customers.
A7: ✅ Completed Orders (Delivered) | B7: 948289.7 | C7: Actual sales that stayed with the customer.
A8: 🧾 Total Commission (Platform Fee) | B8: 239885.22 | C8: Myntra’s commission deduction on all sales.
A9: 🚚 Total Logistics (Forward + Return) | B9: 89164.03 | C9: Forward: 43,008.33, Return: 46,155.70
A10: 💸 Effective Business Retention Rate | B10: ≈ 56 % | C10: Seller keeps only ₹56 for every ₹100 sold after deductions.
A11: ⚠️ High Return Rate | B11: ≈ 44 % | C11: Nearly half the total sales were returned → huge impact on profit.
A12: 🧮 Key Loss Factors | B12: Returns + Reverse Logistics + Commission | C12: These 3 together eat away almost 40 % of total revenue.
A13: 🟢 Current Situation Summary | C13: Sales volume is good, but profit is reduced because of high return cost and platform fees.
A16: 🧭 WHAT THE BUSINESS SHOULD DO NEXT
A18: Focus Area | B18: Issue / Reason | C18: Action to Take | D18: Expected Impact
A19: 🔁 Reduce Returns | B19: High refund & double logistics loss | C19: Improve product info, sizing, and QC; limit free returns on low-margin items | D19: 5–10 % more profit if returns fall by even 10 %
A20: 🚚 Control Logistics Cost | B20: Paying both forward & reverse freight | C20: Negotiate cheaper reverse rates or use lighter packaging | D20: 3–5 % cost reduction
A21: 💼 Optimize Commission | B21: 14 % fee + GST adds up | C21: Check lower-fee category programs / reclaim GST inputs | D21: 2–3 % higher margin
A22: 📊 Track Settlement Efficiency | B22: Only 56 % of revenue retained | C22: Add monthly KPI → (Net Settlement ÷ Total Sales) × 100 | D22: Target ≥ 70 %
A23: 💰 Cash-Flow Buffer | B23: Reverse settlements deducted later | C23: Keep small reserve for refund claw-backs | D23: Smooth cash management
A26: Summary:
A27: The business generated ₹16.9 L in total sales, but after returns and deductions, only ₹9.48 L was realized.
A28: Returns (₹7.4 L) and reverse-logistics costs are the main reasons for low profitability.
A29: Current efficiency stands at ≈ 56 %, meaning the seller keeps ₹56 per ₹100 sold.
A30: By reducing returns and negotiating costs, profitability can improve by 15–20 %.

Sheet Completed
A1: order_id | B1: Customer_Paid | C1: Commission | D1: Logistics | E1: GST_taxes | F1: Myntra_Settlement | G1: Final_settlement | H1: Difference (what Myntra kept per order) | I1: PG_status
A2: 8657309311 | B2: 4193.99 | C2: 1336.205 | D2: 71.98 | E2: 468.084 | F2: 2763.337 | G2: 2295.253 | H2: 1430.653 | I2: Settled
A3: 8622766805 | B3: 2419 | C3: 513.795 | D3: 71.98 | E3: 269.979 | F3: 1820.266 | G3: 1550.287 | H3: 598.734 | I3: Settled
A4: 8625934871 | B4: 2944 | C4: 764.262 | D4: 71.98 | E4: 328.573 | F4: 2091.986 | G4: 1763.413 | H4: 852.014 | I4: Settled
A5: 8644779341 | B5: 2794 | C5: 692.353 | D5: 71.98 | E5: 311.833 | F5: 2014.699 | G5: 1702.866 | H5: 779.301 | I5: Settled
A6: 8592986686 | B6: 2406 | C6: 596.207 | D6: 71.98 | E6: 268.531 | F6: 1724.924 | G6: 1456.393 | H6: 681.076 | I6: Settled
A7: 8631845358 | B7: 3169 | C7: 822.672 | D7: 71.98 | E7: 353.687 | F7: 2257.372 | G7: 1903.685 | H7: 911.628 | I7: Settled
A8: 8614350224 | B8: 2994 | C8: 635.926 | D8: 71.98 | E8: 334.156 | F8: 2270.055 | G8: 1935.899 | H8: 723.945 | I8: Settled
A9: 8598134488 | B9: 1204 | C9: 298.351 | D9: 53.1 | E9: 134.375 | F9: 846.099 | G9: 711.724 | H9: 357.901 | I9: Settled
A10: 8594147199 | B10: 2343.99 | C10: 608.5 | D10: 71.98 | E10: 261.604 | F10: 1650.953 | G10: 1389.349 | H10: 693.037 | I10: Settled
A11: 8631135329 | B11: 3294 | C11: 816.253 | D11: 71.98 | E11: 367.635 | F11: 2388.121 | G11: 2020.486 | H11: 905.879 | I11: Settled
A12: 8631283767 | B12: 3674 | C12: 1127.183 | D12: 71.98 | E12: 410.042 | F12: 2455.155 | G12: 2045.113 | H12: 1218.845 | I12: Settled
A13: 8619882203 | B13: 2156 | C13: 457.934 | D13: 71.98 | E13: 240.625 | F13: 1614.536 | G13: 1373.911 | H13: 541.464 | I13: Settled
... A373: 8690064005 | B373: 2719 | C373: 705.852 | D373: 71.98 | E373: 426.281 | F373: 1927.343 | G373: 1501.062 | H373: 791.657 | I373: Pending

Sheet Return
A1: order_release_id | B1: customer_paid_amt | C1: Commission | D1: Logistics | E1: myntra_settlement | F1: return_logistics | G1: Reverse settlement | H1: Net Settlement
A2: 8620217140 | B2: 5212 | C2: 1562.659 | D2: 71.98 | E2: 3371.361 | F2: 197.06 | G2: 3640.401 | H2: =E2-G2 -> -269.04
A3: 8647172312 | B3: 4800 | C3: 1325.632 | D3: 71.98 | E3: 3196.388 | F3: 197.06 | G3: 3465.428 | H3: =E3-G3 -> -269.04
A4: 8629832600 | B4: 4800 | C4: 1434.05 | D4: 71.98 | E4: 3087.97 | F4: 132.16 | G4: 3292.11 | H4: =E4-G4 -> -204.14
A5: 8613771637 | B5: 4800 | C5: 1325.632 | D5: 71.98 | E5: 3196.388 | F5: 197.06 | G5: 3465.428 | H5: =E5-G5 -> -269.04
A6: 8611806865 | B6: 4800 | C6: 1325.637 | D6: 71.98 | E6: 3196.403 | F6: 197.06 | G6: 3465.443 | H6: =E6-G6 -> -269.04
A7: 8644200717 | B7: 4800 | C7: 1434.05 | D7: 71.98 | E7: 3087.97 | F7: 197.06 | G7: 3357.01 | H7: =E7-G7 -> -269.04
A8: 8632082388 | B8: 4800 | C8: 1325.632 | D8: 71.98 | E8: 3196.388 | F8: 197.06 | G8: 3465.428 | H8: =E8-G8 -> -269.04
A9: 8643967266 | B9: 4800 | C9: 1325.632 | D9: 71.98 | E9: 3196.388 | F9: 132.16 | G9: 3400.528 | H9: =E9-G9 -> -204.14
A10: 8637117652 | B10: 4785 | C10: 1159.206 | D10: 71.98 | E10: 3347.814 | F10: 197.06 | G10: 3616.854 | H10: =E10-G10 -> -269.04
A11: 8612739940 | B11: 4750 | C11: 1150.346 | D11: 71.98 | E11: 3321.674 | F11: 197.06 | G11: 3590.714 | H11: =E11-G11 -> -269.04
A12: 8690365732 | B12: 4750 | C12: 1149.106 | D12: 71.98 | E12: 3322.904 | F12: 197.06 | G12: 3591.944 | H12: =E12-G12 -> -269.04
A13: 8612775582 | B13: 4500 | C13: 1340.403 | D13: 71.98 | E13: 2881.617 | F13: 197.06 | G13: 3150.657 | H13: =E13-G13 -> -269.04
... A281: 8628691316 | B281: 209 | C281: 18.557 | D281: 31.86 | E281: 99.583 | F281: 132.16 | G281: 263.603 | H281: =E281-G281 -> -164.02
H282: =SUM(H2:H281) -> -66759.68
